Workbook

Sheet boq- 271225
S4: Birthday | T4: 31st Jan
A6: Date : | B6: 45991 | E6: Project Code :
A7: Client Name : | B7: Rahul Dhanawat | E7: Quotation Revision : | F7: 0
A8: Address : | B8: 10BKC | E8: Elemantra Contact Person : | F8: Payal- 93724 07848
A10: Quotation Summary | F10: SR.NO | G10: Description | H10: Amount
B11: Area in Sqft | D11: 1673 | F11: 1 | G11: Loose furniture | H11: =K249 -> 460000
A12: SR.NO | B12: Description | D12: Amount | F12: 2 | G12: Additional items | H12: =L266 -> 2875600
A13: 1 | B13: Civil | D13: =N46 -> 1126050 | F13: 3 | G13: Additional items -2 | H13: =N276 -> 244500
A14: 2 | B14: Plumbing | D14: =N52 -> 180000 | G14: Total B | H14: =SUM(H11:H13) -> 3580100
A15: 3 | B15: Electrical | D15: =N55 -> 585550 | F15: Total A+B | H15: =D21+H11+H12+H13 -> 13807554
A16: 4 | B16: POP | D16: =N62 -> 442500 | F16: GST 18% extra
A17: 5 | B17: Carpentry | D17: =N163 -> 6224875
A18: 6 | B18: Painting | D18: =N169 -> 978478.5
A19: 7 | B19: Miscellenious | D19: =K174 -> 190000
A20: 8 | B20: Design Consultation Fees(10%) | D20: 500000
B21: Total A | D21: =SUM(D13:D20) -> 10227454
B22: Per Sqft Rate | D22: =(D21/D11) -> 6113.2418
A24: Sr.No | B24: Id | C24: Item Name | D24: Category | E24: Item Details | F24: Description | G24: UOM | H24: Elemantra Rates | J24: Quantity 14.03.2025 | K24: Amount | L24: Area | M24: Difference Amount | N24: Amount | O24: RA - 1 - WORK % | P24: RA - 1 - WORK %- AMOUNT | Q24: Location | R24: Remark | S24: MAHESH LOOSE ITEMS | T24: DEEPAK MODULAR | U24: ON SITE CARPENTRY | V24: CNC MEHTA
A25: Civil
A26: 1 | C26: Demolition | D26: walls | E26: NA | F26: Demolition | G26: sq.ft | H26: 250 | J26: =H26-(H26*16.622%) -> 208.445 | K26: 40 | L26: =3+3+7*9+100 -> 169 | M26: Entire kitchen this includes below platform as well since wwe are changing verticles it will get damage . | N26: =L26*H26 -> 42250 | O26: 1 | P26: =O26*N26 -> 42250 | Q26: servent ,samar & master bathroom door shifting | R26: keeping 100 sq.ft extra
A27: 2 | C27: civil | D27: walls | E27: NA | F27: Making | G27: sq.ft | H27: 350 | J27: - | K27: - | L27: =6*9 -> 54 | M27: Kitchen Window &door frame | N27: =L27*H27 -> 18900 | O27: 1 | P27: =O27*N27 -> 18900 | Q27: samar & master bathroom wall sfifting
A28: 3 | C28: civil | D28: kitchen platform | E28: NA | F28: includes marble verticals, base marble, moulding , cutting etc , also includes floor bedding with marble | G28: sq.ft | H28: 3000 | L28: 25 | N28: =L28*H28 -> 75000 | O28: 1 | P28: =O28*N28 -> 75000 | Q28: kitchen platform
A29: 4 | C29: civil | D29: utility platform | E29: NA | F29: includes marble verticals, base marble, moulding , cutting etc , also includes floor bedding with marble | G29: sq.ft | H29: 3000 | L29: 9 | N29: =L29*H29 -> 27000 | O29: 1 | P29: =O29*N29 -> 27000 | Q29: utility platform
A30: 5 | C30: civil | D30: Bathroom Tile | E30: 4x2 tile | F30: Laying of Wall tiles of approved colour and size as per drawing, over 20 mm thick cement mortar 1 : 4 ( 1 cement : 4 coarse sand ) and jointed with white cement slurry admixed with matching pigment to match the shade of tile & Grouting and spacer to be included. | G30: sq.ft | H30: 150 | L30: 936 | N30: =L30*H30 -> 140400 | O30: 1 | P30: =O30*N30 -> 140400 | Q30: 4 Bathroom Tile
A31: 6 | C31: civil | D31: Plaster | F31: Providing and laying 12-25 mm thick cement plaster of mis 1 : 4 (1 cement : 4 sand with 50% coarse sand & 50% fine sand) to all type of RCC / brick surface in line, level and plumb including providing wiremesh at all junctions of walls and ceilings etc. complete. | G31: sq.ft | H31: 125 | L31: 936 | N31: =L31*H31 -> 117000 | O31: 1 | P31: =O31*N31 -> 117000 | Q31: 4 Bathroom Tile
A32: 7 | C32: civil | D32: bathroom window frame | E32: single patti | F32: Granite Frame – up to 6 Inches width {Including Bevelling+ Cutting+ Polishing}. Excludes Granite cost | G32: sq.ft | H32: 450 | L32: =10*4+18+18+12+50 -> 138 | N32: =L32*H32 -> 62100 | O32: 1 | P32: =O32*N32 -> 62100 | Q32: 4 bathroom window and 1 kitchen window and 1 show unit window
A33: 8 | C33: civil | D33: brickbat | F33: =VLOOKUP($B33,'Rate card'!$A$4:$G285,5,FALSE) -> 0 | G33: sq.ft | H33: 200 | L33: =40*4 -> 160 | N33: =L33*H33 -> 32000 | O33: 1 | P33: =O33*N33 -> 32000 | Q33: 4 bathroom floor
A34: 9 | C34: civil | D34: waterproffing | E34: 2 cote | G34: sq.ft | H34: 250 | L34: =L33 -> 160 | N34: =L34*H34 -> 40000 | O34: 1 | P34: =O34*N34 -> 40000 | Q34: 4 bathroom floor
A35: 10 | C35: civil | D35: Bathroom floor tile | F35: Laying of Wall tiles of approved colour and size as per drawing, over 20 mm thick cement mortar 1 : 4 ( 1 cement : 4 coarse sand ) and jointed with white cement slurry admixed with matching pigment to match the shade of tile & Grouting and spacer to be included. | G35: sq.ft | H35: 150 | L35: =L34 -> 160 | N35: =L35*H35 -> 24000 | O35: 1 | P35: =O35*N35 -> 24000 | Q35: 4 bathroom floor
A36: 11 | C36: civil | D36: vanity counter | G36: ls | H36: 8000 | L36: 4 | N36: =L36*H36 -> 32000 | P36: =O36*N36 -> 0
A37: 12 | C37: civil | D37: ledge | G37: la | H37: 5000 | L37: 4 | N37: =L37*H37 -> 20000 | O37: 1 | P37: =O37*N37 -> 20000
A38: 13 | N38: =L38*H38 -> 0 | P38: =O38*N38 -> 0
A39: 14 | C39: civil | D39: plain tile | G39: sq.ft | H39: 120 | L39: 350 | N39: =L39*H39 -> 42000 | O39: 1 | P39: =O39*N39 -> 42000 | Q39: tile behid utility and below platform
A40: 15 | C40: civil | D40: marble wardrobe in utility area | G40: sq.ft | H40: 950 | L40: =12*8.5 -> 102 | N40: =L40*H40 -> 96900 | P40: =O40*N40 -> 0 | Q40: marble wardrobe in utility area | R40: shutters are not included
A41: 16 | C41: civil | G41: sq.ft | H41: 300 | L41: 150 | N41: =L41*H41 -> 45000 | O41: 1 | P41: =O41*N41 -> 45000
A42: 17 | C42: civil | D42: Marble Polish | G42: Sq.ft | H42: 85 | L42: 2500 | N42: =L42*H42 -> 212500 | P42: =O42*N42 -> 0
A43: 18 | C43: civil | D43: Niche | H43: 5000 | L43: 5 | N43: =L43*H43 -> 25000 | O43: 1 | P43: =O43*N43 -> 25000
A44: 19 | C44: civil | D44: Ledge | G44: Rft | H44: 2000 | L44: 15 | N44: =L44*H44 -> 30000 | O44: 1 | P44: =O44*N44 -> 30000
A45: 20 | C45: civil | D45: Bathroom dooe frame | G45: rft | H45: 550 | L45: =20*4 -> 80 | N45: =L45*H45 -> 44000 | P45: =O45*N45 -> 0 | R45: ?
L46: Total | N46: =SUM(N26:N45) -> 1126050 | P46: =SUM(P26:P45) -> 740650 | Q46: =P46/N46 -> 0.65774166
A47: Plumbing
A48: 1 | B48: PL 2 | C48: Plumbing | D48: Bathroom Plumbing | E48: CP fitting work 1 Basin +cp fittings+Ceiling shower | F48: cp fiting and sanitary ware fixing in a bathroom | G48: per bathroom | H48: 35000 | J48: 1 | K48: =H48*J48 -> 35000 | L48: 1 | M48: =L48-K48 -> -34999 | N48: =L48*H48 -> 35000 | O48: 0.85 | P48: =O48*N48 -> 29750 | Q48: Samar's toilet
A49: 2 | B49: PL 2 | C49: Plumbing | D49: Bathroom Plumbing | E49: Ceiling shower+body jets+c.p fittings | F49: cp fiting and sanitary ware fixing in a bathroom | G49: per bathroom | H49: 45000 | J49: 1 | K49: =H49*J49 -> 45000 | L49: 2 | M49: =L49-K49 -> -44998 | N49: =L49*H49 -> 90000 | O49: 0.85 | P49: =O49*N49 -> 76500 | Q49: Master & Ranbeer
A50: 3 | B50: PL 2 | C50: Plumbing | D50: Bathroom Plumbing | E50: CP fitting work 1 Basin +cp fittings+Ceiling shower | F50: cp fiting and sanitary ware fixing in a bathroom | G50: per bathroom | H50: 35000 | J50: 1 | K50: =K48 -> 35000 | L50: 1 | M50: =L50-K50 -> -34999 | N50: =L50*H50 -> 35000 | O50: 0.85 | P50: =O50*N50 -> 29750 | Q50: Mother's toilet
A51: 4 | B51: PL 3 | C51: =VLOOKUP($B51,'Rate card'!$A$4:$G285,2,FALSE) -> Plumbing | D51: =VLOOKUP($B51,'Rate card'!$A$4:$G285,3,FALSE) -> Kitchen Plumbing | E51: 3 sink+dishwahser+washing machine | F51: =VLOOKUP($B51,'Rate card'!$A$4:$G285,5,FALSE) -> all plumbing concealed wall and floor CPVC and UPVC pipes and chipping and replastering work | G51: =VLOOKUP($B51,'Rate card'!$A$4:$G285,6,FALSE) -> per kitchen | H51: 20000 | J51: 1 | K51: =H51*J51 -> 20000 | L51: 1 | M51: =L51-K51 -> -19999 | N51: =L51*H51 -> 20000 | O51: 0.85 | P51: =O51*N51 -> 17000 | Q51: Kitchen & Utility
J52: Total | K52: =SUM(K48:K51) -> 135000 | L52: Total | M52: =sum(M48:M51) -> -134995 | N52: =SUM(N48:N51) -> 180000 | P52: =SUM(P48:P51) -> 153000
A53: Electrical
A54: 1 | B54: E 1 | C54: Electrical | D54: 5A Switch socket, Light points,AC point, Fan point, Circuit wiring, DB Dressing | E54: new 5A Switch & Socket, light points, 15A, AC point, fan point from DB on wall include the price for wire and conduits, chipping and replastering on wall is included | F54: NOTE - The rates include fixingof switch / socket in position, effecting proper connections testing and commissioning of lighting fixtures and fans including lamps, control gear, power factor improvement capacitor and all fixing accessories that may be required to check. | G54: All areas | H54: 350 | J54: 1673 | K54: =H54*J54 -> 585550 | L54: 1673 | M54: =L54-K54 -> -583877 | N54: =L54*H54 -> 585550 | O54: 0.75 | P54: =O54*N54 -> 439162.5 | Q54: All areas
J55: Total | K55: =SUM(K54) -> 585550 | L55: TOTAL | N55: =SUM(N54) -> 585550 | P55: =SUM(P54) -> 439162.5
A56: Pop/Falsceiling
A57: 1 | B57: FC 3 | C57: =VLOOKUP($B57,'Rate card'!$A$4:$G285,2,FALSE) -> False Ceiling | D57: =VLOOKUP($B57,'Rate card'!$A$4:$G285,3,FALSE) -> Gypsum Board Ceiling | E57: =VLOOKUP($B57,'Rate card'!$A$4:$G285,4,FALSE) -> Saint Gobain/Gyproc Board + local A Grade channel | F57: =VLOOKUP($B57,'Rate card'!$A$4:$G285,5,FALSE) -> 12.5mm thick gypsum board, with local A Grade Channel including all material, labour, transportation etc | Ceiling Channel and Intermediate Channel at 900mm c/c & Ceiling Section at 450mm c/c | G57: =VLOOKUP($B57,'Rate card'!$A$4:$G285,6,FALSE) -> Sqft | H57: 120 | J57: 1447 | K57: =H57*J57 -> 173640 | L57: 1450 | M57: =L57-K57 -> -172190 | N57: =L57*H57 -> 174000 | O57: 0.95 | P57: =O57*N57 -> 165300 | Q57: All areas
A58: 2 | B58: FC 4 | C58: =VLOOKUP($B58,'Rate card'!$A$4:$G285,2,FALSE) -> False Ceiling | D58: =VLOOKUP($B58,'Rate card'!$A$4:$G285,3,FALSE) -> Gypsum Board Cove | E58: =VLOOKUP($B58,'Rate card'!$A$4:$G285,4,FALSE) -> Gypsum cove | F58: =VLOOKUP($B58,'Rate card'!$A$4:$G285,5,FALSE) -> 12.5mm thick gypsum board, with local A Grade Channel including all material, labour, transportation etc | Ceiling Channel and Intermediate Channel at 900mm c/c & Ceiling Section at 450mm c/c | G58: =VLOOKUP($B58,'Rate card'!$A$4:$G285,6,FALSE) -> Rft | H58: 120 | J58: 800 | K58: =H58*J58 -> 96000 | L58: 800 | M58: =L58-K58 -> -95200 | N58: =L58*H58 -> 96000 | O58: 0.85 | P58: =O58*N58 -> 81600 | Q58: All areas
A59: 3 | B59: FC 5 | C59: =VLOOKUP($B59,'Rate card'!$A$4:$G285,2,FALSE) -> False Ceiling | D59: =VLOOKUP($B59,'Rate card'!$A$4:$G285,3,FALSE) -> Hilux Board ceiling | E59: =VLOOKUP($B59,'Rate card'!$A$4:$G285,4,FALSE) -> Hilux Board + local A Grade channel | F59: =VLOOKUP($B59,'Rate card'!$A$4:$G285,5,FALSE) -> 8mm Ramco hilux board, with local A Grade Channel including all material, labour, transportation etc | Ceiling Channel and Intermediate Channel at 900mm c/c & Ceiling Section at 450mm c/c | G59: =VLOOKUP($B59,'Rate card'!$A$4:$G285,6,FALSE) -> Sqft | H59: 200 | J59: 226 | K59: =H59*J59 -> 45200 | L59: 200 | M59: =L59-K59 -> -45000 | N59: =L59*H59 -> 40000 | O59: 0.3 | P59: =O59*N59 -> 12000 | Q59: Toilets
A60: 4 | B60: FC 11 | C60: =VLOOKUP($B60,'Rate card'!$A$4:$G285,2,FALSE) -> POP | D60: =VLOOKUP($B60,'Rate card'!$A$4:$G285,3,FALSE) -> POP Punning | E60: =VLOOKUP($B60,'Rate card'!$A$4:$G285,4,FALSE) -> POP Punning (Plum) 12-25mm thick | F60: =VLOOKUP($B60,'Rate card'!$A$4:$G285,5,FALSE) -> Providing and applying 12-25 mm thick POP punning on wall /ceiling including scrapping and hacking the existing finished surface and applying plaster of paris in proper line and levels etc. complete. | G60: =VLOOKUP($B60,'Rate card'!$A$4:$G285,6,FALSE) -> Sqft | H60: 45 | J60: 1000 | K60: =H60*J60 -> 45000 | L60: 2500 | M60: =L60-K60 -> -42500 | N60: =L60*H60 -> 112500 | O60: 0.85 | P60: =O60*N60 -> 95625 | Q60: Patch work wall punning
A61: 5 | B61: FC 17 | C61: =VLOOKUP($B61,'Rate card'!$A$4:$G285,2,FALSE) -> False Ceiling | D61: =VLOOKUP($B61,'Rate card'!$A$4:$G285,3,FALSE) -> Light Gala cutting | E61: =VLOOKUP($B61,'Rate card'!$A$4:$G285,4,FALSE) -> NA | F61: =VLOOKUP($B61,'Rate card'!$A$4:$G285,5,FALSE) -> NA | G61: =VLOOKUP($B61,'Rate card'!$A$4:$G285,6,FALSE) -> Nos | H61: 100 | J61: 200 | K61: =H61*J61 -> 20000 | L61: 200 | M61: =#REF!-#REF! -> #REF! | N61: =L61*H61 -> 20000 | Q61: All areas
J62: Total | K62: =SUM(K57:K61) -> 379840 | L62: TOTAL | M62: Total | N62: =SUM(N57:N61) -> 442500 | P62: =SUM(P57:P61) -> 354525
A63: Carpentry
A64: Living Room/Dining
A65: 1 | B65: CP 111 | C65: =VLOOKUP($B65,'Rate card'!$A$4:$G285,2,FALSE) -> Carpentry | D65: Main Door | E65: Veneer Finish | F65: MR ply +both side Veneer finish | G65: =VLOOKUP($B65,'Rate card'!$A$4:$G285,6,FALSE) -> Nos | H65: 65000 | J65: 1 | K65: =H65*J65 -> 65000 | L65: 1 | N65: =L65*H65 -> 65000 | O65: 0.45 | P65: =O65*N65 -> 29250 | Q65: New main door | U65: =N65 -> 65000
A66: 2 | B66: CP 111 | C66: Carpentry | D66: Ply Door Frame | E66: Veneer Finish | F66: MR ply + finish veneer from both sides | G66: Rft | H66: 750 | J66: =4+9+9 -> 22 | K66: =H66*J66 -> 16500 | L66: 22 | N66: =L66*H66 -> 16500 | O66: 0.25 | P66: =O66*N66 -> 4125 | Q66: Door Frame | U66: =N66 -> 16500
A67: 3 | B67: CP 25 | C67: =VLOOKUP($B67,'Rate card'!$A$4:$G285,2,FALSE) -> Carpentry | D67: =VLOOKUP($B67,'Rate card'!$A$4:$G285,3,FALSE) -> Carcass Storage | E67: =VLOOKUP($B67,'Rate card'!$A$4:$G285,4,FALSE) -> Laminate Finish | F67: =VLOOKUP($B67,'Rate card'!$A$4:$G285,5,FALSE) -> MR ply + Inside laminate + finish laminate | G67: =VLOOKUP($B67,'Rate card'!$A$4:$G285,6,FALSE) -> Sqft | H67: 1800 | J67: =7.5*10 -> 75 | K67: =H67*J67 -> 135000 | L67: =10.5*8.5 -> 89.25 | N67: =L67*H67 -> 160650 | O67: 0.25 | P67: =O67*N67 -> 40162.5 | Q67: shoerack including seating drawer and side open shelfs | R67: no need mirror behind door | T67: =N67 -> 160650
A68: 4 | C68: Carpentry | D68: Panelling with mirror | E68: Mirror Finish | G68: Sqft | H68: 650 | L68: =6*8.5 -> 51 | N68: =L68*H68 -> 33150 | P68: =O68*N68 -> 0 | Q68: mirror panel | U68: =N68 -> 33150
A69: 5 | C69: Carpentry | D69: Dining Console | E69: MDF Finish | G69: Sqft | K69: 3000 | L69: 15 | M69: =L69*K69 -> 45000 | N69: =L69*K69 -> 45000 | P69: =O69*N69 -> 0 | S69: =N69 -> 45000
A70: 6 | B70: CP 6 | C70: Carpentry | D70: Panelling with framing | E70: Veneer Finish | F70: Mr Ply+ply framing+Finish Veneer + Onyx | G70: =VLOOKUP($B70,'Rate card'!$A$4:$G285,6,FALSE) -> Sqft | H70: 1800 | J70: 1 | K70: =H70*J70 -> 1800 | L70: =22*8.5 -> 187 | N70: =L70*H70 -> 336600 | O70: 0.65 | P70: =O70*N70 -> 218790 | Q70: Panelling in Passage including shoe room door | U70: =N70 -> 336600
A71: 7 | C71: Carpentry | D71: Console | E71: Onyx | G71: LS | H71: 35000 | L71: 1 | N71: =L71*H71 -> 35000 | O71: 0.25 | P71: =O71*N71 -> 8750 | Q71: Console | R71: as per design | U71: =N71 -> 35000
A72: 8 | B72: CP 25 | C72: =VLOOKUP($B72,'Rate card'!$A$4:$G285,2,FALSE) -> Carpentry | D72: =VLOOKUP($B72,'Rate card'!$A$4:$G285,3,FALSE) -> Carcass Storage | E72: MDF Finish | F72: MR ply + Inside laminate + pu finish | G72: R ft | H72: 5000 | J72: 7.5 | K72: =H72*J72 -> 37500 | L72: 0 | N72: =L72*H72 -> 0 | P72: =O72*N72 -> 0 | Q72: TV unit
A73: 9 | B73: CP 25 | C73: =VLOOKUP($B73,'Rate card'!$A$4:$G285,2,FALSE) -> Carpentry | D73: =VLOOKUP($B73,'Rate card'!$A$4:$G285,3,FALSE) -> Carcass Storage | E73: Veneer + Mirror + marble | F73: MR ply + Inside laminate + finish Veneer | G73: =VLOOKUP($B73,'Rate card'!$A$4:$G285,6,FALSE) -> Sqft | H73: 1800 | J73: =7*8 -> 56 | K73: =H73*J73 -> 100800 | L73: =11*9.5 -> 104.5 | N73: =L73*H73 -> 188100 | O73: 0.65 | P73: =O73*N73 -> 122265 | Q73: TV panel | R73: considering 1500 sq.ft marble | U73: =N73 -> 188100
A74: 10 | B74: CP 25 | C74: =VLOOKUP($B74,'Rate card'!$A$4:$G285,2,FALSE) -> Carpentry | D74: =VLOOKUP($B74,'Rate card'!$A$4:$G285,3,FALSE) -> Carcass Storage | E74: =VLOOKUP($B74,'Rate card'!$A$4:$G285,4,FALSE) -> Laminate Finish | F74: =VLOOKUP($B74,'Rate card'!$A$4:$G285,5,FALSE) -> MR ply + Inside laminate + finish laminate | G74: =VLOOKUP($B74,'Rate card'!$A$4:$G285,6,FALSE) -> Sqft | H74: 3000 | J74: =4*7 -> 28 | K74: =H74*J74 -> 84000 | L74: =3*8.5 -> 25.5 | N74: =L74*H74 -> 76500 | P74: =O74*N74 -> 0 | Q74: Mandir | U74: =N74 -> 76500
A75: 11 | B75: CP 25 | C75: =VLOOKUP($B75,'Rate card'!$A$4:$G285,2,FALSE) -> Carpentry | D75: =VLOOKUP($B75,'Rate card'!$A$4:$G285,3,FALSE) -> Carcass Storage | E75: Veneer + Onyx Finish | F75: =F72 -> MR ply + Inside laminate + pu finish | G75: =VLOOKUP($B75,'Rate card'!$A$4:$G285,6,FALSE) -> Sqft | H75: 2500 | J75: =5*3.5 -> 17.5 | K75: =H75*J75 -> 43750 | L75: =3*3 -> 9 | N75: =L75*H75 -> 22500 | P75: =O75*N75 -> 0 | Q75: Console | R75: Hebind sofa | U75: =N75 -> 22500
A76: 12 | B76: CP 6 | C76: Carpentry | D76: Panelling with framing | E76: CNC MDF + Veneer | F76: Mr Ply+ply framing+Finish Veneer + Onyx | G76: =VLOOKUP($B76,'Rate card'!$A$4:$G285,6,FALSE) -> Sqft | H76: 1500 | J76: =12*10 -> 120 | K76: =H76*J76 -> 180000 | L76: =12.5*8.5 -> 106.25 | N76: =L76*H76 -> 159375 | O76: 0.5 | P76: =O76*N76 -> 79687.5 | Q76: Wall Panel on sofa wall | R76: incluing master bedroom door and 3d panel | U76: 84375 | V76: 75000
A77: 13 | B77: CP 6 | C77: Carpentry | D77: Panelling with framing | E77: Veneer + Mirror + Marble | F77: MR ply + Inside laminate + finish Veneer | G77: =VLOOKUP($B77,'Rate card'!$A$4:$G285,6,FALSE) -> Sqft | H77: 1800 | J77: =29*10 -> 290 | K77: =H77*J77 -> 522000 | L77: =34*8.5 -> 289 | N77: =L77*H77 -> 520200 | O77: 0.4 | P77: =O77*N77 -> 208080 | Q77: Panelling on mother's & samar's bed room wall | U77: =N77 -> 520200
A78: 14 | C78: Carpentry | N78: 45000 | P78: =O78*N78 -> 0 | U78: =N78 -> 45000
A79: 15 | B79: CP 6 | C79: Carpentry | D79: Panelling with framing | E79: Mirror Finish | F79: Mr Ply+ply framing+Finish Veneer + Onyx | G79: =VLOOKUP($B79,'Rate card'!$A$4:$G285,6,FALSE) -> Sqft | H79: 850 | J79: =12*10 -> 120 | K79: =H79*J79 -> 102000 | L79: =5*8.5 -> 42.5 | N79: =L79*H79 -> 36125 | O79: 0.75 | P79: =O79*N79 -> 27093.75 | Q79: mirror panel on dining wall | R79: brown mirror | U79: =N79 -> 36125
A80: Modular Kitchen
A81: 1 | B81: CP 25 | C81: =VLOOKUP($B81,'Rate card'!$A$4:$G285,2,FALSE) -> Carpentry | D81: =VLOOKUP($B81,'Rate card'!$A$4:$G285,3,FALSE) -> Carcass Storage | E81: Acrylic Finish | F81: Marine ply + Inside laminate + Acrylic Finish | G81: =VLOOKUP($B81,'Rate card'!$A$4:$G285,6,FALSE) -> Sqft | H81: 2700 | J81: =18.5*2.5 -> 46.25 | K81: =H81*J81 -> 124875 | L81: =20*2.5 -> 50 | N81: =L81*H81 -> 135000 | O81: 0.3 | P81: =O81*N81 -> 40500 | Q81: undercounter
A82: 2 | B82: CP 25 | C82: =VLOOKUP($B82,'Rate card'!$A$4:$G285,2,FALSE) -> Carpentry | D82: =VLOOKUP($B82,'Rate card'!$A$4:$G285,3,FALSE) -> Carcass Storage | E82: Acrylic Finish | F82: Marine ply + Inside laminate + Acrylic Finish | G82: =VLOOKUP($B82,'Rate card'!$A$4:$G285,6,FALSE) -> Sqft | H82: 2700 | J82: =28+11.25*2.5+4*2.5 -> 66.125 | K82: =H82*J82 -> 178537.5 | L82: =20*5.5 -> 110 | N82: =L82*H82 -> 297000 | O82: 0.3 | P82: =O82*N82 -> 89100 | Q82: overhead+loft
A83: 3 | B83: CP 25 | C83: =VLOOKUP($B83,'Rate card'!$A$4:$G285,2,FALSE) -> Carpentry | D83: =VLOOKUP($B83,'Rate card'!$A$4:$G285,3,FALSE) -> Carcass Storage | E83: Acrylic Finish | F83: Marine ply + Inside laminate + Acrylic Finish | G83: =VLOOKUP($B83,'Rate card'!$A$4:$G285,6,FALSE) -> Sqft | H83: 2700 | J83: =4*10 -> 40 | K83: =H83*J83 -> 108000 | L83: =4*10.5 -> 42 | N83: =L83*H83 -> 113400 | O83: 0.3 | P83: =O83*N83 -> 34020 | Q83: Pantry Storage, next to mandir and oven unit and side glass unit
A84: 4 | B84: CP 61 | C84: =VLOOKUP($B84,'Rate card'!$A$4:$G285,2,FALSE) -> Carpentry | D84: =VLOOKUP($B84,'Rate card'!$A$4:$G285,3,FALSE) -> Kitchen Basket | E84: tandem | F84: =VLOOKUP($B84,'Rate card'!$A$4:$G285,5,FALSE) -> Basket + Channel+Fitting charges | G84: =VLOOKUP($B84,'Rate card'!$A$4:$G285,6,FALSE) -> Nos | H84: 8000 | J84: 5 | K84: =H84*J84 -> 40000 | L84: 14 | N84: =L84*H84 -> 112000 | O84: 0.3 | P84: =O84*N84 -> 33600 | Q84: Modular kitchen
A85: 5 | B85: CP 64 | C85: =VLOOKUP($B85,'Rate card'!$A$4:$G285,2,FALSE) -> Carpentry | D85: =VLOOKUP($B85,'Rate card'!$A$4:$G285,3,FALSE) -> Wicker basket | E85: =VLOOKUP($B85,'Rate card'!$A$4:$G285,4,FALSE) -> Wicker basket | F85: =VLOOKUP($B85,'Rate card'!$A$4:$G285,5,FALSE) -> Basket + Channel+Fitting charges | G85: =VLOOKUP($B85,'Rate card'!$A$4:$G285,6,FALSE) -> Nos | H85: 6000 | J85: 2 | K85: =H85*J85 -> 12000 | L85: 2 | N85: =L85*H85 -> 12000 | O85: 0.3 | P85: =O85*N85 -> 3600 | Q85: Modular kitchen
A86: 6 | D86: Back Painted Glass | G86: Sqft | H86: 950 | L86: 30 | N86: =L86*H86 -> 28500 | O86: 0.3 | P86: =O86*N86 -> 8550
A87: 7 | C87: Carpentry | D87: Kitchen Sliding door | E87: Flutted glass finish | F87: Modular Kitchen | G87: Sqft | H87: 1650 | J87: =3*7 -> 21 | K87: =H87*J87 -> 34650 | L87: =3*7.5 -> 22.5 | N87: =L87*H87 -> 37125 | O87: 0.3 | P87: =O87*N87 -> 11137.5 | Q87: kitchen
A88: Utility | N88: =L88*H88 -> 0
A89: 1 | B89: CP 25 | C89: =VLOOKUP($B89,'Rate card'!$A$4:$G285,2,FALSE) -> Carpentry | D89: =VLOOKUP($B89,'Rate card'!$A$4:$G285,3,FALSE) -> Carcass Storage | E89: =VLOOKUP($B89,'Rate card'!$A$4:$G285,4,FALSE) -> Laminate Finish | F89: Marine ply + Inside laminate + finish laminate | G89: =VLOOKUP($B89,'Rate card'!$A$4:$G285,6,FALSE) -> Sqft | H89: 1800 | J89: =5.5*2.5 -> 13.75 | K89: =H89*J89 -> 24750 | L89: =12*2.5 -> 30 | N89: =L89*H89 -> 54000 | O89: 0.3 | P89: =O89*N89 -> 16200 | Q89: undercounter | U89: =N89 -> 54000
A90: 2 | B90: CP 25 | C90: =VLOOKUP($B90,'Rate card'!$A$4:$G285,2,FALSE) -> Carpentry | D90: =VLOOKUP($B90,'Rate card'!$A$4:$G285,3,FALSE) -> Carcass Storage | E90: =VLOOKUP($B90,'Rate card'!$A$4:$G285,4,FALSE) -> Laminate Finish | F90: Marine ply + Inside laminate + finish laminate | G90: =VLOOKUP($B90,'Rate card'!$A$4:$G285,6,FALSE) -> Sqft | H90: 650 | J90: =10*10 -> 100 | K90: =H90*J90 -> 65000 | L90: =12*8.5 -> 102 | N90: =L90*H90 -> 66300 | O90: 0.3 | P90: =O90*N90 -> 19890 | Q90: only shutters | U90: =N90 -> 66300
A91: 3 | B91: CP 117 | C91: =VLOOKUP($B91,'Rate card'!$A$4:$G285,2,FALSE) -> Carpentry | D91: =VLOOKUP($B91,'Rate card'!$A$4:$G285,3,FALSE) -> Carcass Storage | E91: =VLOOKUP($B91,'Rate card'!$A$4:$G285,4,FALSE) -> Laminate Finish | F91: Marine ply + Inside laminate + finish laminate | G91: =VLOOKUP($B91,'Rate card'!$A$4:$G285,6,FALSE) -> Sqft | H91: 1800 | J91: 22 | K91: =H91*J91 -> 39600 | L91: =4*5 -> 20 | N91: =L91*H91 -> 36000 | O91: 0.3 | P91: =O91*N91 -> 10800 | Q91: Washing machine storage | U91: =N91 -> 36000
A92: Mother's Bedroom
A93: 1 | B93: CP 21 | C93: =VLOOKUP($B93,'Rate card'!$A$4:$G285,2,FALSE) -> Carpentry | D93: =VLOOKUP($B93,'Rate card'!$A$4:$G285,3,FALSE) -> Bed | E93: =VLOOKUP($B93,'Rate card'!$A$4:$G285,4,FALSE) -> Laminate Finish | F93: MR ply panelling + Foam material and labour. Excludes Fabric cost | G93: =VLOOKUP($B93,'Rate card'!$A$4:$G285,6,FALSE) -> Sqft | H93: 1800 | J93: =5.5*6.5 -> 35.75 | K93: =H93*J93 -> 64350 | L93: =6*6.5 -> 39 | N93: =L93*H93 -> 70200 | O93: 0.7 | P93: =O93*N93 -> 49140 | Q93: king size bed | U93: =N93 -> 70200
A94: 2 | B94: CP 45 | C94: =VLOOKUP($B94,'Rate card'!$A$4:$G285,2,FALSE) -> Carpentry | D94: =VLOOKUP($B94,'Rate card'!$A$4:$G285,3,FALSE) -> Headboard | E94: =VLOOKUP($B94,'Rate card'!$A$4:$G285,4,FALSE) -> Fabric Finish | F94: =VLOOKUP($B94,'Rate card'!$A$4:$G285,5,FALSE) -> MR ply panelling + Foam material and labour. Excludes Fabric cost | G94: =VLOOKUP($B94,'Rate card'!$A$4:$G285,6,FALSE) -> Sqft | H94: 1300 | J94: =5.5*3 -> 16.5 | K94: =H94*J94 -> 21450 | L94: =9*4.5 -> 40.5 | N94: =L94*H94 -> 52650 | P94: =O94*N94 -> 0 | Q94: Headboard | U94: =N94 -> 52650
A95: 3 | B95: CP 46 | C95: =VLOOKUP($B95,'Rate card'!$A$4:$G285,2,FALSE) -> Carpentry | D95: Bed side table | E95: =VLOOKUP($B95,'Rate card'!$A$4:$G285,4,FALSE) -> Laminate Finish | F95: =VLOOKUP($B95,'Rate card'!$A$4:$G285,5,FALSE) -> MR ply + Inside laminate + finish laminate (1 Drawer) | G95: =VLOOKUP($B95,'Rate card'!$A$4:$G285,6,FALSE) -> Nos | H95: 20000 | J95: 2 | K95: =H95*J95 -> 40000 | L95: 2 | N95: =L95*H95 -> 40000 | P95: =O95*N95 -> 0 | Q95: Bed side table | S95: =N95 -> 40000
A96: 4 | B96: CP 25 | C96: =VLOOKUP($B96,'Rate card'!$A$4:$G285,2,FALSE) -> Carpentry | D96: =VLOOKUP($B96,'Rate card'!$A$4:$G285,3,FALSE) -> Carcass Storage | E96: =VLOOKUP($B96,'Rate card'!$A$4:$G285,4,FALSE) -> Laminate Finish | F96: =VLOOKUP($B96,'Rate card'!$A$4:$G285,5,FALSE) -> MR ply + Inside laminate + finish laminate | G96: Sqft | H96: 1800 | J96: 7 | K96: =H96*J96 -> 12600 | L96: =7*1 -> 7 | N96: =L96*H96 -> 12600 | O96: 0.35 | P96: =O96*N96 -> 4410 | Q96: Dresser
A97: 5 | B97: CP 25 | C97: =VLOOKUP($B97,'Rate card'!$A$4:$G285,2,FALSE) -> Carpentry | D97: =VLOOKUP($B97,'Rate card'!$A$4:$G285,3,FALSE) -> Carcass Storage | E97: =VLOOKUP($B97,'Rate card'!$A$4:$G285,4,FALSE) -> Laminate Finish | F97: =VLOOKUP($B97,'Rate card'!$A$4:$G285,5,FALSE) -> MR ply + Inside laminate + finish laminate | G97: =VLOOKUP($B97,'Rate card'!$A$4:$G285,6,FALSE) -> Sqft | H97: =VLOOKUP($B97,'Rate card'!$A$4:$J285,8,FALSE) -> 1800 | J97: =5*10 -> 50 | K97: =H97*J97 -> 90000 | L97: =5*9 -> 45 | N97: =L97*H97 -> 81000 | O97: 0.5 | P97: =O97*N97 -> 40500 | Q97: Wardrobe near entrance | T97: =N97 -> 81000
A98: 6 | B98: CP 3 | C98: =VLOOKUP($B98,'Rate card'!$A$4:$G285,2,FALSE) -> Carpentry | D98: =VLOOKUP($B98,'Rate card'!$A$4:$G285,3,FALSE) -> Panelling with framing | E98: =VLOOKUP($B98,'Rate card'!$A$4:$G285,4,FALSE) -> Mirror Finish | F98: =VLOOKUP($B98,'Rate card'!$A$4:$G285,5,FALSE) -> MR ply + ply framing + 5mm clear mirror | G98: =VLOOKUP($B98,'Rate card'!$A$4:$G285,6,FALSE) -> Sqft | H98: =VLOOKUP($B98,'Rate card'!$A$4:$J285,8,FALSE) -> 750 | J98: =2.5*7 -> 17.5 | K98: =H98*J98 -> 13125 | L98: =7*2 -> 14 | N98: =L98*H98 -> 10500 | O98: 0.25 | P98: =O98*N98 -> 2625 | Q98: Mirror | U98: =N98 -> 10500
A99: 7 | B99: CP 1 | C99: Carpentry | D99: Panelling with framing | E99: =VLOOKUP($B99,'Rate card'!$A$4:$G285,4,FALSE) -> Laminate Finish | F99: MR ply + ply framing + finish laminate | G99: =VLOOKUP($B99,'Rate card'!$A$4:$G285,6,FALSE) -> Sqft | H99: 950 | J99: 80 | K99: =H99*J99 -> 76000 | L99: =9*5 -> 45 | N99: =L99*H99 -> 42750 | P99: =O99*N99 -> 0 | Q99: Wall panel | R99: including rafters nad charcol sheet | U99: =N99 -> 42750
A100: 8 | B100: CP 17 | C100: =VLOOKUP($B100,'Rate card'!$A$4:$G285,2,FALSE) -> Carpentry | D100: =VLOOKUP($B100,'Rate card'!$A$4:$G285,3,FALSE) -> Wardrobe | E100: =VLOOKUP($B100,'Rate card'!$A$4:$G285,4,FALSE) -> Laminate Finish | F100: =VLOOKUP($B100,'Rate card'!$A$4:$G285,5,FALSE) -> MR ply + Inside laminate + finish laminate. (Includes 4 pencil drawers, Handles of base rate Rs.1000/pc) | G100: =VLOOKUP($B100,'Rate card'!$A$4:$G285,6,FALSE) -> Sqft | H100: 1800 | J100: =7.5*10 -> 75 | K100: =H100*J100 -> 135000 | L100: =10*9 -> 90 | N100: =L100*H100 -> 162000 | O100: 0.5 | P100: =O100*N100 -> 81000 | Q100: Wardrobe | T100: =N100 -> 162000
A101: 9 | B101: CP 6 | C101: =VLOOKUP($B101,'Rate card'!$A$4:$G285,2,FALSE) -> Carpentry | D101: =VLOOKUP($B101,'Rate card'!$A$4:$G285,3,FALSE) -> Panelling with framing | E101: =VLOOKUP($B101,'Rate card'!$A$4:$G285,4,FALSE) -> MDF | F101: =VLOOKUP($B101,'Rate card'!$A$4:$G285,5,FALSE) -> MR ply + ply framing + 12mm MDF | G101: =VLOOKUP($B101,'Rate card'!$A$4:$G285,6,FALSE) -> Sqft | H101: 600 | J101: =12*2.5 -> 30 | K101: =H101*J101 -> 18000 | L101: =10*2 -> 20 | N101: =L101*H101 -> 12000 | O101: 0.9 | P101: =O101*N101 -> 10800 | Q101: pelmet | U101: =N101 -> 12000
A102: Samar's Bedroom | P102: =O102*N102 -> 0
A103: 1 | B103: CP 21 | C103: =VLOOKUP($B103,'Rate card'!$A$4:$G285,2,FALSE) -> Carpentry | D103: =VLOOKUP($B103,'Rate card'!$A$4:$G285,3,FALSE) -> Bed | E103: =VLOOKUP($B103,'Rate card'!$A$4:$G285,4,FALSE) -> Laminate Finish | F103: =VLOOKUP($B103,'Rate card'!$A$4:$G285,5,FALSE) -> MR ply + Inside laminate + finish laminate | G103: =VLOOKUP($B103,'Rate card'!$A$4:$G285,6,FALSE) -> Sqft | H103: 2200 | J103: =6*6.5 -> 39 | K103: =H103*J103 -> 85800 | L103: =6*6.5 -> 39 | N103: =L103*H103 -> 85800 | O103: 0.7 | P103: =O103*N103 -> 60060 | Q103: King size Bed, 2 internal drawers+ 1 side box | U103: =N103 -> 85800
A104: 2 | B104: CP 45 | C104: =VLOOKUP($B104,'Rate card'!$A$4:$G285,2,FALSE) -> Carpentry | D104: =VLOOKUP($B104,'Rate card'!$A$4:$G285,3,FALSE) -> Headboard | E104: =VLOOKUP($B104,'Rate card'!$A$4:$G285,4,FALSE) -> Fabric Finish | F104: =VLOOKUP($B104,'Rate card'!$A$4:$G285,5,FALSE) -> MR ply panelling + Foam material and labour. Excludes Fabric cost | G104: =VLOOKUP($B104,'Rate card'!$A$4:$G285,6,FALSE) -> Sqft | H104: 1300 | J104: =6*3.5 -> 21 | K104: =H104*J104 -> 27300 | L104: =6*4.5 -> 27 | N104: =L104*H104 -> 35100 | P104: =O104*N104 -> 0 | Q104: Headboard | U104: =N104 -> 35100
A105: 3 | B105: CP 46 | C105: =VLOOKUP($B105,'Rate card'!$A$4:$G285,2,FALSE) -> Carpentry | D105: Bed side table | E105: =VLOOKUP($B105,'Rate card'!$A$4:$G285,4,FALSE) -> Laminate Finish | F105: =VLOOKUP($B105,'Rate card'!$A$4:$G285,5,FALSE) -> MR ply + Inside laminate + finish laminate (1 Drawer) | G105: =VLOOKUP($B105,'Rate card'!$A$4:$G285,6,FALSE) -> Nos | H105: 20000 | J105: 1 | K105: =H105*J105 -> 20000 | L105: 2 | N105: =L105*H105 -> 40000 | P105: =O105*N105 -> 0 | Q105: Bed side table | S105: =N105 -> 40000
A106: 4 | B106: CP 49 | C106: =VLOOKUP($B106,'Rate card'!$A$4:$G285,2,FALSE) -> Carpentry | D106: =VLOOKUP($B106,'Rate card'!$A$4:$G285,3,FALSE) -> Study Table | E106: =VLOOKUP($B106,'Rate card'!$A$4:$G285,4,FALSE) -> Laminate Finish | F106: =VLOOKUP($B106,'Rate card'!$A$4:$G285,5,FALSE) -> MR ply + Inside laminate + finish laminate (2 pencil drawers) | G106: =VLOOKUP($B106,'Rate card'!$A$4:$G285,6,FALSE) -> Rft | H106: 4500 | J106: 4 | K106: =H106*J106 -> 18000 | L106: 4.5 | N106: =L106*H106 -> 20250 | O106: 0.65 | P106: =O106*N106 -> 13162.5 | Q106: Study table | T106: =N106 -> 20250
...

Sheet WO- Awdesh
A6: Date : | B6: 46029 | E6: Project Code : | F6: Wing 15 - 702
A7: Client Name : | B7: Rahul Dhanawat | E7: WO-1 | F7: AWDESH
A8: Address : | B8: 10BKC | E8: Elemantra Contact Person :
A9: Sr.No | B9: Id | C9: Item Name | D9: Category | E9: Item Details | F9: Description | G9: UOM | H9: Elemantra Rates | I9: awdesh rates | J9: Amount awdesh | K9: Area | L9: Amount | M9: Location | N9: Remarks
A10: Painting | K10: TOTAL
A11: 1 | B11: P 19 | C11: =VLOOKUP($B11,'Rate card'!$A$4:$G1006,2,FALSE) -> Paint | D11: =VLOOKUP($B11,'Rate card'!$A$4:$G1006,3,FALSE) -> Royal Shyne | E11: =VLOOKUP($B11,'Rate card'!$A$4:$G1006,4,FALSE) -> 2 Primer + 1 Putty + 2 RLE | F11: =VLOOKUP($B11,'Rate card'!$A$4:$G1006,5,FALSE) -> Painting with royal Shyne on ceiling, to give an even shade – Two or more coats on new work including preparation of surface. (_putty+_primer+_paint) as per requirement | G11: =VLOOKUP($B11,'Rate card'!$A$4:$G1006,6,FALSE) -> Sqft | H11: =VLOOKUP($B11,'Rate card'!$A$4:$J1006,8,FALSE) -> 42 | I11: 38 | J11: =I11*K11 -> 63574 | K11: 1673 | L11: =K11*H11 -> 70266 | M11: Ceiling
A12: =A11+1 -> 2 | B12: P 5 | C12: =VLOOKUP($B12,'Rate card'!$A$4:$G1006,2,FALSE) -> Paint | D12: =VLOOKUP($B12,'Rate card'!$A$4:$G1006,3,FALSE) -> Royal Shyne | E12: =VLOOKUP($B12,'Rate card'!$A$4:$G1006,4,FALSE) -> 2 Primer + 1 Putty + 2 RLE | F12: =VLOOKUP($B12,'Rate card'!$A$4:$G1006,5,FALSE) -> Painting with royal Shyne on walls, to give an even shade – Two or more coats on new work including preparation of surface. (_putty+_primer+_paint) as per requirement | G12: =VLOOKUP($B12,'Rate card'!$A$4:$G1006,6,FALSE) -> Sqft | H12: =VLOOKUP($B12,'Rate card'!$A$4:$J1006,8,FALSE) -> 45 | I12: 38 | J12: =I12*K12 -> 158935 | K12: =1673*2.5 -> 4182.5 | L12: =K12*H12 -> 188212.5 | M12: Walls
A13: =A12+1 -> 3 | B13: P 5 | C13: =VLOOKUP($B13,'Rate card'!$A$4:$G1006,2,FALSE) -> Paint | D13: Texture paint | E13: =VLOOKUP($B13,'Rate card'!$A$4:$G1006,4,FALSE) -> 2 Primer + 1 Putty + 2 RLE | F13: =VLOOKUP($B13,'Rate card'!$A$4:$G1006,5,FALSE) -> Painting with royal Shyne on walls, to give an even shade – Two or more coats on new work including preparation of surface. (_putty+_primer+_paint) as per requirement | G13: LS | H13: 25000 | I13: 15000 | J13: =I13*K13 -> 15000 | K13: 1 | L13: =K13*H13 -> 25000 | M13: Walls
A14: =A13+1 -> 4 | B14: P 5 | C14: =VLOOKUP($B14,'Rate card'!$A$4:$G1006,2,FALSE) -> Paint | D14: =VLOOKUP($B14,'Rate card'!$A$4:$G1006,3,FALSE) -> Royal Shyne | E14: =VLOOKUP($B14,'Rate card'!$A$4:$G1006,4,FALSE) -> 2 Primer + 1 Putty + 2 RLE | F14: =VLOOKUP($B14,'Rate card'!$A$4:$G1006,5,FALSE) -> Painting with royal Shyne on walls, to give an even shade – Two or more coats on new work including preparation of surface. (_putty+_primer+_paint) as per requirement | G14: =VLOOKUP($B14,'Rate card'!$A$4:$G1006,6,FALSE) -> Sqft | I14: 19 | L14: =K14*H14 -> 0 | M14: Dhaar
A15: 4 | C15: PU | D15: PU- ICA ROYAL ASIAN | G15: Sqft | H15: 350 | I15: 250 | J15: =I15*K15 -> 325000 | K15: 1300 | L15: =K15*H15 -> 455000 | M15: all areas
A16: 5 | C16: PU | D16: PU- ICA ROYAL ASIAN | E16: Dhaar | G16: Sqft | I16: 125
A17: 6 | B17: P 12 | C17: =VLOOKUP($B17,'Rate card'!$A$4:$G1006,2,FALSE) -> Polish | D17: =VLOOKUP($B17,'Rate card'!$A$4:$G1006,3,FALSE) -> Melamine | E17: =VLOOKUP($B17,'Rate card'!$A$4:$G1006,4,FALSE) | F17: As per specifications | G17: =VLOOKUP($B17,'Rate card'!$A$4:$G1006,6,FALSE) -> Sqft | H17: 120 | I17: 75 | J17: =I17*K17 -> 150000 | K17: 2000 | L17: =K17*H17 -> 240000 | M17: Veneer applications
J18: =sum(J11:J17) -> 712509 | K18: TOTAL | L18: =SUM(L11:L17) -> 978478.5

Sheet CNC ORDERS
A4: Carpentry | L4: QTY | M4: VENDOR RATES-Mehta CNC | N4: OUR RATES | O4: artist amount | P4: ply panelling rate | Q4: panelling amt | U4: VENDOR AMOUNT
A5: Living Room/Dining
A6: 1 | B6: CP 6 | C6: Carpentry | D6: Panelling with framing | E6: CNC MDF + Veneer | F6: Mr Ply+ply framing+Finish Veneer + Onyx | G6: =VLOOKUP($B6,'Rate card'!$A$4:$G1002,6,FALSE) -> Sqft | H6: 1500 | J6: 50 | K6: =H6*J6 -> 75000 | L6: 50 | M6: 35300 | N6: =L6*H6 -> 75000 | O6: 30000 | P6: 300 | Q6: =P6*L6 -> 15000 | S6: Wall Panel on sofa wall | T6: incluing master bedroom door and 3d panel | U6: =M6*L6 -> 1765000
A7: Master bed room
A8: 4 | B8: CP 3 | C8: =VLOOKUP($B8,'Rate card'!$A$4:$G1002,2,FALSE) -> Carpentry | D8: =VLOOKUP($B8,'Rate card'!$A$4:$G1002,3,FALSE) -> Panelling with framing | E8: stone finish | F8: =VLOOKUP($B8,'Rate card'!$A$4:$G1002,5,FALSE) -> MR ply + ply framing + 5mm clear mirror | G8: =VLOOKUP($B8,'Rate card'!$A$4:$G1002,6,FALSE) -> Sqft | H8: 1500 | J8: 50 | K8: =H8*J8 -> 75000 | L8: =12*9 -> 108 | M8: 34000 | N8: =L8*H8 -> 162000 | P8: 250 | Q8: =P8*L8 -> 27000 | S8: Bed back wall | U8: =M8*L8 -> 3672000
A9: Ranbeer's Bedroom
A10: 1 | B10: CP 1 | C10: Carpentry | D10: Panelling with framing | E10: =VLOOKUP($B10,'Rate card'!$A$4:$G1002,4,FALSE) -> Laminate Finish | F10: MR ply + ply framing + finish laminate | G10: =VLOOKUP($B10,'Rate card'!$A$4:$G1002,6,FALSE) -> Sqft | H10: 1500 | J10: 90 | K10: =H10*J10 -> 135000 | L10: =9*9 -> 81 | M10: 38500 | N10: =L10*H10 -> 121500 | P10: 300 | Q10: =P10*L10 -> 24300 | S10: Wall panel | U10: =M10*L10 -> 3118500
A11: Samars bedroom
A12: 1 | B12: CP 1 | C12: Carpentry | D12: Panelling with framing | E12: CNC Finish | G12: =VLOOKUP($B12,'Rate card'!$A$4:$G1002,6,FALSE) -> Sqft | H12: 1500 | L12: 95 | M12: 38050 | N12: =L12*H12 -> 142500 | P12: 400 | Q12: =P12*L12 -> 38000
M13: =SUM(M6:M12) -> 145850 | N13: =SUM(N6:N12) -> 501000 | O13: =SUM(O6:O10) -> 30000 | Q13: =SUM(Q6:Q12) -> 104300
U14: 119000
M16: =N13 -> 501000 | N16: our rate
M17: =O13 -> 30000 | N17: less artist amt
M18: =Q13 -> 104300 | N18: less ply panelling amt
M19: =M13 -> 145850 | N19: les cnc vendor amt
M20: =SUM(M17:M19) -> 280150 | N20: OUR MARGIN 42%
M21: =M16-M20 -> 220850

Sheet Sheet17
A1: Task | B1: Column 2 | C1: Dur | D1: Start date | E1: End date | F1: Milestone | G1: Timeline milestone | H1: Design remarks | I1: Execution remarks | J1: Wk 2 | K1: Wk 3 | L1: Wk 4 | M1: Wk 5 | N1: Wk 6 | O1: Wk 7 | P1: Wk 8 | Q1: Wk 9 | R1: Wk 10 | S1: Wk 11 | T1: Wk 12 | U1: Wk 13 | V1: Wk 14 | W1: Wk 15 | X1: Wk 16 | Y1: Wk 17 | Z1: Wk 18 | AA1: Wk 19 | AB1: Wk 20 | AC1: Wk 21 | AD1: Wk 22 | AE1: Wk 23 | AF1: Wk 24 | AG1: Wk 25 | AH1: Wk 26 | AI1: Wk 27
A2: Civil & plumbing | B2: In progress | C2: =E2-D2 -> 32 | D2: 45992 | E2: =E5 -> 46024 | F2: Civil completed (90%) | G2: Month 1 | J2: =E51-D2 -> 100
A3: Demolition & making of structure | B3: Completed | C3: 25 | D3: =D2 -> 45992 | E3: =D3+C3 -> 46017 | F3: Civil - 10%
A4: Plumbing + waterproofing | B4: Completed | C4: 15 | D4: =D2+5 -> 45997 | E4: =D4+C4 -> 46012 | F4: Civil - 25% | J4: Start date
A5: Kitchen and utility counter | B5: Completed | C5: 12 | D5: =E4 -> 46012 | E5: =D5+C5 -> 46024 | F5: Civil 65% | J5: =D2 -> 45992
A6: Bathrooms tiling | B6: In progress | D6: =E5 -> 46024 | E6: =D6+C6 -> 46024 | J6: =D3 -> 45992
A7: Living italian cladding | B7: Not started | D7: =E6 -> 46024 | E7: =D7+C7 -> 46024 | J7: =D4 -> 45997
A8: Living onyx cladiing | B8: Not started | D8: =E7 -> 46024 | E8: =D8+C8 -> 46024 | J8: =D5 -> 46012
A9: HVAC | B9: In progress | C9: =E9-D9 -> 79 | D9: =D10 -> 45999 | E9: =E11 -> 46078 | G9: Month 1 | J9: End date
A10: Piping | B10: Completed | C10: 18 | D10: =D3+7 -> 45999 | E10: =D10+C10 -> 46017 | F10: HVAC 30% | J10: =E51 -> 46092
A11: Machines installation | B11: Not started | C11: 20 | D11: 46058 | E11: =D11+C11 -> 46078 | F11: HVAC 100%
A12: Carpentry - Phase 1 | B12: In progress | C12: =E12-D12 -> 38 | D12: =D13 -> 46007 | E12: =E17 -> 46045 | F12: Carpentry on site (70%) | G12: Month 1 & 2
A13: Wall Panelling Living - framing | B13: In progress | C13: 8 | D13: =E3-10 -> 46007 | E13: =D13+C13 -> 46015 | F13: Carpentry on site (15%) | H13: Reduce wall panneling | I13: Parallel teams
A14: Wall Panelling bedrooms framing | B14: In progress | C14: 8 | D14: =E13 -> 46015 | E14: =D14+C14 -> 46023 | F14: Carpentry on site (25%) | H14: Reduce wall panneling | I14: Parallel teams
A15: Wall panelling - Ply+veneer+mirror | B15: In progress | C15: 12 | D15: =E14 -> 46023 | E15: =D15+C15 -> 46035 | F15: Carpentry on site (45%) | H15: Reduce wall panneling | I15: Parallel teams
A16: Carcass - making | B16: In progress | C16: 15 | D16: =D14+5 -> 46020 | E16: =D16+C16 -> 46035 | F16: Carpentry on site (60%)
A17: Lamintes/ veneer pasting | B17: In progress | C17: 15 | D17: =E16-5 -> 46030 | E17: =D17+C17 -> 46045 | F17: Carpentry on site (70%)
A18: Electricals - phase 1 | B18: In progress | C18: =E21-D19 -> 25 | D18: =D19 -> 45998 | E18: =D18+C18 -> 46023 | F18: Electrical completed (70%) | G18: Month 1
A19: Jari work | B19: Completed | C19: 10 | D19: =D2+6 -> 45998 | E19: =D19+C19 -> 46008 | F19: Electrical (15%) | I19: In house team
A20: Conduiting | B20: Completed | C20: 10 | D20: =E19 -> 46008 | E20: =D20+C20 -> 46018 | F20: Electrical (40%) | I20: In house team
A21: Wiring | B21: Completed | C21: 10 | D21: =E20-5 -> 46013 | E21: =D21+C21 -> 46023 | F21: Electrical (70%) | H21: Parallel electric | I21: In house team
A22: False ceiling & POP | B22: In progress | C22: =E22-D22 -> 64 | D22: =D23 -> 45998 | E22: =E27 -> 46062 | F22: False ceiling completed (95%) | G22: Month 1 & 2
A23: POP | B23: In progress | C23: 8 | D23: =D19 -> 45998 | E23: =D23+C23 -> 46006 | F23: False ceiling (15%) | H23: More MP
A24: Framing | B24: Completed | C24: 12 | D24: =E20-5 -> 46013 | E24: =D24+C24 -> 46025 | F24: False ceiling (35%) | H24: More MP
A25: bathrooms framing | B25: Not started | D25: =E20-10 -> 46008 | E25: =D25+C25 -> 46008
A26: Board closing | B26: Completed | C26: 12 | D26: =E21-10 -> 46013 | E26: =D26+C26 -> 46025 | F26: False ceiling (75%)
A27: Finishing | B27: Completed | C27: 25 | D27: =D33 -> 46037 | E27: =D27+C27 -> 46062 | F27: False ceiling (95%)
A28: Carpentry - modular | B28: In progress | C28: =E28-D28 -> 37 | D28: =D29 -> 46015 | E28: =E33 -> 46052 | F28: Modular installation (95%) | G28: Month 1 & 2
A29: Order placing wardrobes | B29: Order Placed | C29: 12 | D29: =E26-10 -> 46015 | E29: =D29+C29 -> 46027 | F29: Modular (30%) | H29: Place orders basis false ceiling framing | I29: Vendor to be finalized in month 1
A30: order placing loose items | B30: Order Placed | D30: =E27-10 -> 46052 | E30: =D30+C30 -> 46052
A31: Order delivery | B31: In progress | C31: 30 | D31: =E29-10 -> 46017 | E31: =D31+C31 -> 46047 | F31: Modular (80%)
A32: order placing kitchen | B32: Order Placed | D32: =E30-10 -> 46042 | E32: =D32+C32 -> 46042
A33: Installation | B33: Not started | C33: 15 | D33: =E31-10 -> 46037 | E33: =D33+C33 -> 46052 | F33: Modular (95%)
A34: Finishing phase | B34: In progress | C34: =E34-D34 -> 33 | D34: =D35 -> 46037 | E34: =E38 -> 46070 | F34: Finishing completed (95%) | G34: Month 2
A35: Laminate finishing | B35: In progress | C35: 15 | D35: =D33 -> 46037 | E35: =D35+C35 -> 46052 | I35: Mix of teams : In house & external
A36: Grooves, T patti, mirrors | B36: Not started | C36: 15 | D36: =E44 -> 46062 | E36: =D36+C36 -> 46077
A37: Veneer finishing | B37: In progress | D37: =D35 -> 46037 | E37: =D37+C37 -> 46037
A38: Civil finishing | B38: In progress | C38: 8 | D38: =D36 -> 46062 | E38: =D38+C38 -> 46070
A39: Electricals - phase 2 | B39: Not started | C39: =E39-D39 -> 35 | D39: =D40 -> 46052 | E39: =E41 -> 46087 | F39: Electricals (95%) | G39: Month 2
A40: Light fixing | B40: Not started | C40: 10 | D40: =E35 -> 46052 | E40: =D40+C40 -> 46062
A41: Hanging/ decor lights | B41: Not started | C41: 10 | D41: =E36 -> 46077 | E41: =D41+C41 -> 46087 | I41: Order to be made in Month 2
A42: Paint & Polish | B42: Not started | C42: =E42-D42 -> 25 | D42: =D43 -> 46037 | E42: =E45 -> 46062 | F42: Paint & polish (95%) | G42: Month 2 & 3 | H42: Strictly no PU
A43: Ceiling | B43: Not started | C43: 15 | D43: =D33 -> 46037 | E43: =D43+C43 -> 46052 | H43: No Melamine
A44: Wall paints | B44: Not started | C44: 15 | D44: =E43-5 -> 46047 | E44: =D44+C44 -> 46062
A45: Texture paint | B45: Not started | C45: 10 | D45: =E44-10 -> 46052 | E45: =D45+C45 -> 46062
A46: melamine spray - veneer | B46: Not started | D46: =E45-10 -> 46052 | E46: =D46+C46 -> 46052
A47: PU works | B47: Not started | D47: =E46-10 -> 46042 | E47: =D47+C47 -> 46042
A48: Cleaning snags decor | B48: Not started | C48: =E48-D48 -> 30 | D48: =D49 -> 46062 | E48: =E51 -> 46092 | F48: Snags/ decor/ photoshoot | G48: Month 3 & 4
A49: Deep cleaning | B49: Not started | C49: 10 | D49: =E44 -> 46062 | E49: =D49+C49 -> 46072
A50: Buffer & snags | B50: Not started | C50: 10 | D50: =E49 -> 46072 | E50: =D50+C50 -> 46082
A51: Decor & photoshoot | B51: Not started | C51: 10 | D51: =E50 -> 46082 | E51: =D51+C51 -> 46092
A67: Rahul Dhanawat- schedule
A69: sr no | B69: agency | C69: duration | D69: start date | E69: end date
A70: 1 | B70: carpentry | C70: 50 days | D70: 46025 | E70: 46076
A71: 2 | B71: civil | C71: 20 days | D71: 46025 | E71: 46045
A72: 3 | B72: plumbing | C72: 10 days | D72: 46098 | E72: 46108
A73: 4 | B73: electrical | C73: 10 days | D73: 46098 | E73: 46108
A74: 5 | B74: pop | C74: 10 days | D74: 46025 | E74: 46035
A75: 6 | B75: painting | C75: 60 days | D75: 46049 | E75: 46108
A76: 7 | B76: deep cleaning | C76: 10 days | D76: 46108 | E76: 46118

Sheet loose items alisha  mahesh
A4: Sr.No | B4: Id | C4: Item Name | D4: Category | E4: Item Details | F4: Description | G4: UOM | H4: Elemantra Rates | J4: Quantity 14.03.2025 | K4: Amount | L4: Rate vendor | M4: Area | N4: Difference Amount | O4: Amount | P4: amount vendor | Q4: Location | R4: Remark
A5: Carpentry
A6: Living Room/Dining
A7: 1 | C7: Carpentry | D7: Dining Console | E7: MDF Finish | G7: Sqft | K7: 3000 | L7: 1950 | M7: 15 | N7: =M7*L7 -> 29250 | O7: =M7*K7 -> 45000 | P7: =L7*M7 -> 29250 | S7: 15000
A8: Mother's Bedroom | N8: =M8*L8 -> 0
A9: 1 | B9: CP 46 | C9: =VLOOKUP($B9,'Rate card'!$A$4:$G1003,2,FALSE) -> Carpentry | D9: Bed side table | E9: =VLOOKUP($B9,'Rate card'!$A$4:$G1003,4,FALSE) -> Laminate Finish | F9: =VLOOKUP($B9,'Rate card'!$A$4:$G1003,5,FALSE) -> MR ply + Inside laminate + finish laminate (1 Drawer) | G9: =VLOOKUP($B9,'Rate card'!$A$4:$G1003,6,FALSE) -> Nos | H9: 20000 | J9: 2 | K9: =H9*J9 -> 40000 | L9: 13000 | M9: 2 | N9: =M9*L9 -> 26000 | O9: =M9*H9 -> 40000 | P9: =M9*L9 -> 26000 | Q9: Bed side table | S9: 16000
A10: Samar's Bedroom | N10: =M10*L10 -> 0
A11: 1 | B11: CP 46 | C11: =VLOOKUP($B11,'Rate card'!$A$4:$G1003,2,FALSE) -> Carpentry | D11: Bed side table | E11: =VLOOKUP($B11,'Rate card'!$A$4:$G1003,4,FALSE) -> Laminate Finish | F11: =VLOOKUP($B11,'Rate card'!$A$4:$G1003,5,FALSE) -> MR ply + Inside laminate + finish laminate (1 Drawer) | G11: =VLOOKUP($B11,'Rate card'!$A$4:$G1003,6,FALSE) -> Nos | H11: 20000 | J11: 1 | K11: =H11*J11 -> 20000 | L11: 13000 | M11: 2 | N11: =M11*L11 -> 26000 | O11: =M11*H11 -> 40000 | P11: =M11*L11 -> 26000 | Q11: Bed side table | S11: 22000
A12: 2 | B12: CP 49 | C12: =VLOOKUP($B12,'Rate card'!$A$4:$G1003,2,FALSE) -> Carpentry | D12: =VLOOKUP($B12,'Rate card'!$A$4:$G1003,3,FALSE) -> Study Table | E12: =VLOOKUP($B12,'Rate card'!$A$4:$G1003,4,FALSE) -> Laminate Finish | F12: =VLOOKUP($B12,'Rate card'!$A$4:$G1003,5,FALSE) -> MR ply + Inside laminate + finish laminate (2 pencil drawers) | G12: =VLOOKUP($B12,'Rate card'!$A$4:$G1003,6,FALSE) -> Rft | H12: 4500 | J12: 4 | K12: =H12*J12 -> 18000 | L12: 2925 | M12: 4.5 | N12: =M12*L12 -> 13162.5 | P12: =M12*L12 -> 13162.5 | Q12: Study table
A13: Ranbeer's Bedroom | N13: =M13*L13 -> 0
A14: 1 | B14: CP 46 | C14: =VLOOKUP($B14,'Rate card'!$A$4:$G1003,2,FALSE) -> Carpentry | D14: Bed side table | E14: =VLOOKUP($B14,'Rate card'!$A$4:$G1003,4,FALSE) -> Laminate Finish | F14: =VLOOKUP($B14,'Rate card'!$A$4:$G1003,5,FALSE) -> MR ply + Inside laminate + finish laminate (1 Drawer) | G14: =VLOOKUP($B14,'Rate card'!$A$4:$G1003,6,FALSE) -> Nos | H14: 20000 | J14: 2 | K14: =H14*J14 -> 40000 | L14: 13000 | M14: 2 | N14: =M14*L14 -> 26000 | O14: =M14*H14 -> 40000 | P14: =M14*L14 -> 26000 | Q14: Bed side table | S14: 22000
A15: 2 | B15: CP 49 | C15: =VLOOKUP($B15,'Rate card'!$A$4:$G1003,2,FALSE) -> Carpentry | D15: =VLOOKUP($B15,'Rate card'!$A$4:$G1003,3,FALSE) -> Study Table | E15: =VLOOKUP($B15,'Rate card'!$A$4:$G1003,4,FALSE) -> Laminate Finish | F15: =VLOOKUP($B15,'Rate card'!$A$4:$G1003,5,FALSE) -> MR ply + Inside laminate + finish laminate (2 pencil drawers) | G15: =VLOOKUP($B15,'Rate card'!$A$4:$G1003,6,FALSE) -> Rft | H15: 4500 | J15: 4 | K15: =H15*J15 -> 18000 | L15: 2925 | M15: 5 | N15: =M15*L15 -> 14625 | O15: =M15*H15 -> 22500 | P15: =M15*L15 -> 14625 | Q15: Study table | S15: 30000
A16: Master bed room | N16: =M16*L16 -> 0 | O16: =M16*H16 -> 0
A17: 3 | B17: CP 46 | C17: Carpentry | D17: Bed side table | E17: Laminate Finish | F17: MR ply + Inside laminate + finish laminate (1 Drawer) | G17: Nos | H17: 20000 | J17: 2 | K17: =H17*J17 -> 40000 | M17: 2 | N17: =L17*H17 -> 0 | O17: =M17*H17 -> 40000 | P17: =O17*N17 -> 0 | Q17: Bed side table | S17: 22000
A18: 1 | B18: CP 25 | C18: =VLOOKUP($B18,'Rate card'!$A$4:$G1003,2,FALSE) -> Carpentry | D18: TV unit | E18: MDF Finish | F18: =VLOOKUP($B18,'Rate card'!$A$4:$G1003,5,FALSE) -> MR ply + Inside laminate + finish laminate | G18: R ft | H18: 4500 | J18: 7.25 | K18: =H18*J18 -> 32625 | L18: 2925 | M18: 9 | N18: =M18*L18 -> 26325 | O18: =M18*H18 -> 40500 | P18: =M18*L18 -> 26325 | Q18: TV unit | S18: 25000
A19: Master Toilet | N19: =M19*L19 -> 0 | O19: =M19*H19 -> 0
A20: 1 | B20: CP 25 | C20: =VLOOKUP($B20,'Rate card'!$A$4:$G1003,2,FALSE) -> Carpentry | D20: =VLOOKUP($B20,'Rate card'!$A$4:$G1003,3,FALSE) -> Carcass Storage | E20: =VLOOKUP($B20,'Rate card'!$A$4:$G1003,4,FALSE) -> Laminate Finish | F20: =VLOOKUP($B20,'Rate card'!$A$4:$G1003,5,FALSE) -> MR ply + Inside laminate + finish laminate | G20: =VLOOKUP($B20,'Rate card'!$A$4:$G1003,6,FALSE) -> Sqft | H20: =VLOOKUP($B20,'Rate card'!$A$4:$J1003,8,FALSE) -> 1800 | J20: 10 | K20: =H20*J20 -> 18000 | L20: 1170 | M20: 10 | N20: =M20*L20 -> 11700 | P20: =M20*L20 -> 11700 | Q20: vanity
A21: Mother's Toilet | N21: =M21*L21 -> 0
A22: 1 | B22: CP 25 | C22: =VLOOKUP($B22,'Rate card'!$A$4:$G1003,2,FALSE) -> Carpentry | D22: =VLOOKUP($B22,'Rate card'!$A$4:$G1003,3,FALSE) -> Carcass Storage | E22: =VLOOKUP($B22,'Rate card'!$A$4:$G1003,4,FALSE) -> Laminate Finish | F22: =VLOOKUP($B22,'Rate card'!$A$4:$G1003,5,FALSE) -> MR ply + Inside laminate + finish laminate | G22: =VLOOKUP($B22,'Rate card'!$A$4:$G1003,6,FALSE) -> Sqft | H22: =VLOOKUP($B22,'Rate card'!$A$4:$J1003,8,FALSE) -> 1800 | J22: 6 | K22: =H22*J22 -> 10800 | L22: 1170 | M22: 6 | N22: =M22*L22 -> 7020 | P22: =M22*L22 -> 7020 | Q22: vanity
A23: 2 | B23: CP 25 | C23: =VLOOKUP($B23,'Rate card'!$A$4:$G1003,2,FALSE) -> Carpentry | D23: =VLOOKUP($B23,'Rate card'!$A$4:$G1003,3,FALSE) -> Carcass Storage | E23: =VLOOKUP($B23,'Rate card'!$A$4:$G1003,4,FALSE) -> Laminate Finish | F23: =VLOOKUP($B23,'Rate card'!$A$4:$G1003,5,FALSE) -> MR ply + Inside laminate + finish laminate | G23: =VLOOKUP($B23,'Rate card'!$A$4:$G1003,6,FALSE) -> Sqft | H23: 1800 | J23: 15 | K23: =J23*H23 -> 27000 | L23: 1170 | M23: 15 | N23: =M23*L23 -> 17550 | O23: =M23*H23 -> 27000 | P23: =M23*L23 -> 17550 | Q23: vanity above storage | S23: 10000
A24: Samar's Toilet | N24: =M24*L24 -> 0 | O24: =M24*H24 -> 0
A25: 1 | B25: CP 25 | C25: =VLOOKUP($B25,'Rate card'!$A$4:$G1003,2,FALSE) -> Carpentry | D25: =VLOOKUP($B25,'Rate card'!$A$4:$G1003,3,FALSE) -> Carcass Storage | E25: =VLOOKUP($B25,'Rate card'!$A$4:$G1003,4,FALSE) -> Laminate Finish | F25: =VLOOKUP($B25,'Rate card'!$A$4:$G1003,5,FALSE) -> MR ply + Inside laminate + finish laminate | G25: =VLOOKUP($B25,'Rate card'!$A$4:$G1003,6,FALSE) -> Sqft | H25: =VLOOKUP($B25,'Rate card'!$A$4:$J1003,8,FALSE) -> 1800 | J25: 6 | K25: =H25*J25 -> 10800 | L25: 1170 | M25: 6 | N25: =M25*L25 -> 7020 | P25: =M25*L25 -> 7020 | Q25: vanity
A26: 2 | B26: CP 25 | C26: =VLOOKUP($B26,'Rate card'!$A$4:$G1003,2,FALSE) -> Carpentry | D26: =VLOOKUP($B26,'Rate card'!$A$4:$G1003,3,FALSE) -> Carcass Storage | E26: =VLOOKUP($B26,'Rate card'!$A$4:$G1003,4,FALSE) -> Laminate Finish | F26: =VLOOKUP($B26,'Rate card'!$A$4:$G1003,5,FALSE) -> MR ply + Inside laminate + finish laminate | G26: =VLOOKUP($B26,'Rate card'!$A$4:$G1003,6,FALSE) -> Sqft | H26: 1800 | J26: 15 | K26: =J26*H26 -> 27000 | L26: 1170 | M26: 15 | N26: =M26*L26 -> 17550 | O26: =M26*H26 -> 27000 | P26: =M26*L26 -> 17550 | Q26: vanity above storage | S26: 10000
A27: Ranbeer's Toilet | N27: =M27*L27 -> 0
A28: 1 | B28: CP 25 | C28: =VLOOKUP($B28,'Rate card'!$A$4:$G1003,2,FALSE) -> Carpentry | D28: =VLOOKUP($B28,'Rate card'!$A$4:$G1003,3,FALSE) -> Carcass Storage | E28: =VLOOKUP($B28,'Rate card'!$A$4:$G1003,4,FALSE) -> Laminate Finish | F28: =VLOOKUP($B28,'Rate card'!$A$4:$G1003,5,FALSE) -> MR ply + Inside laminate + finish laminate | G28: =VLOOKUP($B28,'Rate card'!$A$4:$G1003,6,FALSE) -> Sqft | H28: =VLOOKUP($B28,'Rate card'!$A$4:$J1003,8,FALSE) -> 1800 | J28: 6 | K28: =H28*J28 -> 10800 | L28: 1170 | M28: 6 | N28: =M28*L28 -> 7020 | P28: =M28*L28 -> 7020 | Q28: vanity
K29: =SUM(K7:K28) -> 316025 | N29: =SUM(N7:N28) -> 229222.5
O30: =SUM(O6:O28) -> 322000 | P30: =SUM(P6:P28) -> 229222.5 | S30: =SUM(S7:S29) -> 172000 | U30: =O30/1.25 -> 257600

Sheet R1
A6: Date : | B6: 45722 | E6: Project Code :
A7: Client Name : | B7: Rahul Dhanawat | E7: Quotation Revision : | F7: 0
A8: Address : | B8: 10BKC | E8: Elemantra Contact Person : | F8: Payal- 93724 07848
A10: Quotation Summary | G10: SR.NO | H10: Description | I10: Amount
B11: Area in Sqft | D11: 1673 | G11: 1 | H11: Loose furniture | I11: =J206 -> 415000
A12: SR.NO | B12: Description | D12: Amount | G12: 2 | H12: Additional items | I12: =J221 -> 2044935
A13: 1 | B13: Civil | D13: =J39 -> 979240 | H13: Total B | I13: =SUM(I11:I12) -> 2459935
A14: 2 | B14: Plumbing | D14: =J43 -> 245000 | G14: Total A+B | I14: =D21+I13 -> 9696162.8
A15: 3 | B15: Electrical | D15: =J46 -> 585550 | G15: GST 18% extra
A16: 4 | B16: POP | D16: =J54 -> 547340
A17: 5 | B17: Carpentry | D17: =J146 -> 3569150
A18: 6 | B18: Painting | D18: =J151 -> 308478.5
A19: 7 | B19: Miscellenious | D19: =J156 -> 120000
A20: 8 | B20: Design Consultation Fees(10%) | D20: =(SUM(D12:D19)+I13)*0.1 -> 881469.35
B21: Total A | D21: =SUM(D13:D20) -> 7236227.8
B22: Per Sqft Rate | D22: =(D21/D11) -> 4325.3006
A24: Sr.No | B24: Id | C24: Item Name | D24: Category | E24: Item Details | F24: Description | G24: UOM | H24: Elemantra Rates | I24: Quantity | J24: Amount | K24: Location | N24: Vendor Rate | O24: Amount
A25: Civil
A26: 1 | B26: D2 | C26: =VLOOKUP($B26,'Rate card'!$A$4:$G236,2,FALSE) -> Demolition | D26: =VLOOKUP($B26,'Rate card'!$A$4:$G236,3,FALSE) -> Brickwall - 6" | E26: =VLOOKUP($B26,'Rate card'!$A$4:$G236,4,FALSE) -> NA | F26: =VLOOKUP($B26,'Rate card'!$A$4:$G236,5,FALSE) -> Demolition | G26: =VLOOKUP($B26,'Rate card'!$A$4:$G236,6,FALSE) -> Sqft | H26: 500 | I26: =36+21 -> 57 | J26: =I26*H26 -> 28500 | K26: Kitchen & common toilet | L26: 22 | O26: =VLOOKUP($B26,'Rate card'!$A$4:$J236,7,FALSE) -> 20
A27: 2 | C27: Civil | D27: Brickwall - 4" | F27: Providing and laying 4" (100 MM) brick partition wall with good quality bricks well burnt 1st class in cement mortar 1:4 (1 cement : 4 coarse sand) including providing 2 nos of 6mm dia MS round bars at every IV course including scaffolding, curing, raking out joints etc. complete. | G27: =G26 -> Sqft | H27: 150 | I27: 24 | J27: =I27*H27 -> 3600 | L27: 160
A28: 3 | C28: Civil | D28: Kitchen wall tiles | E28: Upto( 4' x 2' ) tiles laying | F28: Laying of Wall tiles of approved colour and size as per drawing, over 20 mm thick cement mortar 1 : 4 ( 1 cement : 4 coarse sand ) and jointed with white cement slurry admixed with matching pigment to match the shade of tile & Grouting and spacer to be included. | G28: Sqft | H28: 140 | I28: 184 | J28: =I28*H28 -> 25760 | K28: Common toilet wall | L28: 120
A29: 4 | C29: Civil | D29: Bathroom wall tiles | E29: Upto( 4' x 2' ) tiles laying | F29: Laying of Wall tiles of approved colour and size as per drawing, over 20 mm thick cement mortar 1 : 4 ( 1 cement : 4 coarse sand ) and jointed with white cement slurry admixed with matching pigment to match the shade of tile & Grouting and spacer to be included. | G29: Sqft | H29: 140 | I29: 1930 | J29: =I29*H29 -> 270200 | K29: Toilets | L29: 120
A30: 5 | B30: C23 | C30: =VLOOKUP($B30,'Rate card'!$A$4:$G236,2,FALSE) -> Civil | D30: =VLOOKUP($B30,'Rate card'!$A$4:$G236,3,FALSE) -> Kitchen platform | E30: =VLOOKUP($B30,'Rate card'!$A$4:$G236,4,FALSE) -> Fully Modular Kitchen - Granite/Marble | F30: =VLOOKUP($B30,'Rate card'!$A$4:$G236,5,FALSE) -> Laying marble (18mm thk) of approved colour, shade and size on the platform as per drawing / flooring pattern, matching of grain, laid on a levelled, neat cement base with adhesive of approved make (laticrete) grouted of matching colour pigment to match the shade of stone and protection of floor to be taken into account.(cement concrete base taken into account in the civil works ) | G30: =VLOOKUP($B30,'Rate card'!$A$4:$G236,6,FALSE) -> Sqft | H30: 500 | I30: 36 | J30: =I30*H30 -> 18000 | K30: Kitchen | O30: =VLOOKUP($B30,'Rate card'!$A$4:$J236,7,FALSE) -> 150
A31: 6 | B31: C23 | C31: =VLOOKUP($B31,'Rate card'!$A$4:$G236,2,FALSE) -> Civil | D31: Utility platfrom | E31: =VLOOKUP($B31,'Rate card'!$A$4:$G236,4,FALSE) -> Fully Modular Kitchen - Granite/Marble | F31: =VLOOKUP($B31,'Rate card'!$A$4:$G236,5,FALSE) -> Laying marble (18mm thk) of approved colour, shade and size on the platform as per drawing / flooring pattern, matching of grain, laid on a levelled, neat cement base with adhesive of approved make (laticrete) grouted of matching colour pigment to match the shade of stone and protection of floor to be taken into account.(cement concrete base taken into account in the civil works ) | G31: =VLOOKUP($B31,'Rate card'!$A$4:$G236,6,FALSE) -> Sqft | H31: 500 | I31: 10 | J31: =I31*H31 -> 5000 | K31: utility | O31: =VLOOKUP($B31,'Rate card'!$A$4:$J236,7,FALSE) -> 150
A32: 7 | C32: Civil | D32: Floor Tiles | F32: Laying of floor tiles of approved colour and size as per drawing, over 20 mm thick cement mortar 1 : 4 ( 1 cement : 4 coarse sand ) and jointed with white cement slurry admixed with matching pigment to match the shade of tile & Grouting and spacer to be included. | G32: Sqft | H32: 140 | I32: 1673 | J32: =H32*I32 -> 234220 | K32: All areas
A33: 8 | B33: C14 | C33: =VLOOKUP($B33,'Rate card'!$A$4:$G236,2,FALSE) -> Civil | D33: =VLOOKUP($B33,'Rate card'!$A$4:$G236,3,FALSE) -> Floor PCC | E33: =VLOOKUP($B33,'Rate card'!$A$4:$G236,4,FALSE) | F33: =VLOOKUP($B33,'Rate card'!$A$4:$G236,5,FALSE) -> P / L 50-75mm average thickness Plain Cement Concrete 1:2:4 (1 cement : 2 coarse sand : 4 aggregate, 20mm and down gauge) , tamped, spaded, trowelled and smooth finish. | G33: =VLOOKUP($B33,'Rate card'!$A$4:$G236,6,FALSE) -> Sqft | H33: =VLOOKUP($B33,'Rate card'!$A$4:$J236,8,FALSE) -> 120 | I33: 1673 | J33: =H33*I33 -> 200760 | K33: All areas | N33: =VLOOKUP($B33,'Rate card'!$A$4:$J236,7,FALSE) -> 75 | O33: =I33*N33 -> 125475
A34: 9 | B34: C13 | C34: =VLOOKUP($B34,'Rate card'!$A$4:$G236,2,FALSE) -> Civil | D34: Wall Skirting | E34: =VLOOKUP($B34,'Rate card'!$A$4:$G236,4,FALSE) | F34: Laying of floor tiles of approved colour and size as per drawing, over 20 mm thick cement mortar 1 : 4 ( 1 cement : 4 coarse sand ) and jointed with white cement slurry admixed with matching pigment to match the shade of tile & Grouting and spacer to be included. | G34: =VLOOKUP($B34,'Rate card'!$A$4:$G236,6,FALSE) -> Rft | H34: 140 | I34: 450 | J34: =H34*I34 -> 63000 | K34: All areas | N34: =VLOOKUP($B34,'Rate card'!$A$4:$J236,7,FALSE) -> 40 | O34: =I34*N34 -> 18000
A35: 10 | B35: C15 | C35: =VLOOKUP($B35,'Rate card'!$A$4:$G236,2,FALSE) -> Civil | D35: =VLOOKUP($B35,'Rate card'!$A$4:$G236,3,FALSE) -> Granite frames | E35: =VLOOKUP($B35,'Rate card'!$A$4:$G236,4,FALSE) -> Single patti | F35: =VLOOKUP($B35,'Rate card'!$A$4:$G236,5,FALSE) -> Granite Frame – up to 6 Inches width {Including Bevelling+ Cutting+ Polishing}. Excludes Granite cost | G35: =VLOOKUP($B35,'Rate card'!$A$4:$G236,6,FALSE) -> Rft | H35: =VLOOKUP($B35,'Rate card'!$A$4:$J236,8,FALSE) -> 130 | I35: 150 | J35: =H35*I35 -> 19500 | K35: Living ,kitchen bed rooms & Toilets | N35: =VLOOKUP($B35,'Rate card'!$A$4:$J236,7,FALSE) -> 80 | O35: =I35*N35 -> 12000
A36: 11 | B36: C27 | C36: =VLOOKUP($B36,'Rate card'!$A$4:$G236,2,FALSE) -> Civil | D36: =VLOOKUP($B36,'Rate card'!$A$4:$G236,3,FALSE) -> Brickbat | E36: =VLOOKUP($B36,'Rate card'!$A$4:$G236,4,FALSE) | F36: =VLOOKUP($B36,'Rate card'!$A$4:$G236,5,FALSE) -> Providing & laying brickbat coba (6") with PCC | G36: =VLOOKUP($B36,'Rate card'!$A$4:$G236,6,FALSE) -> Sqft | H36: =VLOOKUP($B36,'Rate card'!$A$4:$J236,8,FALSE) -> 200 | I36: 226 | J36: =H36*I36 -> 45200 | K36: toilets | N36: =VLOOKUP($B36,'Rate card'!$A$4:$J236,7,FALSE) -> 150 | O36: =I36*N36 -> 33900
A37: 12 | B37: C30 | C37: =VLOOKUP($B37,'Rate card'!$A$4:$G236,2,FALSE) -> Civil | D37: =VLOOKUP($B37,'Rate card'!$A$4:$G236,3,FALSE) -> Waterproofing | E37: Floor & walls | F37: =VLOOKUP($B37,'Rate card'!$A$4:$G236,5,FALSE) -> Waterproofing with 2 coats | G37: =VLOOKUP($B37,'Rate card'!$A$4:$G236,6,FALSE) -> Sqft | H37: =VLOOKUP($B37,'Rate card'!$A$4:$J236,8,FALSE) -> 80 | I37: 350 | J37: =H37*I37 -> 28000 | K37: toilets | N37: =VLOOKUP($B37,'Rate card'!$A$4:$J236,7,FALSE) -> 50 | O37: =I37*N37 -> 17500
A38: 13 | B38: C45 | C38: =VLOOKUP($B38,'Rate card'!$A$4:$G236,2,FALSE) -> Civil | D38: =VLOOKUP($B38,'Rate card'!$A$4:$G236,3,FALSE) -> Vanity counter | E38: =VLOOKUP($B38,'Rate card'!$A$4:$G236,4,FALSE) -> Granite/Marble | F38: =VLOOKUP($B38,'Rate card'!$A$4:$G236,5,FALSE) -> Laying marble (18mm thk) of approved colour, shade and size on the platform as per drawing / flooring pattern, matching of grain, laid on a levelled, neat cement base with adhesive of approved make (laticrete) grouted of matching colour pigment to match the shade of stone and protection of floor to be taken into account.(cement concrete base taken into account in the civil works ) | G38: =VLOOKUP($B38,'Rate card'!$A$4:$G236,6,FALSE) -> Rft | H38: =VLOOKUP($B38,'Rate card'!$A$4:$J236,8,FALSE) -> 1500 | I38: 25 | J38: =H38*I38 -> 37500 | K38: Toilets | N38: =VLOOKUP($B38,'Rate card'!$A$4:$J236,7,FALSE) -> 1000 | O38: =I38*N38 -> 25000
I39: Total | J39: =SUM(J26:J38) -> 979240
A40: Plumbing
A41: 1 | B41: PL 2 | C41: Plumbing | D41: Bathroom Plumbing | E41: CP fitting work (1 WC+ 1Shower and divertor + 1 Basin + 1 Geyser) | F41: cp fiting and sanitary ware fixing in a bathroom (only fitting charges) | G41: per bathroom | H41: 45000 | I41: 5 | J41: =H41*I41 -> 225000 | K41: All Toilets, | N41: =VLOOKUP($B41,'Rate card'!$A$4:$J236,7,FALSE) -> 8000 | O41: =I41*N41 -> 40000
A42: 2 | B42: PL 3 | C42: =VLOOKUP($B42,'Rate card'!$A$4:$G236,2,FALSE) -> Plumbing | D42: =VLOOKUP($B42,'Rate card'!$A$4:$G236,3,FALSE) -> Kitchen Plumbing | E42: =VLOOKUP($B42,'Rate card'!$A$4:$G236,4,FALSE) -> Internal Concealed work (1 Basin + 1 Geyser) | F42: =VLOOKUP($B42,'Rate card'!$A$4:$G236,5,FALSE) -> all plumbing concealed wall and floor CPVC and UPVC pipes and chipping and replastering work | G42: =VLOOKUP($B42,'Rate card'!$A$4:$G236,6,FALSE) -> per kitchen | H42: 20000 | I42: 1 | J42: =H42*I42 -> 20000 | K42: Kitchen & Utility | N42: =VLOOKUP($B42,'Rate card'!$A$4:$J236,7,FALSE) -> 5500 | O42: =I42*N42 -> 5500
I43: Total | J43: =SUM(J41,J42) -> 245000
A44: Electrical
A45: 1 | B45: E 1 | C45: Electrical | D45: 5A Switch socket, Light points,AC point, Fan point, Circuit wiring, DB Dressing | E45: new 5A Switch & Socket, light points, 15A, AC point, fan point from DB on wall include the price for wire and conduits, chipping and replastering on wall is included | F45: NOTE - The rates include fixingof switch / socket in position, effecting proper connections testing and commissioning of lighting fixtures and fans including lamps, control gear, power factor improvement capacitor and all fixing accessories that may be required to check. | G45: All areas | H45: 350 | I45: 1673 | J45: =H45*I45 -> 585550 | K45: All areas | N45: =VLOOKUP($B45,'Rate card'!$A$4:$J236,7,FALSE) -> 625 | O45: =I45*N45 -> 1045625
I46: Total | J46: =SUM(J45) -> 585550
A47: Pop/Falsceiling
A48: 1 | B48: FC 3 | C48: =VLOOKUP($B48,'Rate card'!$A$4:$G236,2,FALSE) -> False Ceiling | D48: =VLOOKUP($B48,'Rate card'!$A$4:$G236,3,FALSE) -> Gypsum Board Ceiling | E48: =VLOOKUP($B48,'Rate card'!$A$4:$G236,4,FALSE) -> Saint Gobain/Gyproc Board + local A Grade channel | F48: =VLOOKUP($B48,'Rate card'!$A$4:$G236,5,FALSE) -> 12.5mm thick gypsum board, with local A Grade Channel including all material, labour, transportation etc | Ceiling Channel and Intermediate Channel at 900mm c/c & Ceiling Section at 450mm c/c | G48: =VLOOKUP($B48,'Rate card'!$A$4:$G236,6,FALSE) -> Sqft | H48: 120 | I48: 1447 | J48: =H48*I48 -> 173640 | K48: All areas
A49: 2 | B49: FC 4 | C49: =VLOOKUP($B49,'Rate card'!$A$4:$G236,2,FALSE) -> False Ceiling | D49: =VLOOKUP($B49,'Rate card'!$A$4:$G236,3,FALSE) -> Gypsum Board Cove | E49: =VLOOKUP($B49,'Rate card'!$A$4:$G236,4,FALSE) -> Gypsum cove | F49: =VLOOKUP($B49,'Rate card'!$A$4:$G236,5,FALSE) -> 12.5mm thick gypsum board, with local A Grade Channel including all material, labour, transportation etc | Ceiling Channel and Intermediate Channel at 900mm c/c & Ceiling Section at 450mm c/c | G49: =VLOOKUP($B49,'Rate card'!$A$4:$G236,6,FALSE) -> Rft | H49: 120 | I49: 800 | J49: =H49*I49 -> 96000 | K49: All areas
A50: 3 | B50: FC 5 | C50: =VLOOKUP($B50,'Rate card'!$A$4:$G236,2,FALSE) -> False Ceiling | D50: =VLOOKUP($B50,'Rate card'!$A$4:$G236,3,FALSE) -> Hilux Board ceiling | E50: =VLOOKUP($B50,'Rate card'!$A$4:$G236,4,FALSE) -> Hilux Board + local A Grade channel | F50: =VLOOKUP($B50,'Rate card'!$A$4:$G236,5,FALSE) -> 8mm Ramco hilux board, with local A Grade Channel including all material, labour, transportation etc | Ceiling Channel and Intermediate Channel at 900mm c/c & Ceiling Section at 450mm c/c | G50: =VLOOKUP($B50,'Rate card'!$A$4:$G236,6,FALSE) -> Sqft | H50: 200 | I50: 226 | J50: =H50*I50 -> 45200 | K50: Toilets | N50: =VLOOKUP($B50,'Rate card'!$A$4:$J236,7,FALSE) -> 120 | O50: =I50*N50 -> 27120
A51: 4 | B51: FC 11 | C51: =VLOOKUP($B51,'Rate card'!$A$4:$G236,2,FALSE) -> POP | D51: =VLOOKUP($B51,'Rate card'!$A$4:$G236,3,FALSE) -> POP Punning | E51: =VLOOKUP($B51,'Rate card'!$A$4:$G236,4,FALSE) -> POP Punning (Plum) 12-25mm thick | F51: =VLOOKUP($B51,'Rate card'!$A$4:$G236,5,FALSE) -> Providing and applying 12-25 mm thick POP punning on wall /ceiling including scrapping and hacking the existing finished surface and applying plaster of paris in proper line and levels etc. complete. | G51: =VLOOKUP($B51,'Rate card'!$A$4:$G236,6,FALSE) -> Sqft | H51: 45 | I51: 4500 | J51: =H51*I51 -> 202500 | K51: All areas - wall punning
A52: 5 | B52: FC 12 | C52: =VLOOKUP($B52,'Rate card'!$A$4:$G236,2,FALSE) -> POP | D52: =VLOOKUP($B52,'Rate card'!$A$4:$G236,3,FALSE) -> POP Punning dhar | E52: =VLOOKUP($B52,'Rate card'!$A$4:$G236,4,FALSE) -> POP Punning (Plum) 12-25mm thick | F52: =VLOOKUP($B52,'Rate card'!$A$4:$G236,5,FALSE) -> Providing and applying 12-25 mm thick POP punning on wall /ceiling including scrapping and hacking the existing finished surface and applying plaster of paris in proper line and levels etc. complete. | G52: =VLOOKUP($B52,'Rate card'!$A$4:$G236,6,FALSE) -> Rft | H52: 25 | I52: 600 | J52: =H52*I52 -> 15000 | K52: All areas - Patch works and wall levelling purpose
A53: 6 | B53: FC 17 | C53: =VLOOKUP($B53,'Rate card'!$A$4:$G236,2,FALSE) -> False Ceiling | D53: =VLOOKUP($B53,'Rate card'!$A$4:$G236,3,FALSE) -> Light Gala cutting | E53: =VLOOKUP($B53,'Rate card'!$A$4:$G236,4,FALSE) -> NA | F53: =VLOOKUP($B53,'Rate card'!$A$4:$G236,5,FALSE) -> NA | G53: =VLOOKUP($B53,'Rate card'!$A$4:$G236,6,FALSE) -> Nos | H53: 100 | I53: 150 | J53: =H53*I53 -> 15000 | K53: All areas
I54: Total | J54: =SUM(J48:J53) -> 547340
A55: Carpentry
A56: Living Room/Dining
A57: 1 | B57: CP 111 | C57: =VLOOKUP($B57,'Rate card'!$A$4:$G236,2,FALSE) -> Carpentry | D57: Main Door | E57: =VLOOKUP($B57,'Rate card'!$A$4:$G236,4,FALSE) -> Laminate Finish | F57: =VLOOKUP($B57,'Rate card'!$A$4:$G236,5,FALSE) -> MRply + finish laminate from both sides | G57: =VLOOKUP($B57,'Rate card'!$A$4:$G236,6,FALSE) -> Nos | H57: 45000 | I57: 1 | J57: =H57*I57 -> 45000 | K57: New main door
A58: 2 | B58: CP 1 | C58: =VLOOKUP($B58,'Rate card'!$A$4:$G236,2,FALSE) -> Carpentry | D58: =VLOOKUP($B58,'Rate card'!$A$4:$G236,3,FALSE) -> Panelling with framing | E58: =VLOOKUP($B58,'Rate card'!$A$4:$G236,4,FALSE) -> Laminate Finish | F58: =VLOOKUP($B58,'Rate card'!$A$4:$G236,5,FALSE) -> MR ply + ply framing + finish laminate | G58: =VLOOKUP($B58,'Rate card'!$A$4:$G236,6,FALSE) -> Sqft | H58: 650 | I58: 20 | J58: =H58*I58 -> 13000 | K58: safety door panelling | N58: =VLOOKUP($B58,'Rate card'!$A$4:$J236,7,FALSE) -> 450 | O58: =I58*N58 -> 9000
A59: 3 | B59: CP 25 | C59: =VLOOKUP($B59,'Rate card'!$A$4:$G236,2,FALSE) -> Carpentry | D59: =VLOOKUP($B59,'Rate card'!$A$4:$G236,3,FALSE) -> Carcass Storage | E59: =VLOOKUP($B59,'Rate card'!$A$4:$G236,4,FALSE) -> Laminate Finish | F59: =VLOOKUP($B59,'Rate card'!$A$4:$G236,5,FALSE) -> MR ply + Inside laminate + finish laminate | G59: =VLOOKUP($B59,'Rate card'!$A$4:$G236,6,FALSE) -> Sqft | H59: 1800 | I59: =5*3 -> 15 | J59: =H59*I59 -> 27000 | K59: shoerack | N59: =VLOOKUP($B59,'Rate card'!$A$4:$J236,7,FALSE) -> 1350 | O59: =I59*N59 -> 20250
A60: 4 | B60: CP 25 | C60: =VLOOKUP($B60,'Rate card'!$A$4:$G236,2,FALSE) -> Carpentry | D60: =VLOOKUP($B60,'Rate card'!$A$4:$G236,3,FALSE) -> Carcass Storage | E60: =VLOOKUP($B60,'Rate card'!$A$4:$G236,4,FALSE) -> Laminate Finish | F60: =VLOOKUP($B60,'Rate card'!$A$4:$G236,5,FALSE) -> MR ply + Inside laminate + finish laminate | G60: R ft | H60: 4500 | I60: 7 | J60: =H60*I60 -> 31500 | K60: TV unit | N60: =VLOOKUP($B60,'Rate card'!$A$4:$J236,7,FALSE) -> 1350 | O60: =I60*N60 -> 9450
A61: 5 | B61: CP 25 | C61: =VLOOKUP($B61,'Rate card'!$A$4:$G236,2,FALSE) -> Carpentry | D61: =VLOOKUP($B61,'Rate card'!$A$4:$G236,3,FALSE) -> Carcass Storage | E61: =VLOOKUP($B61,'Rate card'!$A$4:$G236,4,FALSE) -> Laminate Finish | F61: =VLOOKUP($B61,'Rate card'!$A$4:$G236,5,FALSE) -> MR ply + Inside laminate + finish laminate | G61: =VLOOKUP($B61,'Rate card'!$A$4:$G236,6,FALSE) -> Sqft | H61: =VLOOKUP($B61,'Rate card'!$A$4:$J236,8,FALSE) -> 1800 | I61: =7*7 -> 49 | J61: =H61*I61 -> 88200 | K61: TV panel | N61: =VLOOKUP($B61,'Rate card'!$A$4:$J236,7,FALSE) -> 1350 | O61: =I61*N61 -> 66150
A62: 6 | B62: CP 25 | C62: =VLOOKUP($B62,'Rate card'!$A$4:$G236,2,FALSE) -> Carpentry | D62: =VLOOKUP($B62,'Rate card'!$A$4:$G236,3,FALSE) -> Carcass Storage | E62: =VLOOKUP($B62,'Rate card'!$A$4:$G236,4,FALSE) -> Laminate Finish | F62: =VLOOKUP($B62,'Rate card'!$A$4:$G236,5,FALSE) -> MR ply + Inside laminate + finish laminate | G62: =VLOOKUP($B62,'Rate card'!$A$4:$G236,6,FALSE) -> Sqft | H62: =VLOOKUP($B62,'Rate card'!$A$4:$J236,8,FALSE) -> 1800 | I62: =4*7 -> 28 | J62: =H62*I62 -> 50400 | K62: Mandir | N62: =VLOOKUP($B62,'Rate card'!$A$4:$J236,7,FALSE) -> 1350 | O62: =I62*N62 -> 37800
A63: 7 | B63: CP 25 | C63: =VLOOKUP($B63,'Rate card'!$A$4:$G236,2,FALSE) -> Carpentry | D63: =VLOOKUP($B63,'Rate card'!$A$4:$G236,3,FALSE) -> Carcass Storage | E63: =VLOOKUP($B63,'Rate card'!$A$4:$G236,4,FALSE) -> Laminate Finish | F63: =VLOOKUP($B63,'Rate card'!$A$4:$G236,5,FALSE) -> MR ply + Inside laminate + finish laminate | G63: =VLOOKUP($B63,'Rate card'!$A$4:$G236,6,FALSE) -> Sqft | H63: =VLOOKUP($B63,'Rate card'!$A$4:$J236,8,FALSE) -> 1800 | I63: =5*3.5 -> 17.5 | J63: =H63*I63 -> 31500 | K63: Console | N63: =VLOOKUP($B63,'Rate card'!$A$4:$J236,7,FALSE) -> 1350 | O63: =I63*N63 -> 23625
A64: 8 | B64: CP 6 | C64: =VLOOKUP($B64,'Rate card'!$A$4:$G236,2,FALSE) -> Carpentry | D64: =VLOOKUP($B64,'Rate card'!$A$4:$G236,3,FALSE) -> Panelling with framing | E64: =VLOOKUP($B64,'Rate card'!$A$4:$G236,4,FALSE) -> MDF | F64: =VLOOKUP($B64,'Rate card'!$A$4:$G236,5,FALSE) -> MR ply + ply framing + 12mm MDF | G64: =VLOOKUP($B64,'Rate card'!$A$4:$G236,6,FALSE) -> Sqft | H64: 600 | I64: 22 | J64: =H64*I64 -> 13200 | K64: Pelmet
A65: 9 | B65: CP 6 | C65: Carpentry | D65: Panelling with framing | E65: Moulding & Mirror | F65: Moulding & Mirror | G65: L.s | H65: 50000 | I65: 1 | J65: =H65*I65 -> 50000 | K65: Wall Panel on dinning wall
A66: 10 | B66: CP 6 | C66: Carpentry | D66: Panelling with framing | E66: =E63 -> Laminate Finish | F66: =F64 -> MR ply + ply framing + 12mm MDF | G66: =VLOOKUP($B66,'Rate card'!$A$4:$G236,6,FALSE) -> Sqft | H66: 650 | I66: 75 | J66: =H66*I66 -> 48750 | K66: Wall Panel on sofa wall
A67: 11 | B67: CP 6 | C67: Carpentry | D67: Panelling with framing | E67: =E66 -> Laminate Finish | F67: =F65 -> Moulding & Mirror | G67: =VLOOKUP($B67,'Rate card'!$A$4:$G236,6,FALSE) -> Sqft | H67: 650 | I67: 30 | J67: =H67*I67 -> 19500 | K67: Panel in Passage above shoe rack
A68: 12 | B68: CP 6 | C68: Carpentry | D68: Panelling with framing | E68: Moulding & Mirror | F68: =F66 -> MR ply + ply framing + 12mm MDF | G68: =VLOOKUP($B68,'Rate card'!$A$4:$G236,6,FALSE) -> Sqft | H68: 650 | I68: 40 | J68: =H68*I68 -> 26000 | K68: Panel in Passage
A69: Modular Kitchen
A70: 1 | B70: CP 25 | C70: =VLOOKUP($B70,'Rate card'!$A$4:$G236,2,FALSE) -> Carpentry | D70: =VLOOKUP($B70,'Rate card'!$A$4:$G236,3,FALSE) -> Carcass Storage | E70: Acrylic Finish | F70: Marine ply + Inside laminate + Acrylic Finish | G70: =VLOOKUP($B70,'Rate card'!$A$4:$G236,6,FALSE) -> Sqft | H70: 2700 | I70: 42 | J70: =H70*I70 -> 113400 | K70: undercounter
A71: 2 | B71: CP 25 | C71: =VLOOKUP($B71,'Rate card'!$A$4:$G236,2,FALSE) -> Carpentry | D71: =VLOOKUP($B71,'Rate card'!$A$4:$G236,3,FALSE) -> Carcass Storage | E71: Acrylic Finish | F71: Marine ply + Inside laminate + Acrylic Finish | G71: =VLOOKUP($B71,'Rate card'!$A$4:$G236,6,FALSE) -> Sqft | H71: 2700 | I71: =7.5*2.5+6.5*2.5+40 -> 75 | J71: =H71*I71 -> 202500 | K71: overhead+loft
A72: 3 | B72: CP 25 | C72: =VLOOKUP($B72,'Rate card'!$A$4:$G236,2,FALSE) -> Carpentry | D72: =VLOOKUP($B72,'Rate card'!$A$4:$G236,3,FALSE) -> Carcass Storage | E72: Acrylic Finish | F72: Marine ply + Inside laminate + Acrylic Finish | G72: =VLOOKUP($B72,'Rate card'!$A$4:$G236,6,FALSE) -> Sqft | H72: 2700 | I72: 28 | J72: =H72*I72 -> 75600 | K72: Pantry Storage, next to fridge
A73: 4 | B73: CP 61 | C73: =VLOOKUP($B73,'Rate card'!$A$4:$G236,2,FALSE) -> Carpentry | D73: =VLOOKUP($B73,'Rate card'!$A$4:$G236,3,FALSE) -> Kitchen Basket | E73: tandem | F73: =VLOOKUP($B73,'Rate card'!$A$4:$G236,5,FALSE) -> Basket + Channel+Fitting charges | G73: =VLOOKUP($B73,'Rate card'!$A$4:$G236,6,FALSE) -> Nos | H73: 8000 | I73: 5 | J73: =H73*I73 -> 40000 | K73: Modular kitchen
A74: 5 | B74: CP 64 | C74: =VLOOKUP($B74,'Rate card'!$A$4:$G236,2,FALSE) -> Carpentry | D74: =VLOOKUP($B74,'Rate card'!$A$4:$G236,3,FALSE) -> Wicker basket | E74: =VLOOKUP($B74,'Rate card'!$A$4:$G236,4,FALSE) -> Wicker basket | F74: =VLOOKUP($B74,'Rate card'!$A$4:$G236,5,FALSE) -> Basket + Channel+Fitting charges | G74: =VLOOKUP($B74,'Rate card'!$A$4:$G236,6,FALSE) -> Nos | H74: 6000 | I74: 2 | J74: =H74*I74 -> 12000 | K74: Modular kitchen
A75: 6 | C75: Carpentry | D75: Kitchen Sliding door | E75: Flutted glass finish | F75: Modular Kitchen | G75: Sqft | H75: 1650 | I75: =3*7 -> 21 | J75: =H75*I75 -> 34650 | K75: kitchen | N75: Scope added
A76: Utility
A77: 1 | B77: CP 25 | C77: =VLOOKUP($B77,'Rate card'!$A$4:$G236,2,FALSE) -> Carpentry | D77: =VLOOKUP($B77,'Rate card'!$A$4:$G236,3,FALSE) -> Carcass Storage | E77: =VLOOKUP($B77,'Rate card'!$A$4:$G236,4,FALSE) -> Laminate Finish | F77: Marine ply + Inside laminate + finish laminate | G77: =VLOOKUP($B77,'Rate card'!$A$4:$G236,6,FALSE) -> Sqft | H77: 1800 | I77: 21 | J77: =H77*I77 -> 37800 | K77: undercounter
A78: 2 | B78: CP 25 | C78: =VLOOKUP($B78,'Rate card'!$A$4:$G236,2,FALSE) -> Carpentry | D78: =VLOOKUP($B78,'Rate card'!$A$4:$G236,3,FALSE) -> Carcass Storage | E78: =VLOOKUP($B78,'Rate card'!$A$4:$G236,4,FALSE) -> Laminate Finish | F78: Marine ply + Inside laminate + finish laminate | G78: =VLOOKUP($B78,'Rate card'!$A$4:$G236,6,FALSE) -> Sqft | H78: 1800 | I78: 110 | J78: =H78*I78 -> 198000 | K78: Storage
A79: 3 | B79: CP 117 | C79: =VLOOKUP($B79,'Rate card'!$A$4:$G236,2,FALSE) -> Carpentry | D79: =VLOOKUP($B79,'Rate card'!$A$4:$G236,3,FALSE) -> Carcass Storage | E79: =VLOOKUP($B79,'Rate card'!$A$4:$G236,4,FALSE) -> Laminate Finish | F79: Marine ply + Inside laminate + finish laminate | G79: =VLOOKUP($B79,'Rate card'!$A$4:$G236,6,FALSE) -> Sqft | H79: 1800 | I79: 22 | J79: =H79*I79 -> 39600 | K79: Washing machine storage | N79: =VLOOKUP($B79,'Rate card'!$A$4:$J236,7,FALSE) -> 2000 | O79: =I79*N79 -> 44000
A80: Bedroom 1
A81: 1 | B81: CP 21 | C81: =VLOOKUP($B81,'Rate card'!$A$4:$G236,2,FALSE) -> Carpentry | D81: =VLOOKUP($B81,'Rate card'!$A$4:$G236,3,FALSE) -> Bed | E81: =VLOOKUP($B81,'Rate card'!$A$4:$G236,4,FALSE) -> Laminate Finish | F81: =VLOOKUP($B81,'Rate card'!$A$4:$G236,5,FALSE) -> MR ply + Inside laminate + finish laminate | G81: =VLOOKUP($B81,'Rate card'!$A$4:$G236,6,FALSE) -> Sqft | H81: 1800 | I81: 36 | J81: =H81*I81 -> 64800 | K81: Queen size Bed | N81: =VLOOKUP($B81,'Rate card'!$A$4:$J236,7,FALSE) -> 1400 | O81: =I81*N81 -> 50400
A82: 2 | B82: CP 45 | C82: =VLOOKUP($B82,'Rate card'!$A$4:$G236,2,FALSE) -> Carpentry | D82: =VLOOKUP($B82,'Rate card'!$A$4:$G236,3,FALSE) -> Headboard | E82: =VLOOKUP($B82,'Rate card'!$A$4:$G236,4,FALSE) -> Fabric Finish | F82: =VLOOKUP($B82,'Rate card'!$A$4:$G236,5,FALSE) -> MR ply panelling + Foam material and labour. Excludes Fabric cost | G82: =VLOOKUP($B82,'Rate card'!$A$4:$G236,6,FALSE) -> Sqft | H82: 1300 | I82: 14 | J82: =H82*I82 -> 18200 | K82: Headboard | N82: =VLOOKUP($B82,'Rate card'!$A$4:$J236,7,FALSE) -> 950 | O82: =I82*N82 -> 13300
A83: 3 | B83: CP 46 | C83: =VLOOKUP($B83,'Rate card'!$A$4:$G236,2,FALSE) -> Carpentry | D83: Bed side table | E83: =VLOOKUP($B83,'Rate card'!$A$4:$G236,4,FALSE) -> Laminate Finish | F83: =VLOOKUP($B83,'Rate card'!$A$4:$G236,5,FALSE) -> MR ply + Inside laminate + finish laminate (1 Drawer) | G83: =VLOOKUP($B83,'Rate card'!$A$4:$G236,6,FALSE) -> Nos | H83: 13000 | I83: 2 | J83: =H83*I83 -> 26000 | K83: Bed side table
A84: 4 | B84: CP 25 | C84: =VLOOKUP($B84,'Rate card'!$A$4:$G236,2,FALSE) -> Carpentry | D84: =VLOOKUP($B84,'Rate card'!$A$4:$G236,3,FALSE) -> Carcass Storage | E84: =VLOOKUP($B84,'Rate card'!$A$4:$G236,4,FALSE) -> Laminate Finish | F84: =VLOOKUP($B84,'Rate card'!$A$4:$G236,5,FALSE) -> MR ply + Inside laminate + finish laminate | G84: R ft | H84: 4500 | I84: 7 | J84: =H84*I84 -> 31500 | K84: TV unit + Dresser | N84: =VLOOKUP($B84,'Rate card'!$A$4:$J236,7,FALSE) -> 1350 | O84: =I84*N84 -> 9450
A85: 5 | B85: CP 25 | C85: =VLOOKUP($B85,'Rate card'!$A$4:$G236,2,FALSE) -> Carpentry | D85: =VLOOKUP($B85,'Rate card'!$A$4:$G236,3,FALSE) -> Carcass Storage | E85: =VLOOKUP($B85,'Rate card'!$A$4:$G236,4,FALSE) -> Laminate Finish | F85: =VLOOKUP($B85,'Rate card'!$A$4:$G236,5,FALSE) -> MR ply + Inside laminate + finish laminate | G85: =VLOOKUP($B85,'Rate card'!$A$4:$G236,6,FALSE) -> Sqft | H85: =VLOOKUP($B85,'Rate card'!$A$4:$J236,8,FALSE) -> 1800 | I85: 45 | J85: =H85*I85 -> 81000 | K85: Wardrobe near entrance
A86: 6 | B86: CP 3 | C86: =VLOOKUP($B86,'Rate card'!$A$4:$G236,2,FALSE) -> Carpentry | D86: =VLOOKUP($B86,'Rate card'!$A$4:$G236,3,FALSE) -> Panelling with framing | E86: =VLOOKUP($B86,'Rate card'!$A$4:$G236,4,FALSE) -> Mirror Finish | F86: =VLOOKUP($B86,'Rate card'!$A$4:$G236,5,FALSE) -> MR ply + ply framing + 5mm clear mirror | G86: =VLOOKUP($B86,'Rate card'!$A$4:$G236,6,FALSE) -> Sqft | H86: =VLOOKUP($B86,'Rate card'!$A$4:$J236,8,FALSE) -> 750 | I86: =2*5 -> 10 | J86: =H86*I86 -> 7500 | K86: Mirror
A87: 7 | B87: CP 1 | C87: Carpentry | D87: Panelling with framing | E87: =VLOOKUP($B87,'Rate card'!$A$4:$G236,4,FALSE) -> Laminate Finish | F87: MR ply + ply framing + finish laminate | G87: =VLOOKUP($B87,'Rate card'!$A$4:$G236,6,FALSE) -> Sqft | H87: =VLOOKUP($B87,'Rate card'!$A$4:$J236,8,FALSE) -> 650 | I87: 80 | J87: =H87*I87 -> 52000 | K87: Wall panel
A88: 8 | B88: CP 17 | C88: =VLOOKUP($B88,'Rate card'!$A$4:$G236,2,FALSE) -> Carpentry | D88: =VLOOKUP($B88,'Rate card'!$A$4:$G236,3,FALSE) -> Wardrobe | E88: =VLOOKUP($B88,'Rate card'!$A$4:$G236,4,FALSE) -> Laminate Finish | F88: =VLOOKUP($B88,'Rate card'!$A$4:$G236,5,FALSE) -> MR ply + Inside laminate + finish laminate. (Includes 4 pencil drawers, Handles of base rate Rs.1000/pc) | G88: =VLOOKUP($B88,'Rate card'!$A$4:$G236,6,FALSE) -> Sqft | H88: 1800 | I88: 69 | J88: =H88*I88 -> 124200 | K88: Wardrobe
A89: 9 | B89: CP 6 | C89: =VLOOKUP($B89,'Rate card'!$A$4:$G236,2,FALSE) -> Carpentry | D89: =VLOOKUP($B89,'Rate card'!$A$4:$G236,3,FALSE) -> Panelling with framing | E89: =VLOOKUP($B89,'Rate card'!$A$4:$G236,4,FALSE) -> MDF | F89: =VLOOKUP($B89,'Rate card'!$A$4:$G236,5,FALSE) -> MR ply + ply framing + 12mm MDF | G89: =VLOOKUP($B89,'Rate card'!$A$4:$G236,6,FALSE) -> Sqft | H89: 600 | I89: 22 | J89: =H89*I89 -> 13200 | K89: pelmet
A90: Bedroom 2
A91: 1 | B91: CP 21 | C91: =VLOOKUP($B91,'Rate card'!$A$4:$G236,2,FALSE) -> Carpentry | D91: =VLOOKUP($B91,'Rate card'!$A$4:$G236,3,FALSE) -> Bed | E91: =VLOOKUP($B91,'Rate card'!$A$4:$G236,4,FALSE) -> Laminate Finish | F91: =VLOOKUP($B91,'Rate card'!$A$4:$G236,5,FALSE) -> MR ply + Inside laminate + finish laminate | G91: =VLOOKUP($B91,'Rate card'!$A$4:$G236,6,FALSE) -> Sqft | H91: 2200 | I91: 40 | J91: =H91*I91 -> 88000 | K91: King size Bed, 2 internal drawers+ 1 side box | N91: =VLOOKUP($B91,'Rate card'!$A$4:$J236,7,FALSE) -> 1400 | O91: =I91*N91 -> 56000
A92: 2 | B92: CP 45 | C92: =VLOOKUP($B92,'Rate card'!$A$4:$G236,2,FALSE) -> Carpentry | D92: =VLOOKUP($B92,'Rate card'!$A$4:$G236,3,FALSE) -> Headboard | E92: =VLOOKUP($B92,'Rate card'!$A$4:$G236,4,FALSE) -> Fabric Finish | F92: =VLOOKUP($B92,'Rate card'!$A$4:$G236,5,FALSE) -> MR ply panelling + Foam material and labour. Excludes Fabric cost | G92: =VLOOKUP($B92,'Rate card'!$A$4:$G236,6,FALSE) -> Sqft | H92: 1300 | I92: 18 | J92: =H92*I92 -> 23400 | K92: Headboard | N92: =VLOOKUP($B92,'Rate card'!$A$4:$J236,7,FALSE) -> 950 | O92: =I92*N92 -> 17100
A93: 3 | B93: CP 46 | C93: =VLOOKUP($B93,'Rate card'!$A$4:$G236,2,FALSE) -> Carpentry | D93: Bed side table | E93: =VLOOKUP($B93,'Rate card'!$A$4:$G236,4,FALSE) -> Laminate Finish | F93: =VLOOKUP($B93,'Rate card'!$A$4:$G236,5,FALSE) -> MR ply + Inside laminate + finish laminate (1 Drawer) | G93: =VLOOKUP($B93,'Rate card'!$A$4:$G236,6,FALSE) -> Nos | H93: 13000 | I93: 1 | J93: =H93*I93 -> 13000 | K93: Bed side table
A94: 4 | B94: CP 49 | C94: =VLOOKUP($B94,'Rate card'!$A$4:$G236,2,FALSE) -> Carpentry | D94: =VLOOKUP($B94,'Rate card'!$A$4:$G236,3,FALSE) -> Study Table | E94: =VLOOKUP($B94,'Rate card'!$A$4:$G236,4,FALSE) -> Laminate Finish | F94: =VLOOKUP($B94,'Rate card'!$A$4:$G236,5,FALSE) -> MR ply + Inside laminate + finish laminate (2 pencil drawers) | G94: =VLOOKUP($B94,'Rate card'!$A$4:$G236,6,FALSE) -> Rft | H94: 4500 | I94: 4 | J94: =H94*I94 -> 18000 | K94: Study table
A95: 5 | B95: CP 25 | C95: =VLOOKUP($B95,'Rate card'!$A$4:$G236,2,FALSE) -> Carpentry | D95: =VLOOKUP($B95,'Rate card'!$A$4:$G236,3,FALSE) -> Carcass Storage | E95: =VLOOKUP($B95,'Rate card'!$A$4:$G236,4,FALSE) -> Laminate Finish | F95: =VLOOKUP($B95,'Rate card'!$A$4:$G236,5,FALSE) -> MR ply + Inside laminate + finish laminate | G95: =VLOOKUP($B95,'Rate card'!$A$4:$G236,6,FALSE) -> Sqft | H95: =VLOOKUP($B95,'Rate card'!$A$4:$J236,8,FALSE) -> 1800 | I95: 20 | J95: =H95*I95 -> 36000 | K95: Overhead storage
A96: 6 | B96: CP 25 | C96: =VLOOKUP($B96,'Rate card'!$A$4:$G236,2,FALSE) -> Carpentry | D96: =VLOOKUP($B96,'Rate card'!$A$4:$G236,3,FALSE) -> Carcass Storage | E96: =VLOOKUP($B96,'Rate card'!$A$4:$G236,4,FALSE) -> Laminate Finish | F96: =VLOOKUP($B96,'Rate card'!$A$4:$G236,5,FALSE) -> MR ply + Inside laminate + finish laminate | G96: =VLOOKUP($B96,'Rate card'!$A$4:$G236,6,FALSE) -> Sqft | H96: =VLOOKUP($B96,'Rate card'!$A$4:$J236,8,FALSE) -> 1800 | I96: 18 | J96: =H96*I96 -> 32400 | K96: Bookshelf
A97: 7 | B97: CP 3 | C97: =VLOOKUP($B97,'Rate card'!$A$4:$G236,2,FALSE) -> Carpentry | D97: =VLOOKUP($B97,'Rate card'!$A$4:$G236,3,FALSE) -> Panelling with framing | E97: =VLOOKUP($B97,'Rate card'!$A$4:$G236,4,FALSE) -> Mirror Finish | F97: =VLOOKUP($B97,'Rate card'!$A$4:$G236,5,FALSE) -> MR ply + ply framing + 5mm clear mirror | G97: =VLOOKUP($B97,'Rate card'!$A$4:$G236,6,FALSE) -> Sqft | H97: =VLOOKUP($B97,'Rate card'!$A$4:$J236,8,FALSE) -> 750 | I97: =2*5 -> 10 | J97: =H97*I97 -> 7500 | K97: Mirror
A98: 8 | B98: CP 108 | C98: =VLOOKUP($B98,'Rate card'!$A$4:$G236,2,FALSE) -> Carpentry | D98: =VLOOKUP($B98,'Rate card'!$A$4:$G236,3,FALSE) -> Dresser | E98: =VLOOKUP($B98,'Rate card'!$A$4:$G236,4,FALSE) -> Laminate Finish | F98: =VLOOKUP($B98,'Rate card'!$A$4:$G236,5,FALSE) -> MRply + Inside laminate + finish laminate | G98: =VLOOKUP($B98,'Rate card'!$A$4:$G236,6,FALSE) -> Sqft | H98: 1800 | I98: 6 | J98: =H98*I98 -> 10800 | K98: Dresser | N98: =VLOOKUP($B98,'Rate card'!$A$4:$J236,7,FALSE) -> 1400 | O98: =I98*N98 -> 8400
A99: 9 | B99: CP 1 | C99: Carpentry | D99: Panelling with framing | E99: =VLOOKUP($B99,'Rate card'!$A$4:$G236,4,FALSE) -> Laminate Finish | F99: MR ply + ply framing + finish laminate | G99: =VLOOKUP($B99,'Rate card'!$A$4:$G236,6,FALSE) -> Sqft | H99: =VLOOKUP($B99,'Rate card'!$A$4:$J236,8,FALSE) -> 650 | I99: 40 | J99: =H99*I99 -> 26000 | K99: Wall panel
A100: 10 | B100: CP 17 | C100: =VLOOKUP($B100,'Rate card'!$A$4:$G236,2,FALSE) -> Carpentry | D100: =VLOOKUP($B100,'Rate card'!$A$4:$G236,3,FALSE) -> Wardrobe | E100: =VLOOKUP($B100,'Rate card'!$A$4:$G236,4,FALSE) -> Laminate Finish | F100: =VLOOKUP($B100,'Rate card'!$A$4:$G236,5,FALSE) -> MR ply + Inside laminate + finish laminate. (Includes 4 pencil drawers, Handles of base rate Rs.1000/pc) | G100: =VLOOKUP($B100,'Rate card'!$A$4:$G236,6,FALSE) -> Sqft | H100: 1800 | I100: 86 | J100: =H100*I100 -> 154800 | K100: Wardrobe both
A101: 11 | B101: CP 6 | C101: =VLOOKUP($B101,'Rate card'!$A$4:$G236,2,FALSE) -> Carpentry | D101: =VLOOKUP($B101,'Rate card'!$A$4:$G236,3,FALSE) -> Panelling with framing | E101: =VLOOKUP($B101,'Rate card'!$A$4:$G236,4,FALSE) -> MDF | F101: =VLOOKUP($B101,'Rate card'!$A$4:$G236,5,FALSE) -> MR ply + ply framing + 12mm MDF | G101: =VLOOKUP($B101,'Rate card'!$A$4:$G236,6,FALSE) -> Sqft | H101: 600 | I101: 22 | J101: =H101*I101 -> 13200 | K101: pelmet
A102: Bedroom 3
A103: 1 | B103: CP 21 | C103: =VLOOKUP($B103,'Rate card'!$A$4:$G236,2,FALSE) -> Carpentry | D103: =VLOOKUP($B103,'Rate card'!$A$4:$G236,3,FALSE) -> Bed | E103: =VLOOKUP($B103,'Rate card'!$A$4:$G236,4,FALSE) -> Laminate Finish | F103: =VLOOKUP($B103,'Rate card'!$A$4:$G236,5,FALSE) -> MR ply + Inside laminate + finish laminate | G103: =VLOOKUP($B103,'Rate card'!$A$4:$G236,6,FALSE) -> Sqft | H103: 2200 | I103: 40 | J103: =H103*I103 -> 88000 | K103: King size Bed, 2 internal drawers+ 1 side box | N103: =VLOOKUP($B103,'Rate card'!$A$4:$J236,7,FALSE) -> 1400 | O103: =I103*N103 -> 56000
A104: 2 | B104: CP 45 | C104: =VLOOKUP($B104,'Rate card'!$A$4:$G236,2,FALSE) -> Carpentry | D104: =VLOOKUP($B104,'Rate card'!$A$4:$G236,3,FALSE) -> Headboard | E104: =VLOOKUP($B104,'Rate card'!$A$4:$G236,4,FALSE) -> Fabric Finish | F104: =VLOOKUP($B104,'Rate card'!$A$4:$G236,5,FALSE) -> MR ply panelling + Foam material and labour. Excludes Fabric cost | G104: =VLOOKUP($B104,'Rate card'!$A$4:$G236,6,FALSE) -> Sqft | H104: 1300 | I104: 18 | J104: =H104*I104 -> 23400 | K104: Headboard | N104: =VLOOKUP($B104,'Rate card'!$A$4:$J236,7,FALSE) -> 950 | O104: =I104*N104 -> 17100
A105: 3 | B105: CP 46 | C105: =VLOOKUP($B105,'Rate card'!$A$4:$G236,2,FALSE) -> Carpentry | D105: Bed side table | E105: =VLOOKUP($B105,'Rate card'!$A$4:$G236,4,FALSE) -> Laminate Finish | F105: =VLOOKUP($B105,'Rate card'!$A$4:$G236,5,FALSE) -> MR ply + Inside laminate + finish laminate (1 Drawer) | G105: =VLOOKUP($B105,'Rate card'!$A$4:$G236,6,FALSE) -> Nos | H105: 13000 | I105: 2 | J105: =H105*I105 -> 26000 | K105: Bed side table
A106: 4 | B106: CP 49 | C106: =VLOOKUP($B106,'Rate card'!$A$4:$G236,2,FALSE) -> Carpentry | D106: =VLOOKUP($B106,'Rate card'!$A$4:$G236,3,FALSE) -> Study Table | E106: =VLOOKUP($B106,'Rate card'!$A$4:$G236,4,FALSE) -> Laminate Finish | F106: =VLOOKUP($B106,'Rate card'!$A$4:$G236,5,FALSE) -> MR ply + Inside laminate + finish laminate (2 pencil drawers) | G106: =VLOOKUP($B106,'Rate card'!$A$4:$G236,6,FALSE) -> Rft | H106: 4500 | I106: 3 | J106: =H106*I106 -> 13500 | K106: Study table
A107: 5 | B107: CP 25 | C107: =VLOOKUP($B107,'Rate card'!$A$4:$G236,2,FALSE) -> Carpentry | D107: =VLOOKUP($B107,'Rate card'!$A$4:$G236,3,FALSE) -> Carcass Storage | E107: =VLOOKUP($B107,'Rate card'!$A$4:$G236,4,FALSE) -> Laminate Finish | F107: =VLOOKUP($B107,'Rate card'!$A$4:$G236,5,FALSE) -> MR ply + Inside laminate + finish laminate | G107: =VLOOKUP($B107,'Rate card'!$A$4:$G236,6,FALSE) -> Sqft | H107: =VLOOKUP($B107,'Rate card'!$A$4:$J236,8,FALSE) -> 1800 | I107: 15 | J107: =H107*I107 -> 27000 | K107: Overhead storage
...

Sheet 14.03.25
A6: Date : | B6: 45730 | E6: Project Code :
A7: Client Name : | B7: Rahul Dhanawat | E7: Quotation Revision : | F7: 0
A8: Address : | B8: 10BKC | E8: Elemantra Contact Person : | F8: Payal- 93724 07848
P9: Add / modify | T9: Note
A10: Quotation Summary | G10: SR.NO | H10: Description | I10: Amount | P10: 1. Balcony
B11: Area in Sqft | D11: 1673 | G11: 1 | H11: Loose furniture | I11: =J211 -> 355000 | P11: 2. Utility tiles
A12: SR.NO | B12: Description | D12: Amount | G12: 2 | H12: Additional items | I12: =J225 -> 1651300 | P12: 3. Water outlets
A13: 1 | B13: Civil | D13: =J42 -> 566705 | H13: Total B | I13: =SUM(I11:I12) -> 2006300 | P13: 4. Kitchen flooring
A14: 2 | B14: Plumbing | D14: =J48 -> 125000 | G14: Total A+B | I14: =D21+I13 -> 8815486 | P14: 5. Smart lock at the entrace
A15: 3 | B15: Electrical | D15: =J51 -> 585550 | G15: GST 18% extra | P15: 6. Exhaust fans
A16: 4 | B16: POP | D16: =J59 -> 394840 | P16: 7. Rubber bidding
A17: 5 | B17: Carpentry | D17: =J152 -> 4148612.5 | P17: 8. Shaft closing
A18: 6 | B18: Painting | D18: =J158 -> 368478.5
A19: 7 | B19: Miscellenious | D19: =J163 -> 120000
A20: 8 | B20: Design Consultation Fees(10%) | D20: 500000
B21: Total A | D21: =SUM(D13:D20) -> 6809186
B22: Per Sqft Rate | D22: =(D21/D11) -> 4070.0454
A24: Sr.No | B24: Id | C24: Item Name | D24: Category | E24: Item Details | F24: Description | G24: UOM | H24: Elemantra Rates | I24: Quantity | J24: Amount | K24: Location | N24: Vendor Rate | O24: Amount
A25: Civil
A26: 1 | B26: D2 | C26: =VLOOKUP($B26,'Rate card'!$A$4:$G240,2,FALSE) -> Demolition | D26: =VLOOKUP($B26,'Rate card'!$A$4:$G240,3,FALSE) -> Brickwall - 6" | E26: =VLOOKUP($B26,'Rate card'!$A$4:$G240,4,FALSE) -> NA | F26: =VLOOKUP($B26,'Rate card'!$A$4:$G240,5,FALSE) -> Demolition | G26: =VLOOKUP($B26,'Rate card'!$A$4:$G240,6,FALSE) -> Sqft | H26: 500 | I26: =3*10+3*10 -> 60 | J26: =I26*H26 -> 30000 | K26: Kitchen & common toilet | O26: =VLOOKUP($B26,'Rate card'!$A$4:$J240,7,FALSE) -> 20
A27: 2 | C27: Civil | D27: Brickwall - 4" | E27: =E26 -> NA | F27: Providing and laying 4" (100 MM) brick partition wall with good quality bricks well burnt 1st class in cement mortar 1:4 (1 cement : 4 coarse sand) including providing 2 nos of 6mm dia MS round bars at every IV course including scaffolding, curing, raking out joints etc. complete. | G27: =#REF! -> #REF! | H27: 150 | I27: =3*10+3*10 -> 60 | J27: =I27*H27 -> 9000 | K27: Kitchen & common toilet
A28: 3 | C28: Civil | D28: Plaster | E28: =E26 -> NA | F28: Providing and laying 12-25 mm thick cement plaster of mis 1 : 4 (1 cement : 4 sand with 50% coarse sand & 50% fine sand) to all type of RCC / brick surface in line, level and plumb including providing wiremesh at all junctions of walls and ceilings etc. complete. | G28: Sqft | H28: 120 | I28: =I27 -> 60 | J28: =I28*H28 -> 7200 | K28: Kitchen & common toilet
A29: 4 | B29: C23 | C29: =VLOOKUP($B29,'Rate card'!$A$4:$G240,2,FALSE) -> Civil | D29: =VLOOKUP($B29,'Rate card'!$A$4:$G240,3,FALSE) -> Kitchen platform | E29: =VLOOKUP($B29,'Rate card'!$A$4:$G240,4,FALSE) -> Fully Modular Kitchen - Granite/Marble | F29: =VLOOKUP($B29,'Rate card'!$A$4:$G240,5,FALSE) -> Laying marble (18mm thk) of approved colour, shade and size on the platform as per drawing / flooring pattern, matching of grain, laid on a levelled, neat cement base with adhesive of approved make (laticrete) grouted of matching colour pigment to match the shade of stone and protection of floor to be taken into account.(cement concrete base taken into account in the civil works ) | G29: =VLOOKUP($B29,'Rate card'!$A$4:$G240,6,FALSE) -> Sqft | H29: 500 | I29: =18.5*2 -> 37 | J29: =I29*H29 -> 18500 | K29: Kitchen | O29: =VLOOKUP($B29,'Rate card'!$A$4:$J240,7,FALSE) -> 150
A30: 5 | C30: Civil | D30: Plaster | E30: =E28 -> NA | F30: Providing and laying 12-25 mm thick cement plaster of mis 1 : 4 (1 cement : 4 sand with 50% coarse sand & 50% fine sand) to all type of RCC / brick surface in line, level and plumb including providing wiremesh at all junctions of walls and ceilings etc. complete. | G30: Sqft | H30: 120 | I30: =I31 -> 192.5 | J30: =I30*H30 -> 23100 | K30: Kitchen wall
A31: 6 | C31: Civil | D31: Kitchen wall tiles | E31: Upto( 4' x 2' ) tiles laying | F31: Laying of Wall tiles of approved colour and size as per drawing, over 20 mm thick cement mortar 1 : 4 ( 1 cement : 4 coarse sand ) and jointed with white cement slurry admixed with matching pigment to match the shade of tile & Grouting and spacer to be included. | G31: Sqft | H31: 140 | I31: =11.25*7+1.5*7+12*7+2.75*7 -> 192.5 | J31: =I31*H31 -> 26950 | K31: Kitchen
A32: 7 | B32: C27 | C32: =VLOOKUP($B32,'Rate card'!$A$4:$G240,2,FALSE) -> Civil | D32: =VLOOKUP($B32,'Rate card'!$A$4:$G240,3,FALSE) -> Brickbat | E32: =VLOOKUP($B32,'Rate card'!$A$4:$G240,4,FALSE) | F32: =VLOOKUP($B32,'Rate card'!$A$4:$G240,5,FALSE) -> Providing & laying brickbat coba (6") with PCC | G32: =VLOOKUP($B32,'Rate card'!$A$4:$G240,6,FALSE) -> Sqft | H32: =VLOOKUP($B32,'Rate card'!$A$4:$J240,8,FALSE) -> 200 | I32: =55+40+40+57 -> 192 | J32: =H32*I32 -> 38400 | K32: Toilets | N32: =VLOOKUP($B32,'Rate card'!$A$4:$J240,7,FALSE) -> 150 | O32: =I32*N32 -> 28800
A33: 8 | B33: C30 | C33: =VLOOKUP($B33,'Rate card'!$A$4:$G240,2,FALSE) -> Civil | D33: =VLOOKUP($B33,'Rate card'!$A$4:$G240,3,FALSE) -> Waterproofing | E33: Floor & walls | F33: =VLOOKUP($B33,'Rate card'!$A$4:$G240,5,FALSE) -> Waterproofing with 2 coats | G33: =VLOOKUP($B33,'Rate card'!$A$4:$G240,6,FALSE) -> Sqft | H33: =VLOOKUP($B33,'Rate card'!$A$4:$J240,8,FALSE) -> 80 | I33: 350 | J33: =H33*I33 -> 28000 | K33: Toilets | N33: =VLOOKUP($B33,'Rate card'!$A$4:$J240,7,FALSE) -> 50 | O33: =I33*N33 -> 17500
A34: 9 | C34: Civil | D34: Plaster | E34: =E30 -> NA | F34: Providing and laying 12-25 mm thick cement plaster of mis 1 : 4 (1 cement : 4 sand with 50% coarse sand & 50% fine sand) to all type of RCC / brick surface in line, level and plumb including providing wiremesh at all junctions of walls and ceilings etc. complete. | G34: Sqft | H34: 120 | I34: =272+234+234+275 -> 1015 | J34: =I34*H34 -> 121800 | K34: Bathroom walls
A35: 10 | C35: Civil | D35: Bathroom floor & wall tiles | E35: Upto( 4' x 2' ) tiles laying | F35: Laying of Wall tiles of approved colour and size as per drawing, over 20 mm thick cement mortar 1 : 4 ( 1 cement : 4 coarse sand ) and jointed with white cement slurry admixed with matching pigment to match the shade of tile & Grouting and spacer to be included. | G35: Sqft | H35: 140 | I35: =55+272+40+234+40+234+57+275 -> 1207 | J35: =I35*H35 -> 168980 | K35: Toilets
A36: 11 | B36: C23 | C36: =VLOOKUP($B36,'Rate card'!$A$4:$G240,2,FALSE) -> Civil | D36: Utility platfrom | E36: =VLOOKUP($B36,'Rate card'!$A$4:$G240,4,FALSE) -> Fully Modular Kitchen - Granite/Marble | F36: =VLOOKUP($B36,'Rate card'!$A$4:$G240,5,FALSE) -> Laying marble (18mm thk) of approved colour, shade and size on the platform as per drawing / flooring pattern, matching of grain, laid on a levelled, neat cement base with adhesive of approved make (laticrete) grouted of matching colour pigment to match the shade of stone and protection of floor to be taken into account.(cement concrete base taken into account in the civil works ) | G36: =VLOOKUP($B36,'Rate card'!$A$4:$G240,6,FALSE) -> Sqft | H36: 500 | I36: 10 | J36: =I36*H36 -> 5000 | K36: utility | O36: =VLOOKUP($B36,'Rate card'!$A$4:$J240,7,FALSE) -> 150
A37: 12 | B37: C15 | C37: =VLOOKUP($B37,'Rate card'!$A$4:$G240,2,FALSE) -> Civil | D37: =VLOOKUP($B37,'Rate card'!$A$4:$G240,3,FALSE) -> Granite frames | E37: =VLOOKUP($B37,'Rate card'!$A$4:$G240,4,FALSE) -> Single patti | F37: =VLOOKUP($B37,'Rate card'!$A$4:$G240,5,FALSE) -> Granite Frame – up to 6 Inches width {Including Bevelling+ Cutting+ Polishing}. Excludes Granite cost | G37: =VLOOKUP($B37,'Rate card'!$A$4:$G240,6,FALSE) -> Rft | H37: =VLOOKUP($B37,'Rate card'!$A$4:$J240,8,FALSE) -> 130 | I37: =20*4 -> 80 | J37: =H37*I37 -> 10400 | K37: kitchen & Toilets | N37: =VLOOKUP($B37,'Rate card'!$A$4:$J240,7,FALSE) -> 80 | O37: =I37*N37 -> 6400
A38: 13 | B38: C45 | C38: =VLOOKUP($B38,'Rate card'!$A$4:$G240,2,FALSE) -> Civil | D38: =VLOOKUP($B38,'Rate card'!$A$4:$G240,3,FALSE) -> Vanity counter | E38: =VLOOKUP($B38,'Rate card'!$A$4:$G240,4,FALSE) -> Granite/Marble | F38: =VLOOKUP($B38,'Rate card'!$A$4:$G240,5,FALSE) -> Laying marble (18mm thk) of approved colour, shade and size on the platform as per drawing / flooring pattern, matching of grain, laid on a levelled, neat cement base with adhesive of approved make (laticrete) grouted of matching colour pigment to match the shade of stone and protection of floor to be taken into account.(cement concrete base taken into account in the civil works ) | G38: =VLOOKUP($B38,'Rate card'!$A$4:$G240,6,FALSE) -> Rft | H38: =VLOOKUP($B38,'Rate card'!$A$4:$J240,8,FALSE) -> 1500 | I38: 22 | J38: =H38*I38 -> 33000 | K38: Toilets | N38: =VLOOKUP($B38,'Rate card'!$A$4:$J240,7,FALSE) -> 1000 | O38: =I38*N38 -> 22000
A39: 14 | C39: Tiles behind Wardrobe | G39: sqft | H39: 50 | I39: =I92+I95+I107+I120+I131 -> 327.5 | J39: =(H39*I39) -> 16375 | K39: Behind wardrobe
A40: 15
A41: 13 | B41: C45 | C41: =VLOOKUP($B41,'Rate card'!$A$4:$G240,2,FALSE) -> Civil | D41: Ledge | E41: =VLOOKUP($B41,'Rate card'!$A$4:$G240,4,FALSE) -> Granite/Marble | F41: =VLOOKUP($B41,'Rate card'!$A$4:$G240,5,FALSE) -> Laying marble (18mm thk) of approved colour, shade and size on the platform as per drawing / flooring pattern, matching of grain, laid on a levelled, neat cement base with adhesive of approved make (laticrete) grouted of matching colour pigment to match the shade of stone and protection of floor to be taken into account.(cement concrete base taken into account in the civil works ) | G41: =VLOOKUP($B41,'Rate card'!$A$4:$G240,6,FALSE) -> Rft | H41: =VLOOKUP($B41,'Rate card'!$A$4:$J240,8,FALSE) -> 1500 | I41: 20 | J41: =H41*I41 -> 30000 | K41: Toilets | N41: =VLOOKUP($B41,'Rate card'!$A$4:$J240,7,FALSE) -> 1000 | O41: =I41*N41 -> 20000
I42: Total | J42: =SUM(J26:J41) -> 566705
A43: Plumbing
A44: 1 | B44: PL 2 | C44: Plumbing | D44: Bathroom Plumbing | E44: CP fitting work 1 Basin +cp fittings+Ceiling shower | F44: cp fiting and sanitary ware fixing in a bathroom | G44: per bathroom | H44: 35000 | I44: 1 | J44: =H44*I44 -> 35000 | K44: Samar's toilet | N44: =VLOOKUP($B44,'Rate card'!$A$4:$J240,7,FALSE) -> 8000 | O44: =I44*N44 -> 8000
A45: 2 | B45: PL 2 | C45: Plumbing | D45: Bathroom Plumbing | E45: Ceiling shower+body jets+c.p fittings | F45: cp fiting and sanitary ware fixing in a bathroom | G45: per bathroom | H45: 40000 | I45: 1 | J45: =H45*I45 -> 40000 | K45: Master & Ranbeer | N45: =VLOOKUP($B45,'Rate card'!$A$4:$J240,7,FALSE) -> 8000 | O45: =I45*N45 -> 8000
A46: 3 | B46: PL 2 | C46: Plumbing | D46: Bathroom Plumbing | E46: CP fitting work 1 Basin +cp fittings+Ceiling shower | F46: cp fiting and sanitary ware fixing in a bathroom | G46: per bathroom | H46: 25000 | I46: 1 | J46: =H46*I46 -> 25000 | K46: Mother's toilet | N46: =VLOOKUP($B46,'Rate card'!$A$4:$J240,7,FALSE) -> 8000 | O46: =I46*N46 -> 8000
A47: 4 | B47: PL 3 | C47: =VLOOKUP($B47,'Rate card'!$A$4:$G240,2,FALSE) -> Plumbing | D47: =VLOOKUP($B47,'Rate card'!$A$4:$G240,3,FALSE) -> Kitchen Plumbing | E47: 3 sink+dishwahser+washing machine | F47: =VLOOKUP($B47,'Rate card'!$A$4:$G240,5,FALSE) -> all plumbing concealed wall and floor CPVC and UPVC pipes and chipping and replastering work | G47: =VLOOKUP($B47,'Rate card'!$A$4:$G240,6,FALSE) -> per kitchen | H47: 25000 | I47: 1 | J47: =H47*I47 -> 25000 | K47: Kitchen & Utility | N47: =VLOOKUP($B47,'Rate card'!$A$4:$J240,7,FALSE) -> 5500 | O47: =I47*N47 -> 5500
I48: Total | J48: =SUM(J44:J47) -> 125000
A49: Electrical
A50: 1 | B50: E 1 | C50: Electrical | D50: 5A Switch socket, Light points,AC point, Fan point, Circuit wiring, DB Dressing | E50: new 5A Switch & Socket, light points, 15A, AC point, fan point from DB on wall include the price for wire and conduits, chipping and replastering on wall is included | F50: NOTE - The rates include fixingof switch / socket in position, effecting proper connections testing and commissioning of lighting fixtures and fans including lamps, control gear, power factor improvement capacitor and all fixing accessories that may be required to check. | G50: All areas | H50: 350 | I50: 1673 | J50: =H50*I50 -> 585550 | K50: All areas | N50: =VLOOKUP($B50,'Rate card'!$A$4:$J240,7,FALSE) -> 625 | O50: =I50*N50 -> 1045625
I51: Total | J51: =SUM(J50) -> 585550
A52: Pop/Falsceiling
A53: 1 | B53: FC 3 | C53: =VLOOKUP($B53,'Rate card'!$A$4:$G240,2,FALSE) -> False Ceiling | D53: =VLOOKUP($B53,'Rate card'!$A$4:$G240,3,FALSE) -> Gypsum Board Ceiling | E53: =VLOOKUP($B53,'Rate card'!$A$4:$G240,4,FALSE) -> Saint Gobain/Gyproc Board + local A Grade channel | F53: =VLOOKUP($B53,'Rate card'!$A$4:$G240,5,FALSE) -> 12.5mm thick gypsum board, with local A Grade Channel including all material, labour, transportation etc | Ceiling Channel and Intermediate Channel at 900mm c/c & Ceiling Section at 450mm c/c | G53: =VLOOKUP($B53,'Rate card'!$A$4:$G240,6,FALSE) -> Sqft | H53: 120 | I53: 1447 | J53: =H53*I53 -> 173640 | K53: All areas
A54: 2 | B54: FC 4 | C54: =VLOOKUP($B54,'Rate card'!$A$4:$G240,2,FALSE) -> False Ceiling | D54: =VLOOKUP($B54,'Rate card'!$A$4:$G240,3,FALSE) -> Gypsum Board Cove | E54: =VLOOKUP($B54,'Rate card'!$A$4:$G240,4,FALSE) -> Gypsum cove | F54: =VLOOKUP($B54,'Rate card'!$A$4:$G240,5,FALSE) -> 12.5mm thick gypsum board, with local A Grade Channel including all material, labour, transportation etc | Ceiling Channel and Intermediate Channel at 900mm c/c & Ceiling Section at 450mm c/c | G54: =VLOOKUP($B54,'Rate card'!$A$4:$G240,6,FALSE) -> Rft | H54: 120 | I54: 800 | J54: =H54*I54 -> 96000 | K54: All areas
A55: 3 | B55: FC 5 | C55: =VLOOKUP($B55,'Rate card'!$A$4:$G240,2,FALSE) -> False Ceiling | D55: =VLOOKUP($B55,'Rate card'!$A$4:$G240,3,FALSE) -> Hilux Board ceiling | E55: =VLOOKUP($B55,'Rate card'!$A$4:$G240,4,FALSE) -> Hilux Board + local A Grade channel | F55: =VLOOKUP($B55,'Rate card'!$A$4:$G240,5,FALSE) -> 8mm Ramco hilux board, with local A Grade Channel including all material, labour, transportation etc | Ceiling Channel and Intermediate Channel at 900mm c/c & Ceiling Section at 450mm c/c | G55: =VLOOKUP($B55,'Rate card'!$A$4:$G240,6,FALSE) -> Sqft | H55: 200 | I55: 226 | J55: =H55*I55 -> 45200 | K55: Toilets | N55: =VLOOKUP($B55,'Rate card'!$A$4:$J240,7,FALSE) -> 120 | O55: =I55*N55 -> 27120
A56: 4 | B56: FC 11 | C56: =VLOOKUP($B56,'Rate card'!$A$4:$G240,2,FALSE) -> POP | D56: =VLOOKUP($B56,'Rate card'!$A$4:$G240,3,FALSE) -> POP Punning | E56: =VLOOKUP($B56,'Rate card'!$A$4:$G240,4,FALSE) -> POP Punning (Plum) 12-25mm thick | F56: =VLOOKUP($B56,'Rate card'!$A$4:$G240,5,FALSE) -> Providing and applying 12-25 mm thick POP punning on wall /ceiling including scrapping and hacking the existing finished surface and applying plaster of paris in proper line and levels etc. complete. | G56: =VLOOKUP($B56,'Rate card'!$A$4:$G240,6,FALSE) -> Sqft | H56: 45 | I56: 1000 | J56: =H56*I56 -> 45000 | K56: Patch work wall punning
A57: 5 | B57: FC 12 | C57: =VLOOKUP($B57,'Rate card'!$A$4:$G240,2,FALSE) -> POP | D57: =VLOOKUP($B57,'Rate card'!$A$4:$G240,3,FALSE) -> POP Punning dhar | E57: =VLOOKUP($B57,'Rate card'!$A$4:$G240,4,FALSE) -> POP Punning (Plum) 12-25mm thick | F57: =VLOOKUP($B57,'Rate card'!$A$4:$G240,5,FALSE) -> Providing and applying 12-25 mm thick POP punning on wall /ceiling including scrapping and hacking the existing finished surface and applying plaster of paris in proper line and levels etc. complete. | G57: =VLOOKUP($B57,'Rate card'!$A$4:$G240,6,FALSE) -> Rft | H57: 25 | I57: 600 | J57: =H57*I57 -> 15000 | K57: Patch works and wall levelling purpose
A58: 6 | B58: FC 17 | C58: =VLOOKUP($B58,'Rate card'!$A$4:$G240,2,FALSE) -> False Ceiling | D58: =VLOOKUP($B58,'Rate card'!$A$4:$G240,3,FALSE) -> Light Gala cutting | E58: =VLOOKUP($B58,'Rate card'!$A$4:$G240,4,FALSE) -> NA | F58: =VLOOKUP($B58,'Rate card'!$A$4:$G240,5,FALSE) -> NA | G58: =VLOOKUP($B58,'Rate card'!$A$4:$G240,6,FALSE) -> Nos | H58: 100 | I58: 200 | J58: =H58*I58 -> 20000 | K58: All areas
I59: Total | J59: =SUM(J53:J58) -> 394840
A60: Carpentry
A61: Living Room/Dining
A62: 1 | B62: CP 111 | C62: =VLOOKUP($B62,'Rate card'!$A$4:$G240,2,FALSE) -> Carpentry | D62: Main Door | E62: Veneer Finish | F62: MR ply +both side Veneer finish | G62: =VLOOKUP($B62,'Rate card'!$A$4:$G240,6,FALSE) -> Nos | H62: 65000 | I62: 1 | J62: =H62*I62 -> 65000 | K62: New main door
A63: 2 | B63: CP 111 | C63: Carpentry | D63: Ply Door Frame | E63: Veneer Finish | F63: MR ply + finish veneer from both sides | G63: Rft | H63: 750 | I63: =4+9+9 -> 22 | J63: =H63*I63 -> 16500 | K63: Door Frame
A64: 3 | B64: CP 1 | C64: Carpentry | D64: Panelling with framing | E64: Veneer Finish | F64: MR ply + ply framing + finish Veneer | G64: =VLOOKUP($B64,'Rate card'!$A$4:$G240,6,FALSE) -> Sqft | H64: 800 | I64: =7*3+9*2 -> 39 | J64: =H64*I64 -> 31200 | K64: safety door panelling | N64: =VLOOKUP($B64,'Rate card'!$A$4:$J240,7,FALSE) -> 450 | O64: =I64*N64 -> 17550
A65: 4 | B65: CP 25 | C65: =VLOOKUP($B65,'Rate card'!$A$4:$G240,2,FALSE) -> Carpentry | D65: =VLOOKUP($B65,'Rate card'!$A$4:$G240,3,FALSE) -> Carcass Storage | E65: =VLOOKUP($B65,'Rate card'!$A$4:$G240,4,FALSE) -> Laminate Finish | F65: =VLOOKUP($B65,'Rate card'!$A$4:$G240,5,FALSE) -> MR ply + Inside laminate + finish laminate | G65: =VLOOKUP($B65,'Rate card'!$A$4:$G240,6,FALSE) -> Sqft | H65: 1800 | I65: =7.5*10 -> 75 | J65: =H65*I65 -> 135000 | K65: shoerack | N65: =VLOOKUP($B65,'Rate card'!$A$4:$J240,7,FALSE) -> 1350 | O65: =I65*N65 -> 101250
A66: 5 | B66: CP 6 | C66: Carpentry | D66: Panelling with framing | E66: =E73 -> Laminate Finish | F66: Mirror +Laminate+ledge in marble | G66: L.s | H66: 50000 | I66: 1 | J66: =H66*I66 -> 50000 | K66: Panelling in Passage above
A67: 6 | B67: CP 25 | C67: =VLOOKUP($B67,'Rate card'!$A$4:$G240,2,FALSE) -> Carpentry | D67: =VLOOKUP($B67,'Rate card'!$A$4:$G240,3,FALSE) -> Carcass Storage | E67: =VLOOKUP($B67,'Rate card'!$A$4:$G240,4,FALSE) -> Laminate Finish | F67: MR ply + Inside laminate + finish Veneer | G67: R ft | H67: 5000 | I67: 7.5 | J67: =H67*I67 -> 37500 | K67: TV unit | N67: =VLOOKUP($B67,'Rate card'!$A$4:$J240,7,FALSE) -> 1350 | O67: =I67*N67 -> 10125
A68: 7 | B68: CP 25 | C68: =VLOOKUP($B68,'Rate card'!$A$4:$G240,2,FALSE) -> Carpentry | D68: =VLOOKUP($B68,'Rate card'!$A$4:$G240,3,FALSE) -> Carcass Storage | E68: =VLOOKUP($B68,'Rate card'!$A$4:$G240,4,FALSE) -> Laminate Finish | F68: =VLOOKUP($B68,'Rate card'!$A$4:$G240,5,FALSE) -> MR ply + Inside laminate + finish laminate | G68: =VLOOKUP($B68,'Rate card'!$A$4:$G240,6,FALSE) -> Sqft | H68: =VLOOKUP($B68,'Rate card'!$A$4:$J240,8,FALSE) -> 1800 | I68: =7*8 -> 56 | J68: =H68*I68 -> 100800 | K68: TV panel | N68: =VLOOKUP($B68,'Rate card'!$A$4:$J240,7,FALSE) -> 1350 | O68: =I68*N68 -> 75600
A69: 8 | B69: CP 25 | C69: =VLOOKUP($B69,'Rate card'!$A$4:$G240,2,FALSE) -> Carpentry | D69: =VLOOKUP($B69,'Rate card'!$A$4:$G240,3,FALSE) -> Carcass Storage | E69: =VLOOKUP($B69,'Rate card'!$A$4:$G240,4,FALSE) -> Laminate Finish | F69: =VLOOKUP($B69,'Rate card'!$A$4:$G240,5,FALSE) -> MR ply + Inside laminate + finish laminate | G69: =VLOOKUP($B69,'Rate card'!$A$4:$G240,6,FALSE) -> Sqft | H69: =VLOOKUP($B69,'Rate card'!$A$4:$J240,8,FALSE) -> 1800 | I69: =4*7 -> 28 | J69: =H69*I69 -> 50400 | K69: Mandir | N69: =VLOOKUP($B69,'Rate card'!$A$4:$J240,7,FALSE) -> 1350 | O69: =I69*N69 -> 37800
A70: 9 | B70: CP 25 | C70: =VLOOKUP($B70,'Rate card'!$A$4:$G240,2,FALSE) -> Carpentry | D70: =VLOOKUP($B70,'Rate card'!$A$4:$G240,3,FALSE) -> Carcass Storage | E70: =VLOOKUP($B70,'Rate card'!$A$4:$G240,4,FALSE) -> Laminate Finish | F70: =F67 -> MR ply + Inside laminate + finish Veneer | G70: =VLOOKUP($B70,'Rate card'!$A$4:$G240,6,FALSE) -> Sqft | H70: 2500 | I70: =5*3.5 -> 17.5 | J70: =H70*I70 -> 43750 | K70: Console | N70: =VLOOKUP($B70,'Rate card'!$A$4:$J240,7,FALSE) -> 1350 | O70: =I70*N70 -> 23625
A71: 10 | B71: CP 6 | C71: =VLOOKUP($B71,'Rate card'!$A$4:$G240,2,FALSE) -> Carpentry | D71: =VLOOKUP($B71,'Rate card'!$A$4:$G240,3,FALSE) -> Panelling with framing | E71: =VLOOKUP($B71,'Rate card'!$A$4:$G240,4,FALSE) -> MDF | F71: =VLOOKUP($B71,'Rate card'!$A$4:$G240,5,FALSE) -> MR ply + ply framing + 12mm MDF | G71: =VLOOKUP($B71,'Rate card'!$A$4:$G240,6,FALSE) -> Sqft | H71: 600 | I71: =12*2.5 -> 30 | J71: =H71*I71 -> 18000 | K71: Pelmet
A72: 11 | B72: CP 6 | C72: Carpentry | D72: Panelling with framing | E72: Moulding & Mirror | F72: Moulding & Mirror | G72: L.s | H72: 50000 | I72: 1 | J72: =H72*I72 -> 50000 | K72: Wall Panel on dinning wall
A73: 12 | B73: CP 6 | C73: Carpentry | D73: Panelling with framing | E73: =E70 -> Laminate Finish | F73: =F71 -> MR ply + ply framing + 12mm MDF | G73: =VLOOKUP($B73,'Rate card'!$A$4:$G240,6,FALSE) -> Sqft | H73: 650 | I73: =12*10 -> 120 | J73: =H73*I73 -> 78000 | K73: Wall Panel on sofa wall
A74: 13 | B74: CP 6 | C74: Carpentry | D74: Panelling with framing | E74: Moulding & Mirror | F74: =F69 -> MR ply + Inside laminate + finish laminate | G74: =VLOOKUP($B74,'Rate card'!$A$4:$G240,6,FALSE) -> Sqft | H74: 650 | I74: =29*10 -> 290 | J74: =H74*I74 -> 188500 | K74: Panelling on mother's & samar's bed room wall
A75: 13 | B75: CP 6 | C75: Carpentry | D75: Panelling with framing | E75: Moulding & Mirror | F75: =F69 -> MR ply + Inside laminate + finish laminate | G75: =VLOOKUP($B75,'Rate card'!$A$4:$G240,6,FALSE) -> Sqft | H75: 1800 | I75: =5*2.5 -> 12.5 | J75: =H75*I75 -> 22500 | K75: Ledge behind sofa
A76: Modular Kitchen
A77: 1 | B77: CP 25 | C77: =VLOOKUP($B77,'Rate card'!$A$4:$G240,2,FALSE) -> Carpentry | D77: =VLOOKUP($B77,'Rate card'!$A$4:$G240,3,FALSE) -> Carcass Storage | E77: Acrylic Finish | F77: Marine ply + Inside laminate + Acrylic Finish | G77: =VLOOKUP($B77,'Rate card'!$A$4:$G240,6,FALSE) -> Sqft | H77: 2700 | I77: =18.5*2.5 -> 46.25 | J77: =H77*I77 -> 124875 | K77: undercounter
A78: 2 | B78: CP 25 | C78: =VLOOKUP($B78,'Rate card'!$A$4:$G240,2,FALSE) -> Carpentry | D78: =VLOOKUP($B78,'Rate card'!$A$4:$G240,3,FALSE) -> Carcass Storage | E78: Acrylic Finish | F78: Marine ply + Inside laminate + Acrylic Finish | G78: =VLOOKUP($B78,'Rate card'!$A$4:$G240,6,FALSE) -> Sqft | H78: 2700 | I78: =28+11.25*2.5+4*2.5 -> 66.125 | J78: =H78*I78 -> 178537.5 | K78: overhead+loft
A79: 3 | B79: CP 25 | C79: =VLOOKUP($B79,'Rate card'!$A$4:$G240,2,FALSE) -> Carpentry | D79: =VLOOKUP($B79,'Rate card'!$A$4:$G240,3,FALSE) -> Carcass Storage | E79: Acrylic Finish | F79: Marine ply + Inside laminate + Acrylic Finish | G79: =VLOOKUP($B79,'Rate card'!$A$4:$G240,6,FALSE) -> Sqft | H79: 2700 | I79: =4*10 -> 40 | J79: =H79*I79 -> 108000 | K79: Pantry Storage, next to fridge
A80: 4 | B80: CP 61 | C80: =VLOOKUP($B80,'Rate card'!$A$4:$G240,2,FALSE) -> Carpentry | D80: =VLOOKUP($B80,'Rate card'!$A$4:$G240,3,FALSE) -> Kitchen Basket | E80: tandem | F80: =VLOOKUP($B80,'Rate card'!$A$4:$G240,5,FALSE) -> Basket + Channel+Fitting charges | G80: =VLOOKUP($B80,'Rate card'!$A$4:$G240,6,FALSE) -> Nos | H80: 8000 | I80: 5 | J80: =H80*I80 -> 40000 | K80: Modular kitchen
A81: 5 | B81: CP 64 | C81: =VLOOKUP($B81,'Rate card'!$A$4:$G240,2,FALSE) -> Carpentry | D81: =VLOOKUP($B81,'Rate card'!$A$4:$G240,3,FALSE) -> Wicker basket | E81: =VLOOKUP($B81,'Rate card'!$A$4:$G240,4,FALSE) -> Wicker basket | F81: =VLOOKUP($B81,'Rate card'!$A$4:$G240,5,FALSE) -> Basket + Channel+Fitting charges | G81: =VLOOKUP($B81,'Rate card'!$A$4:$G240,6,FALSE) -> Nos | H81: 6000 | I81: 2 | J81: =H81*I81 -> 12000 | K81: Modular kitchen
A82: 6 | C82: Carpentry | D82: Kitchen Sliding door | E82: Flutted glass finish | F82: Modular Kitchen | G82: Sqft | H82: 1650 | I82: =3*7 -> 21 | J82: =H82*I82 -> 34650 | K82: kitchen | N82: Scope added
A83: Utility
A84: 1 | B84: CP 25 | C84: =VLOOKUP($B84,'Rate card'!$A$4:$G240,2,FALSE) -> Carpentry | D84: =VLOOKUP($B84,'Rate card'!$A$4:$G240,3,FALSE) -> Carcass Storage | E84: =VLOOKUP($B84,'Rate card'!$A$4:$G240,4,FALSE) -> Laminate Finish | F84: Marine ply + Inside laminate + finish laminate | G84: =VLOOKUP($B84,'Rate card'!$A$4:$G240,6,FALSE) -> Sqft | H84: 1800 | I84: =5.5*2.5 -> 13.75 | J84: =H84*I84 -> 24750 | K84: undercounter
A85: 2 | B85: CP 25 | C85: =VLOOKUP($B85,'Rate card'!$A$4:$G240,2,FALSE) -> Carpentry | D85: =VLOOKUP($B85,'Rate card'!$A$4:$G240,3,FALSE) -> Carcass Storage | E85: =VLOOKUP($B85,'Rate card'!$A$4:$G240,4,FALSE) -> Laminate Finish | F85: Marine ply + Inside laminate + finish laminate | G85: =VLOOKUP($B85,'Rate card'!$A$4:$G240,6,FALSE) -> Sqft | H85: 1800 | I85: =10*10 -> 100 | J85: =H85*I85 -> 180000 | K85: Storage
A86: 3 | B86: CP 117 | C86: =VLOOKUP($B86,'Rate card'!$A$4:$G240,2,FALSE) -> Carpentry | D86: =VLOOKUP($B86,'Rate card'!$A$4:$G240,3,FALSE) -> Carcass Storage | E86: =VLOOKUP($B86,'Rate card'!$A$4:$G240,4,FALSE) -> Laminate Finish | F86: Marine ply + Inside laminate + finish laminate | G86: =VLOOKUP($B86,'Rate card'!$A$4:$G240,6,FALSE) -> Sqft | H86: 1800 | I86: 22 | J86: =H86*I86 -> 39600 | K86: Washing machine storage | N86: =VLOOKUP($B86,'Rate card'!$A$4:$J240,7,FALSE) -> 2000 | O86: =I86*N86 -> 44000
A87: Mother's Bedroom
A88: 1 | B88: CP 21 | C88: =VLOOKUP($B88,'Rate card'!$A$4:$G240,2,FALSE) -> Carpentry | D88: =VLOOKUP($B88,'Rate card'!$A$4:$G240,3,FALSE) -> Bed | E88: =VLOOKUP($B88,'Rate card'!$A$4:$G240,4,FALSE) -> Laminate Finish | F88: =VLOOKUP($B88,'Rate card'!$A$4:$G240,5,FALSE) -> MR ply + Inside laminate + finish laminate | G88: =VLOOKUP($B88,'Rate card'!$A$4:$G240,6,FALSE) -> Sqft | H88: 1800 | I88: =5.5*6.5 -> 35.75 | J88: =H88*I88 -> 64350 | K88: Queen size Bed | N88: =VLOOKUP($B88,'Rate card'!$A$4:$J240,7,FALSE) -> 1400 | O88: =I88*N88 -> 50050
A89: 2 | B89: CP 45 | C89: =VLOOKUP($B89,'Rate card'!$A$4:$G240,2,FALSE) -> Carpentry | D89: =VLOOKUP($B89,'Rate card'!$A$4:$G240,3,FALSE) -> Headboard | E89: =VLOOKUP($B89,'Rate card'!$A$4:$G240,4,FALSE) -> Fabric Finish | F89: =VLOOKUP($B89,'Rate card'!$A$4:$G240,5,FALSE) -> MR ply panelling + Foam material and labour. Excludes Fabric cost | G89: =VLOOKUP($B89,'Rate card'!$A$4:$G240,6,FALSE) -> Sqft | H89: 1300 | I89: =5.5*3 -> 16.5 | J89: =H89*I89 -> 21450 | K89: Headboard | N89: =VLOOKUP($B89,'Rate card'!$A$4:$J240,7,FALSE) -> 950 | O89: =I89*N89 -> 15675
A90: 3 | B90: CP 46 | C90: =VLOOKUP($B90,'Rate card'!$A$4:$G240,2,FALSE) -> Carpentry | D90: Bed side table | E90: =VLOOKUP($B90,'Rate card'!$A$4:$G240,4,FALSE) -> Laminate Finish | F90: =VLOOKUP($B90,'Rate card'!$A$4:$G240,5,FALSE) -> MR ply + Inside laminate + finish laminate (1 Drawer) | G90: =VLOOKUP($B90,'Rate card'!$A$4:$G240,6,FALSE) -> Nos | H90: 13000 | I90: 2 | J90: =H90*I90 -> 26000 | K90: Bed side table
A91: 4 | B91: CP 25 | C91: =VLOOKUP($B91,'Rate card'!$A$4:$G240,2,FALSE) -> Carpentry | D91: =VLOOKUP($B91,'Rate card'!$A$4:$G240,3,FALSE) -> Carcass Storage | E91: =VLOOKUP($B91,'Rate card'!$A$4:$G240,4,FALSE) -> Laminate Finish | F91: =VLOOKUP($B91,'Rate card'!$A$4:$G240,5,FALSE) -> MR ply + Inside laminate + finish laminate | G91: R ft | H91: 4500 | I91: 7 | J91: =H91*I91 -> 31500 | K91: TV unit + Dresser | N91: =VLOOKUP($B91,'Rate card'!$A$4:$J240,7,FALSE) -> 1350 | O91: =I91*N91 -> 9450
A92: 5 | B92: CP 25 | C92: =VLOOKUP($B92,'Rate card'!$A$4:$G240,2,FALSE) -> Carpentry | D92: =VLOOKUP($B92,'Rate card'!$A$4:$G240,3,FALSE) -> Carcass Storage | E92: =VLOOKUP($B92,'Rate card'!$A$4:$G240,4,FALSE) -> Laminate Finish | F92: =VLOOKUP($B92,'Rate card'!$A$4:$G240,5,FALSE) -> MR ply + Inside laminate + finish laminate | G92: =VLOOKUP($B92,'Rate card'!$A$4:$G240,6,FALSE) -> Sqft | H92: =VLOOKUP($B92,'Rate card'!$A$4:$J240,8,FALSE) -> 1800 | I92: =5*10 -> 50 | J92: =H92*I92 -> 90000 | K92: Wardrobe near entrance
A93: 6 | B93: CP 3 | C93: =VLOOKUP($B93,'Rate card'!$A$4:$G240,2,FALSE) -> Carpentry | D93: =VLOOKUP($B93,'Rate card'!$A$4:$G240,3,FALSE) -> Panelling with framing | E93: =VLOOKUP($B93,'Rate card'!$A$4:$G240,4,FALSE) -> Mirror Finish | F93: =VLOOKUP($B93,'Rate card'!$A$4:$G240,5,FALSE) -> MR ply + ply framing + 5mm clear mirror | G93: =VLOOKUP($B93,'Rate card'!$A$4:$G240,6,FALSE) -> Sqft | H93: =VLOOKUP($B93,'Rate card'!$A$4:$J240,8,FALSE) -> 750 | I93: =2.5*7 -> 17.5 | J93: =H93*I93 -> 13125 | K93: Mirror
A94: 7 | B94: CP 1 | C94: Carpentry | D94: Panelling with framing | E94: =VLOOKUP($B94,'Rate card'!$A$4:$G240,4,FALSE) -> Laminate Finish | F94: MR ply + ply framing + finish laminate | G94: =VLOOKUP($B94,'Rate card'!$A$4:$G240,6,FALSE) -> Sqft | H94: =VLOOKUP($B94,'Rate card'!$A$4:$J240,8,FALSE) -> 650 | I94: 80 | J94: =H94*I94 -> 52000 | K94: Wall panel
A95: 8 | B95: CP 17 | C95: =VLOOKUP($B95,'Rate card'!$A$4:$G240,2,FALSE) -> Carpentry | D95: =VLOOKUP($B95,'Rate card'!$A$4:$G240,3,FALSE) -> Wardrobe | E95: =VLOOKUP($B95,'Rate card'!$A$4:$G240,4,FALSE) -> Laminate Finish | F95: =VLOOKUP($B95,'Rate card'!$A$4:$G240,5,FALSE) -> MR ply + Inside laminate + finish laminate. (Includes 4 pencil drawers, Handles of base rate Rs.1000/pc) | G95: =VLOOKUP($B95,'Rate card'!$A$4:$G240,6,FALSE) -> Sqft | H95: 1800 | I95: =7.5*10 -> 75 | J95: =H95*I95 -> 135000 | K95: Wardrobe
A96: 9 | B96: CP 6 | C96: =VLOOKUP($B96,'Rate card'!$A$4:$G240,2,FALSE) -> Carpentry | D96: =VLOOKUP($B96,'Rate card'!$A$4:$G240,3,FALSE) -> Panelling with framing | E96: =VLOOKUP($B96,'Rate card'!$A$4:$G240,4,FALSE) -> MDF | F96: =VLOOKUP($B96,'Rate card'!$A$4:$G240,5,FALSE) -> MR ply + ply framing + 12mm MDF | G96: =VLOOKUP($B96,'Rate card'!$A$4:$G240,6,FALSE) -> Sqft | H96: 600 | I96: =12*2.5 -> 30 | J96: =H96*I96 -> 18000 | K96: pelmet
A97: Samar's Bedroom
A98: 1 | B98: CP 21 | C98: =VLOOKUP($B98,'Rate card'!$A$4:$G240,2,FALSE) -> Carpentry | D98: =VLOOKUP($B98,'Rate card'!$A$4:$G240,3,FALSE) -> Bed | E98: =VLOOKUP($B98,'Rate card'!$A$4:$G240,4,FALSE) -> Laminate Finish | F98: =VLOOKUP($B98,'Rate card'!$A$4:$G240,5,FALSE) -> MR ply + Inside laminate + finish laminate | G98: =VLOOKUP($B98,'Rate card'!$A$4:$G240,6,FALSE) -> Sqft | H98: 2200 | I98: =6*6.5 -> 39 | J98: =H98*I98 -> 85800 | K98: King size Bed, 2 internal drawers+ 1 side box | N98: =VLOOKUP($B98,'Rate card'!$A$4:$J240,7,FALSE) -> 1400 | O98: =I98*N98 -> 54600
A99: 2 | B99: CP 45 | C99: =VLOOKUP($B99,'Rate card'!$A$4:$G240,2,FALSE) -> Carpentry | D99: =VLOOKUP($B99,'Rate card'!$A$4:$G240,3,FALSE) -> Headboard | E99: =VLOOKUP($B99,'Rate card'!$A$4:$G240,4,FALSE) -> Fabric Finish | F99: =VLOOKUP($B99,'Rate card'!$A$4:$G240,5,FALSE) -> MR ply panelling + Foam material and labour. Excludes Fabric cost | G99: =VLOOKUP($B99,'Rate card'!$A$4:$G240,6,FALSE) -> Sqft | H99: 1300 | I99: =6*3.5 -> 21 | J99: =H99*I99 -> 27300 | K99: Headboard | N99: =VLOOKUP($B99,'Rate card'!$A$4:$J240,7,FALSE) -> 950 | O99: =I99*N99 -> 19950
A100: 3 | B100: CP 46 | C100: =VLOOKUP($B100,'Rate card'!$A$4:$G240,2,FALSE) -> Carpentry | D100: Bed side table | E100: =VLOOKUP($B100,'Rate card'!$A$4:$G240,4,FALSE) -> Laminate Finish | F100: =VLOOKUP($B100,'Rate card'!$A$4:$G240,5,FALSE) -> MR ply + Inside laminate + finish laminate (1 Drawer) | G100: =VLOOKUP($B100,'Rate card'!$A$4:$G240,6,FALSE) -> Nos | H100: 13000 | I100: 1 | J100: =H100*I100 -> 13000 | K100: Bed side table
A101: 4 | B101: CP 49 | C101: =VLOOKUP($B101,'Rate card'!$A$4:$G240,2,FALSE) -> Carpentry | D101: =VLOOKUP($B101,'Rate card'!$A$4:$G240,3,FALSE) -> Study Table | E101: =VLOOKUP($B101,'Rate card'!$A$4:$G240,4,FALSE) -> Laminate Finish | F101: =VLOOKUP($B101,'Rate card'!$A$4:$G240,5,FALSE) -> MR ply + Inside laminate + finish laminate (2 pencil drawers) | G101: =VLOOKUP($B101,'Rate card'!$A$4:$G240,6,FALSE) -> Rft | H101: 4500 | I101: 4 | J101: =H101*I101 -> 18000 | K101: Study table
A102: 5 | B102: CP 25 | C102: =VLOOKUP($B102,'Rate card'!$A$4:$G240,2,FALSE) -> Carpentry | D102: =VLOOKUP($B102,'Rate card'!$A$4:$G240,3,FALSE) -> Carcass Storage | E102: =VLOOKUP($B102,'Rate card'!$A$4:$G240,4,FALSE) -> Laminate Finish | F102: =VLOOKUP($B102,'Rate card'!$A$4:$G240,5,FALSE) -> MR ply + Inside laminate + finish laminate | G102: =VLOOKUP($B102,'Rate card'!$A$4:$G240,6,FALSE) -> Sqft | H102: =VLOOKUP($B102,'Rate card'!$A$4:$J240,8,FALSE) -> 1800 | I102: 20 | J102: =H102*I102 -> 36000 | K102: Overhead storage
A103: 6 | B103: CP 25 | C103: =VLOOKUP($B103,'Rate card'!$A$4:$G240,2,FALSE) -> Carpentry | D103: =VLOOKUP($B103,'Rate card'!$A$4:$G240,3,FALSE) -> Carcass Storage | E103: =VLOOKUP($B103,'Rate card'!$A$4:$G240,4,FALSE) -> Laminate Finish | F103: =VLOOKUP($B103,'Rate card'!$A$4:$G240,5,FALSE) -> MR ply + Inside laminate + finish laminate | G103: =VLOOKUP($B103,'Rate card'!$A$4:$G240,6,FALSE) -> Sqft | H103: =VLOOKUP($B103,'Rate card'!$A$4:$J240,8,FALSE) -> 1800 | I103: 18 | J103: =H103*I103 -> 32400 | K103: Bookshelf
A104: 7 | B104: CP 3 | C104: =VLOOKUP($B104,'Rate card'!$A$4:$G240,2,FALSE) -> Carpentry | D104: =VLOOKUP($B104,'Rate card'!$A$4:$G240,3,FALSE) -> Panelling with framing | E104: =VLOOKUP($B104,'Rate card'!$A$4:$G240,4,FALSE) -> Mirror Finish | F104: =VLOOKUP($B104,'Rate card'!$A$4:$G240,5,FALSE) -> MR ply + ply framing + 5mm clear mirror | G104: =VLOOKUP($B104,'Rate card'!$A$4:$G240,6,FALSE) -> Sqft | H104: =VLOOKUP($B104,'Rate card'!$A$4:$J240,8,FALSE) -> 750 | I104: =2*5 -> 10 | J104: =H104*I104 -> 7500 | K104: Mirror
A105: 8 | B105: CP 108 | C105: =VLOOKUP($B105,'Rate card'!$A$4:$G240,2,FALSE) -> Carpentry | D105: =VLOOKUP($B105,'Rate card'!$A$4:$G240,3,FALSE) -> Dresser | E105: =VLOOKUP($B105,'Rate card'!$A$4:$G240,4,FALSE) -> Laminate Finish | F105: =VLOOKUP($B105,'Rate card'!$A$4:$G240,5,FALSE) -> MRply + Inside laminate + finish laminate | G105: =VLOOKUP($B105,'Rate card'!$A$4:$G240,6,FALSE) -> Sqft | H105: 1800 | I105: 6 | J105: =H105*I105 -> 10800 | K105: Dresser | N105: =VLOOKUP($B105,'Rate card'!$A$4:$J240,7,FALSE) -> 1400 | O105: =I105*N105 -> 8400
A106: 9 | B106: CP 1 | C106: Carpentry | D106: Panelling with framing | E106: =VLOOKUP($B106,'Rate card'!$A$4:$G240,4,FALSE) -> Laminate Finish | F106: MR ply + ply framing + finish laminate | G106: =VLOOKUP($B106,'Rate card'!$A$4:$G240,6,FALSE) -> Sqft | H106: =VLOOKUP($B106,'Rate card'!$A$4:$J240,8,FALSE) -> 650 | I106: 40 | J106: =H106*I106 -> 26000 | K106: Wall panel
...

Sheet Amruta - recheck
A6: Date : | B6: 45730 | E6: Project Code :
A7: Client Name : | B7: Rahul Dhanawat | E7: Quotation Revision : | F7: 0
A8: Address : | B8: 10BKC | E8: Elemantra Contact Person : | F8: Payal- 93724 07848
A10: Quotation Summary | E10: SR.NO | F10: Description | G10: Amount
B11: Area in Sqft | D11: 1673 | E11: 1 | F11: Loose furniture | G11: =J247 -> 460000
A12: SR.NO | B12: Description | D12: Amount | E12: 2 | F12: Additional items | G12: =K261
A13: 1 | B13: Civil | D13: =M42 -> 778690 | F13: Total B | G13: =SUM(G11:G12) -> 460000
A14: 2 | B14: Plumbing | D14: =M48 -> 135000 | E14: Total A+B | G14: =D22+G11+G12 -> 9865831
A15: 3 | B15: Electrical | D15: =M51 -> 585550 | E15: GST 18% extra
A16: 4 | B16: POP | D16: =M58 -> 420000
A17: 5 | B17: Carpentry | D17: =M153 -> 5150250
A18: 6 | B18: Painting | D18: =M159 -> 1048478.5
A19: 7 | B19: Miscellenious | D19: =J164 -> 190000
B20: NON BOQ | D20: =J209 -> 597862.5
A21: 8 | B21: Design Consultation Fees(10%) | D21: 500000
B22: Total A | D22: =SUM(D13:D21) -> 9405831
B23: Per Sqft Rate | D23: =(D22/D11) -> 5622.1345
A25: Sr.No | B25: Id | C25: Item Name | D25: Category | E25: Item Details | F25: Description | G25: UOM | H25: Elemantra Rates | I25: Quantity 14.03.2025 | J25: Amount | K25: Area | L25: Difference Amount | M25: Amount | N25: Location | O25: Remark
A26: Civil
A27: 1 | C27: Demolition | D27: walls | E27: NA | F27: Demolition | G27: sq.ft | H27: 50 | I27: =H27-(H27*16.622%) -> 41.689 | J27: 40 | K27: =3+3+7*9+100 -> 169 | L27: Entire kitchen this includes below platform as well since wwe are changing verticles it will get damage . | M27: =K27*H27 -> 8450 | N27: servent ,samar & master bathroom door shifting | O27: keeping 100 sq.ft extra
A28: 2 | C28: civil | D28: walls | E28: NA | F28: Making | G28: sq.ft | H28: 200 | I28: - | J28: - | K28: =6*9 -> 54 | L28: Kitchen Window &door frame | M28: =K28*H28 -> 10800 | N28: samar & master bathroom wall sfifting
A29: 3 | C29: civil | D29: kitchen platform | E29: NA | F29: includes marble verticals, base marble, moulding , cutting etc , also includes floor bedding with marble | G29: rft | H29: 3000 | K29: 25 | M29: =K29*H29 -> 75000 | N29: kitchen platform
A30: 4 | C30: civil | D30: utility platform | E30: NA | F30: includes marble verticals, base marble, moulding , cutting etc , also includes floor bedding with marble | G30: sq.ft | H30: 3000 | K30: 9 | M30: =K30*H30 -> 27000 | N30: utility platform
A31: 5 | C31: civil | D31: Bathroom Tile | E31: 4x2 tile | F31: Laying of Wall tiles of approved colour and size as per drawing, over 20 mm thick cement mortar 1 : 4 ( 1 cement : 4 coarse sand ) and jointed with white cement slurry admixed with matching pigment to match the shade of tile & Grouting and spacer to be included. | G31: sq.ft | H31: 150 | K31: 1050 | M31: =K31*H31 -> 157500 | N31: 4 Bathroom Tile
A32: 6 | C32: civil | D32: Plaster | F32: Providing and laying 12-25 mm thick cement plaster of mis 1 : 4 (1 cement : 4 sand with 50% coarse sand & 50% fine sand) to all type of RCC / brick surface in line, level and plumb including providing wiremesh at all junctions of walls and ceilings etc. complete. | G32: sq.ft | H32: 120 | K32: 1600 | M32: =K32*H32 -> 192000 | N32: 4 Bathroom Tile
A33: 7 | C33: civil | D33: bathroom window frame | E33: single patti | F33: Granite Frame – up to 6 Inches width {Including Bevelling+ Cutting+ Polishing}. Excludes Granite cost | G33: sq.ft | H33: 130 | K33: =10*4+18+18+12+50 -> 138 | M33: =K33*H33 -> 17940 | N33: 4 bathroom window and 1 kitchen window and 1 show unit window
A34: 8 | C34: civil | D34: brickbat | F34: =VLOOKUP($B34,'Rate card'!$A$4:$G279,5,FALSE) -> 0 | G34: sq.ft | H34: 200 | K34: =40*4 -> 160 | M34: =K34*H34 -> 32000 | N34: 4 bathroom floor
A35: 9 | C35: civil | D35: waterproffing | E35: 2 cote | G35: sq.ft | H35: 250 | K35: =K34 -> 160 | M35: =K35*H35 -> 40000 | N35: 4 bathroom floor
A36: 10 | C36: civil | D36: Bathroom floor tile | F36: Laying of Wall tiles of approved colour and size as per drawing, over 20 mm thick cement mortar 1 : 4 ( 1 cement : 4 coarse sand ) and jointed with white cement slurry admixed with matching pigment to match the shade of tile & Grouting and spacer to be included. | G36: sq.ft | H36: 150 | K36: =K35 -> 160 | M36: =K36*H36 -> 24000 | N36: 4 bathroom floor
A37: 11 | C37: civil | D37: vanity counter | G37: ls | H37: 8000 | K37: 4 | M37: =K37*H37 -> 32000
A38: 12 | C38: civil | D38: ledge | G38: la | H38: 5000 | K38: 4 | M38: =K38*H38 -> 20000
A39: 13 | M39: =K39*H39 -> 0
A40: 14 | C40: civil | D40: plain tile | G40: sq.ft | H40: 120 | K40: 350 | M40: =K40*H40 -> 42000 | N40: tile behid utility and below platform
A41: 15 | C41: civil | D41: marble wardrobe in utility area | G41: sq.ft | H41: 400 | K41: 250 | M41: =K41*H41 -> 100000 | N41: marble wardrobe in utility area | O41: shutters are not included
K42: Total | M42: =SUM(M27:M41) -> 778690
A43: Plumbing
A44: 1 | B44: PL 2 | C44: Plumbing | D44: Bathroom Plumbing | E44: CP fitting work 1 Basin +cp fittings+Ceiling shower | F44: cp fiting and sanitary ware fixing in a bathroom | G44: per bathroom | H44: 35000 | I44: 1 | J44: =H44*I44 -> 35000 | K44: 1 | L44: =K44-J44 -> -34999 | M44: =K44*H44 -> 35000 | N44: Samar's toilet
A45: 2 | B45: PL 2 | C45: Plumbing | D45: Bathroom Plumbing | E45: Ceiling shower+body jets+c.p fittings | F45: cp fiting and sanitary ware fixing in a bathroom | G45: per bathroom | H45: 45000 | I45: 1 | J45: =H45*I45 -> 45000 | K45: 1 | L45: =K45-J45 -> -44999 | M45: =K45*H45 -> 45000 | N45: Master & Ranbeer
A46: 3 | B46: PL 2 | C46: Plumbing | D46: Bathroom Plumbing | E46: CP fitting work 1 Basin +cp fittings+Ceiling shower | F46: cp fiting and sanitary ware fixing in a bathroom | G46: per bathroom | H46: 35000 | I46: 1 | J46: =J44 -> 35000 | K46: 1 | L46: =K46-J46 -> -34999 | M46: =K46*H46 -> 35000 | N46: Mother's toilet
A47: 4 | B47: PL 3 | C47: =VLOOKUP($B47,'Rate card'!$A$4:$G279,2,FALSE) -> Plumbing | D47: =VLOOKUP($B47,'Rate card'!$A$4:$G279,3,FALSE) -> Kitchen Plumbing | E47: 3 sink+dishwahser+washing machine | F47: =VLOOKUP($B47,'Rate card'!$A$4:$G279,5,FALSE) -> all plumbing concealed wall and floor CPVC and UPVC pipes and chipping and replastering work | G47: =VLOOKUP($B47,'Rate card'!$A$4:$G279,6,FALSE) -> per kitchen | H47: 20000 | I47: 1 | J47: =H47*I47 -> 20000 | K47: 1 | L47: =K47-J47 -> -19999 | M47: =K47*H47 -> 20000 | N47: Kitchen & Utility
I48: Total | J48: =SUM(J44:J47) -> 135000 | K48: Total | L48: =sum(L44:L47) -> -134996 | M48: =SUM(M44:M47) -> 135000
A49: Electrical
A50: 1 | B50: E 1 | C50: Electrical | D50: 5A Switch socket, Light points,AC point, Fan point, Circuit wiring, DB Dressing | E50: new 5A Switch & Socket, light points, 15A, AC point, fan point from DB on wall include the price for wire and conduits, chipping and replastering on wall is included | F50: NOTE - The rates include fixingof switch / socket in position, effecting proper connections testing and commissioning of lighting fixtures and fans including lamps, control gear, power factor improvement capacitor and all fixing accessories that may be required to check. | G50: All areas | H50: 350 | I50: 1673 | J50: =H50*I50 -> 585550 | K50: 1673 | L50: =K50-J50 -> -583877 | M50: =K50*H50 -> 585550 | N50: All areas
I51: Total | J51: =SUM(J50) -> 585550 | K51: TOTAL | M51: =SUM(M50) -> 585550
A52: Pop/Falsceiling
A53: 1 | B53: FC 3 | C53: =VLOOKUP($B53,'Rate card'!$A$4:$G279,2,FALSE) -> False Ceiling | D53: =VLOOKUP($B53,'Rate card'!$A$4:$G279,3,FALSE) -> Gypsum Board Ceiling | E53: =VLOOKUP($B53,'Rate card'!$A$4:$G279,4,FALSE) -> Saint Gobain/Gyproc Board + local A Grade channel | F53: =VLOOKUP($B53,'Rate card'!$A$4:$G279,5,FALSE) -> 12.5mm thick gypsum board, with local A Grade Channel including all material, labour, transportation etc | Ceiling Channel and Intermediate Channel at 900mm c/c & Ceiling Section at 450mm c/c | G53: =VLOOKUP($B53,'Rate card'!$A$4:$G279,6,FALSE) -> Sqft | H53: 120 | I53: 1447 | J53: =H53*I53 -> 173640 | K53: 1450 | L53: =K53-J53 -> -172190 | M53: =K53*H53 -> 174000 | N53: All areas
A54: 2 | B54: FC 4 | C54: =VLOOKUP($B54,'Rate card'!$A$4:$G279,2,FALSE) -> False Ceiling | D54: =VLOOKUP($B54,'Rate card'!$A$4:$G279,3,FALSE) -> Gypsum Board Cove | E54: =VLOOKUP($B54,'Rate card'!$A$4:$G279,4,FALSE) -> Gypsum cove | F54: =VLOOKUP($B54,'Rate card'!$A$4:$G279,5,FALSE) -> 12.5mm thick gypsum board, with local A Grade Channel including all material, labour, transportation etc | Ceiling Channel and Intermediate Channel at 900mm c/c & Ceiling Section at 450mm c/c | G54: =VLOOKUP($B54,'Rate card'!$A$4:$G279,6,FALSE) -> Rft | H54: 120 | I54: 800 | J54: =H54*I54 -> 96000 | K54: 800 | L54: =K54-J54 -> -95200 | M54: =K54*H54 -> 96000 | N54: All areas
A55: 3 | B55: FC 5 | C55: =VLOOKUP($B55,'Rate card'!$A$4:$G279,2,FALSE) -> False Ceiling | D55: =VLOOKUP($B55,'Rate card'!$A$4:$G279,3,FALSE) -> Hilux Board ceiling | E55: =VLOOKUP($B55,'Rate card'!$A$4:$G279,4,FALSE) -> Hilux Board + local A Grade channel | F55: =VLOOKUP($B55,'Rate card'!$A$4:$G279,5,FALSE) -> 8mm Ramco hilux board, with local A Grade Channel including all material, labour, transportation etc | Ceiling Channel and Intermediate Channel at 900mm c/c & Ceiling Section at 450mm c/c | G55: =VLOOKUP($B55,'Rate card'!$A$4:$G279,6,FALSE) -> Sqft | H55: 200 | I55: 226 | J55: =H55*I55 -> 45200 | K55: 200 | L55: =K55-J55 -> -45000 | M55: =K55*H55 -> 40000 | N55: Toilets
A56: 4 | B56: FC 11 | C56: =VLOOKUP($B56,'Rate card'!$A$4:$G279,2,FALSE) -> POP | D56: =VLOOKUP($B56,'Rate card'!$A$4:$G279,3,FALSE) -> POP Punning | E56: =VLOOKUP($B56,'Rate card'!$A$4:$G279,4,FALSE) -> POP Punning (Plum) 12-25mm thick | F56: =VLOOKUP($B56,'Rate card'!$A$4:$G279,5,FALSE) -> Providing and applying 12-25 mm thick POP punning on wall /ceiling including scrapping and hacking the existing finished surface and applying plaster of paris in proper line and levels etc. complete. | G56: =VLOOKUP($B56,'Rate card'!$A$4:$G279,6,FALSE) -> Sqft | H56: 45 | I56: 1000 | J56: =H56*I56 -> 45000 | K56: 2000 | L56: =K56-J56 -> -43000 | M56: =K56*H56 -> 90000 | N56: Patch work wall punning
A57: 6 | B57: FC 17 | C57: =VLOOKUP($B57,'Rate card'!$A$4:$G279,2,FALSE) -> False Ceiling | D57: =VLOOKUP($B57,'Rate card'!$A$4:$G279,3,FALSE) -> Light Gala cutting | E57: =VLOOKUP($B57,'Rate card'!$A$4:$G279,4,FALSE) -> NA | F57: =VLOOKUP($B57,'Rate card'!$A$4:$G279,5,FALSE) -> NA | G57: =VLOOKUP($B57,'Rate card'!$A$4:$G279,6,FALSE) -> Nos | H57: 100 | I57: 200 | J57: =H57*I57 -> 20000 | K57: 200 | L57: =#REF!-#REF! -> #REF! | M57: =K57*H57 -> 20000 | N57: All areas
I58: Total | J58: =SUM(J53:J57) -> 379840 | K58: TOTAL | L58: Total | M58: =SUM(M53:M57) -> 420000
A59: Carpentry
A60: Living Room/Dining
A61: 1 | B61: CP 111 | C61: =VLOOKUP($B61,'Rate card'!$A$4:$G279,2,FALSE) -> Carpentry | D61: Main Door | E61: Veneer Finish | F61: MR ply +both side Veneer finish | G61: =VLOOKUP($B61,'Rate card'!$A$4:$G279,6,FALSE) -> Nos | H61: 65000 | I61: 1 | J61: =H61*I61 -> 65000 | K61: 1 | M61: =K61*H61 -> 65000 | N61: New main door
A62: 2 | B62: CP 111 | C62: Carpentry | D62: Ply Door Frame | E62: Veneer Finish | F62: MR ply + finish veneer from both sides | G62: Rft | H62: 750 | I62: =4+9+9 -> 22 | J62: =H62*I62 -> 16500 | K62: 22 | M62: =K62*H62 -> 16500 | N62: Door Frame
A63: 3 | B63: CP 25 | C63: =VLOOKUP($B63,'Rate card'!$A$4:$G279,2,FALSE) -> Carpentry | D63: =VLOOKUP($B63,'Rate card'!$A$4:$G279,3,FALSE) -> Carcass Storage | E63: =VLOOKUP($B63,'Rate card'!$A$4:$G279,4,FALSE) -> Laminate Finish | F63: =VLOOKUP($B63,'Rate card'!$A$4:$G279,5,FALSE) -> MR ply + Inside laminate + finish laminate | G63: =VLOOKUP($B63,'Rate card'!$A$4:$G279,6,FALSE) -> Sqft | H63: 1800 | I63: =7.5*10 -> 75 | J63: =H63*I63 -> 135000 | K63: =10.5*8.5 -> 89.25 | M63: =K63*H63 -> 160650 | N63: shoerack including seating drawer and side open shelfs
A64: 4 | C64: Carpentry | D64: Panelling with mirror | E64: Mirror Finish | G64: Sqft | H64: 750 | K64: =6*8.5 -> 51 | M64: =K64*H64 -> 38250 | N64: mirror panel | O64: no need mirror behind door
A65: 5 | B65: CP 6 | C65: Carpentry | D65: Panelling with framing | E65: Veneer Finish | F65: Mr Ply+ply framing+Finish Veneer + Onyx | G65: =VLOOKUP($B65,'Rate card'!$A$4:$G279,6,FALSE) -> Sqft | H65: 900 | I65: 1 | J65: =H65*I65 -> 900 | K65: 110 | M65: =K65*H65 -> 99000 | N65: Panelling in Passage including shoe room door
A66: 5 | B66: CP 6 | C66: Carpentry | D66: Panelling with framing | E66: Onyx Finish | F66: Mr Ply+ply framing+Finish Veneer + Onyx | G66: =VLOOKUP($B66,'Rate card'!$A$4:$G279,6,FALSE) -> Sqft | H66: 2500 | K66: 80 | M66: =K66*H66 -> 200000 | N66: Onyx Panel
A67: 6 | C67: Carpentry | D67: Console | E67: Onyx with acrylic base | G67: LS | H67: 35000 | K67: 1 | M67: =K67*H67 -> 35000 | N67: Console | O67: as per design
A68: 7 | B68: CP 25 | C68: =VLOOKUP($B68,'Rate card'!$A$4:$G279,2,FALSE) -> Carpentry | D68: =VLOOKUP($B68,'Rate card'!$A$4:$G279,3,FALSE) -> Carcass Storage | E68: MDF Finish | F68: MR ply + Inside laminate + pu finish | G68: R ft | H68: 5000 | I68: 7.5 | J68: =H68*I68 -> 37500 | K68: 8 | M68: =K68*H68 -> 40000 | N68: TV unit
A69: 8 | B69: CP 25 | C69: =VLOOKUP($B69,'Rate card'!$A$4:$G279,2,FALSE) -> Carpentry | D69: =VLOOKUP($B69,'Rate card'!$A$4:$G279,3,FALSE) -> Carcass Storage | E69: Veneer + Mirror + marble | F69: MR ply + Inside laminate + finish Veneer | G69: =VLOOKUP($B69,'Rate card'!$A$4:$G279,6,FALSE) -> Sqft | H69: 1100 | I69: =7*8 -> 56 | J69: =H69*I69 -> 61600 | K69: =11*9.5 -> 104.5 | M69: =K69*H69 -> 114950 | N69: TV panel | O69: Excluding Marble
A70: 9 | B70: CP 25 | C70: =VLOOKUP($B70,'Rate card'!$A$4:$G279,2,FALSE) -> Carpentry | D70: =VLOOKUP($B70,'Rate card'!$A$4:$G279,3,FALSE) -> Carcass Storage | E70: =VLOOKUP($B70,'Rate card'!$A$4:$G279,4,FALSE) -> Laminate Finish | F70: =VLOOKUP($B70,'Rate card'!$A$4:$G279,5,FALSE) -> MR ply + Inside laminate + finish laminate | G70: =VLOOKUP($B70,'Rate card'!$A$4:$G279,6,FALSE) -> Sqft | H70: 6000 | I70: =4*7 -> 28 | J70: =H70*I70 -> 168000 | K70: =3*7 -> 21 | M70: =K70*H70 -> 126000 | N70: Mandir
A71: 10 | B71: CP 25 | C71: =VLOOKUP($B71,'Rate card'!$A$4:$G279,2,FALSE) -> Carpentry | D71: =VLOOKUP($B71,'Rate card'!$A$4:$G279,3,FALSE) -> Carcass Storage | E71: Veneer + Onyx Finish | F71: =F68 -> MR ply + Inside laminate + pu finish | G71: =VLOOKUP($B71,'Rate card'!$A$4:$G279,6,FALSE) -> Sqft | H71: 2500 | I71: =5*3.5 -> 17.5 | J71: =H71*I71 -> 43750 | K71: =3*3 -> 9 | M71: =K71*H71 -> 22500 | N71: Console | O71: Hebind sofa
A72: 13 | B72: CP 6 | C72: Carpentry | D72: Panelling with framing | E72: CNC MDF + Veneer | F72: Mr Ply+ply framing+Finish Veneer + Onyx | G72: =VLOOKUP($B72,'Rate card'!$A$4:$G279,6,FALSE) -> Sqft | H72: 1500 | I72: =12*10 -> 120 | J72: =H72*I72 -> 180000 | K72: =12.5*8.5 -> 106.25 | M72: =K72*H72 -> 159375 | N72: Wall Panel on sofa wall | O72: incluing master bedroom door and 3d panel
A73: 14 | B73: CP 6 | C73: Carpentry | D73: Panelling with framing | E73: Veneer + Mirror + Marble | F73: MR ply + Inside laminate + finish Veneer | G73: =VLOOKUP($B73,'Rate card'!$A$4:$G279,6,FALSE) -> Sqft | H73: 1200 | I73: =29*10 -> 290 | J73: =H73*I73 -> 348000 | K73: =34*8.5 -> 289 | M73: =K73*H73 -> 346800 | N73: Panelling on mother's & samar's bed room wall | O73: Excluding Marble
A74: 13 | B74: CP 6 | C74: Carpentry | D74: Panelling with framing | E74: Mirror Finish | F74: Mr Ply+ply framing+Finish Veneer + Onyx | G74: =VLOOKUP($B74,'Rate card'!$A$4:$G279,6,FALSE) -> Sqft | H74: 1000 | I74: =12*10 -> 120 | J74: =H74*I74 -> 120000 | K74: =5*8.5 -> 42.5 | M74: =K74*H74 -> 42500 | N74: mirror panel on dining wall | O74: brown mirror
A75: Modular Kitchen
A76: 1 | B76: CP 25 | C76: =VLOOKUP($B76,'Rate card'!$A$4:$G279,2,FALSE) -> Carpentry | D76: =VLOOKUP($B76,'Rate card'!$A$4:$G279,3,FALSE) -> Carcass Storage | E76: Acrylic Finish | F76: Marine ply + Inside laminate + Acrylic Finish | G76: =VLOOKUP($B76,'Rate card'!$A$4:$G279,6,FALSE) -> Sqft | H76: 2700 | I76: =18.5*2.5 -> 46.25 | J76: =H76*I76 -> 124875 | K76: =20*2.5 -> 50 | M76: =K76*H76 -> 135000 | N76: undercounter
A77: 2 | B77: CP 25 | C77: =VLOOKUP($B77,'Rate card'!$A$4:$G279,2,FALSE) -> Carpentry | D77: =VLOOKUP($B77,'Rate card'!$A$4:$G279,3,FALSE) -> Carcass Storage | E77: Acrylic Finish | F77: Marine ply + Inside laminate + Acrylic Finish | G77: =VLOOKUP($B77,'Rate card'!$A$4:$G279,6,FALSE) -> Sqft | H77: 2700 | I77: =28+11.25*2.5+4*2.5 -> 66.125 | J77: =H77*I77 -> 178537.5 | K77: =20*5.5 -> 110 | M77: =K77*H77 -> 297000 | N77: overhead+loft
A78: 3 | B78: CP 25 | C78: =VLOOKUP($B78,'Rate card'!$A$4:$G279,2,FALSE) -> Carpentry | D78: =VLOOKUP($B78,'Rate card'!$A$4:$G279,3,FALSE) -> Carcass Storage | E78: Acrylic Finish | F78: Marine ply + Inside laminate + Acrylic Finish | G78: =VLOOKUP($B78,'Rate card'!$A$4:$G279,6,FALSE) -> Sqft | H78: 2700 | I78: =4*10 -> 40 | J78: =H78*I78 -> 108000 | K78: =4*10.5 -> 42 | M78: =K78*H78 -> 113400 | N78: Pantry Storage, next to mandir and oven unit and side glass unit
A79: 4 | B79: CP 61 | C79: =VLOOKUP($B79,'Rate card'!$A$4:$G279,2,FALSE) -> Carpentry | D79: =VLOOKUP($B79,'Rate card'!$A$4:$G279,3,FALSE) -> Kitchen Basket | E79: tandem | F79: =VLOOKUP($B79,'Rate card'!$A$4:$G279,5,FALSE) -> Basket + Channel+Fitting charges | G79: =VLOOKUP($B79,'Rate card'!$A$4:$G279,6,FALSE) -> Nos | H79: 8000 | I79: 5 | J79: =H79*I79 -> 40000 | K79: 14 | M79: =K79*H79 -> 112000 | N79: Modular kitchen
A80: 5 | B80: CP 64 | C80: =VLOOKUP($B80,'Rate card'!$A$4:$G279,2,FALSE) -> Carpentry | D80: =VLOOKUP($B80,'Rate card'!$A$4:$G279,3,FALSE) -> Wicker basket | E80: =VLOOKUP($B80,'Rate card'!$A$4:$G279,4,FALSE) -> Wicker basket | F80: =VLOOKUP($B80,'Rate card'!$A$4:$G279,5,FALSE) -> Basket + Channel+Fitting charges | G80: =VLOOKUP($B80,'Rate card'!$A$4:$G279,6,FALSE) -> Nos | H80: 6000 | I80: 2 | J80: =H80*I80 -> 12000 | K80: 2 | M80: =K80*H80 -> 12000 | N80: Modular kitchen
C81: Carpentry | D81: Back Painted Glass | E81: Above kitchen PLatform | G81: Sqft | H81: 1200 | I81: 30 | J81: =I81*H81 -> 36000 | K81: 30 | M81: =K81*H81 -> 36000 | N81: Kitchen BAck Painted Glass
A82: 6 | C82: Carpentry | D82: Kitchen Sliding door | E82: Flutted glass finish | F82: Modular Kitchen | G82: Sqft | H82: 1650 | I82: =3*7 -> 21 | J82: =H82*I82 -> 34650 | K82: =3*7.5 -> 22.5 | M82: =K82*H82 -> 37125 | N82: kitchen
A83: Utility | M83: =K83*H83 -> 0
A84: 1 | B84: CP 25 | C84: =VLOOKUP($B84,'Rate card'!$A$4:$G279,2,FALSE) -> Carpentry | D84: =VLOOKUP($B84,'Rate card'!$A$4:$G279,3,FALSE) -> Carcass Storage | E84: =VLOOKUP($B84,'Rate card'!$A$4:$G279,4,FALSE) -> Laminate Finish | F84: Marine ply + Inside laminate + finish laminate | G84: =VLOOKUP($B84,'Rate card'!$A$4:$G279,6,FALSE) -> Sqft | H84: 1800 | I84: =5.5*2.5 -> 13.75 | J84: =H84*I84 -> 24750 | K84: =12*2.5 -> 30 | M84: =K84*H84 -> 54000 | N84: undercounter
A85: 2 | B85: CP 25 | C85: =VLOOKUP($B85,'Rate card'!$A$4:$G279,2,FALSE) -> Carpentry | D85: =VLOOKUP($B85,'Rate card'!$A$4:$G279,3,FALSE) -> Carcass Storage | E85: =VLOOKUP($B85,'Rate card'!$A$4:$G279,4,FALSE) -> Laminate Finish | F85: Marine ply + Inside laminate + finish laminate | G85: =VLOOKUP($B85,'Rate card'!$A$4:$G279,6,FALSE) -> Sqft | H85: 750 | I85: =10*10 -> 100 | J85: =H85*I85 -> 75000 | K85: =12*8.5 -> 102 | M85: =K85*H85 -> 76500 | N85: only shutters
A86: 3 | B86: CP 117 | C86: =VLOOKUP($B86,'Rate card'!$A$4:$G279,2,FALSE) -> Carpentry | D86: =VLOOKUP($B86,'Rate card'!$A$4:$G279,3,FALSE) -> Carcass Storage | E86: =VLOOKUP($B86,'Rate card'!$A$4:$G279,4,FALSE) -> Laminate Finish | F86: Marine ply + Inside laminate + finish laminate | G86: =VLOOKUP($B86,'Rate card'!$A$4:$G279,6,FALSE) -> Sqft | H86: 1800 | I86: 22 | J86: =H86*I86 -> 39600 | K86: =4*5 -> 20 | M86: =K86*H86 -> 36000 | N86: Washing machine storage
A87: Mother's Bedroom
A88: 1 | B88: CP 21 | C88: =VLOOKUP($B88,'Rate card'!$A$4:$G279,2,FALSE) -> Carpentry | D88: =VLOOKUP($B88,'Rate card'!$A$4:$G279,3,FALSE) -> Bed | E88: =VLOOKUP($B88,'Rate card'!$A$4:$G279,4,FALSE) -> Laminate Finish | F88: MR ply panelling + Foam material and labour. Excludes Fabric cost | G88: =VLOOKUP($B88,'Rate card'!$A$4:$G279,6,FALSE) -> Sqft | H88: 1800 | I88: =5.5*6.5 -> 35.75 | J88: =H88*I88 -> 64350 | K88: =6*6.5 -> 39 | M88: =K88*H88 -> 70200 | N88: king size bed
A89: 2 | B89: CP 45 | C89: =VLOOKUP($B89,'Rate card'!$A$4:$G279,2,FALSE) -> Carpentry | D89: =VLOOKUP($B89,'Rate card'!$A$4:$G279,3,FALSE) -> Headboard | E89: =VLOOKUP($B89,'Rate card'!$A$4:$G279,4,FALSE) -> Fabric Finish | F89: =VLOOKUP($B89,'Rate card'!$A$4:$G279,5,FALSE) -> MR ply panelling + Foam material and labour. Excludes Fabric cost | G89: =VLOOKUP($B89,'Rate card'!$A$4:$G279,6,FALSE) -> Sqft | H89: 1300 | I89: =5.5*3 -> 16.5 | J89: =H89*I89 -> 21450 | K89: =9*4.5 -> 40.5 | M89: =K89*H89 -> 52650 | N89: Headboard
A90: 3 | B90: CP 46 | C90: =VLOOKUP($B90,'Rate card'!$A$4:$G279,2,FALSE) -> Carpentry | D90: Bed side table | E90: =VLOOKUP($B90,'Rate card'!$A$4:$G279,4,FALSE) -> Laminate Finish | F90: =VLOOKUP($B90,'Rate card'!$A$4:$G279,5,FALSE) -> MR ply + Inside laminate + finish laminate (1 Drawer) | G90: =VLOOKUP($B90,'Rate card'!$A$4:$G279,6,FALSE) -> Nos | H90: 20000 | I90: 2 | J90: =H90*I90 -> 40000 | K90: 2 | M90: =K90*H90 -> 40000 | N90: Bed side table
A91: 4 | B91: CP 25 | C91: =VLOOKUP($B91,'Rate card'!$A$4:$G279,2,FALSE) -> Carpentry | D91: =VLOOKUP($B91,'Rate card'!$A$4:$G279,3,FALSE) -> Carcass Storage | E91: =VLOOKUP($B91,'Rate card'!$A$4:$G279,4,FALSE) -> Laminate Finish | F91: =VLOOKUP($B91,'Rate card'!$A$4:$G279,5,FALSE) -> MR ply + Inside laminate + finish laminate | G91: Sqft | H91: 1800 | I91: 7 | J91: =H91*I91 -> 12600 | K91: =7*1 -> 7 | M91: =K91*H91 -> 12600 | N91: Dresser
A92: 5 | B92: CP 25 | C92: =VLOOKUP($B92,'Rate card'!$A$4:$G279,2,FALSE) -> Carpentry | D92: =VLOOKUP($B92,'Rate card'!$A$4:$G279,3,FALSE) -> Carcass Storage | E92: =VLOOKUP($B92,'Rate card'!$A$4:$G279,4,FALSE) -> Laminate Finish | F92: =VLOOKUP($B92,'Rate card'!$A$4:$G279,5,FALSE) -> MR ply + Inside laminate + finish laminate | G92: =VLOOKUP($B92,'Rate card'!$A$4:$G279,6,FALSE) -> Sqft | H92: =VLOOKUP($B92,'Rate card'!$A$4:$J279,8,FALSE) -> 1800 | I92: =5*10 -> 50 | J92: =H92*I92 -> 90000 | K92: =5*9 -> 45 | M92: =K92*H92 -> 81000 | N92: Wardrobe near entrance
A93: 6 | B93: CP 3 | C93: =VLOOKUP($B93,'Rate card'!$A$4:$G279,2,FALSE) -> Carpentry | D93: =VLOOKUP($B93,'Rate card'!$A$4:$G279,3,FALSE) -> Panelling with framing | E93: =VLOOKUP($B93,'Rate card'!$A$4:$G279,4,FALSE) -> Mirror Finish | F93: =VLOOKUP($B93,'Rate card'!$A$4:$G279,5,FALSE) -> MR ply + ply framing + 5mm clear mirror | G93: =VLOOKUP($B93,'Rate card'!$A$4:$G279,6,FALSE) -> Sqft | H93: =VLOOKUP($B93,'Rate card'!$A$4:$J279,8,FALSE) -> 750 | I93: =2.5*7 -> 17.5 | J93: =H93*I93 -> 13125 | K93: =7*2 -> 14 | M93: =K93*H93 -> 10500 | N93: Mirror
A94: 7 | B94: CP 1 | C94: Carpentry | D94: Panelling with framing | E94: =VLOOKUP($B94,'Rate card'!$A$4:$G279,4,FALSE) -> Laminate Finish | F94: MR ply + ply framing + finish laminate | G94: =VLOOKUP($B94,'Rate card'!$A$4:$G279,6,FALSE) -> Sqft | H94: 950 | I94: 80 | J94: =H94*I94 -> 76000 | K94: =9*9 -> 81 | M94: =K94*H94 -> 76950 | N94: Wall panel | O94: including rafters nad charcol sheet
A95: 8 | B95: CP 17 | C95: =VLOOKUP($B95,'Rate card'!$A$4:$G279,2,FALSE) -> Carpentry | D95: =VLOOKUP($B95,'Rate card'!$A$4:$G279,3,FALSE) -> Wardrobe | E95: =VLOOKUP($B95,'Rate card'!$A$4:$G279,4,FALSE) -> Laminate Finish | F95: =VLOOKUP($B95,'Rate card'!$A$4:$G279,5,FALSE) -> MR ply + Inside laminate + finish laminate. (Includes 4 pencil drawers, Handles of base rate Rs.1000/pc) | G95: =VLOOKUP($B95,'Rate card'!$A$4:$G279,6,FALSE) -> Sqft | H95: 2200 | I95: =7.5*10 -> 75 | J95: =H95*I95 -> 165000 | K95: =10*9 -> 90 | M95: =K95*H95 -> 198000 | N95: Wardrobe
A96: 9 | B96: CP 6 | C96: =VLOOKUP($B96,'Rate card'!$A$4:$G279,2,FALSE) -> Carpentry | D96: =VLOOKUP($B96,'Rate card'!$A$4:$G279,3,FALSE) -> Panelling with framing | E96: =VLOOKUP($B96,'Rate card'!$A$4:$G279,4,FALSE) -> MDF | F96: =VLOOKUP($B96,'Rate card'!$A$4:$G279,5,FALSE) -> MR ply + ply framing + 12mm MDF | G96: =VLOOKUP($B96,'Rate card'!$A$4:$G279,6,FALSE) -> Sqft | H96: 600 | I96: =12*2.5 -> 30 | J96: =H96*I96 -> 18000 | K96: =10*2 -> 20 | M96: =K96*H96 -> 12000 | N96: pelmet
A97: Samar's Bedroom
A98: 1 | B98: CP 21 | C98: =VLOOKUP($B98,'Rate card'!$A$4:$G279,2,FALSE) -> Carpentry | D98: =VLOOKUP($B98,'Rate card'!$A$4:$G279,3,FALSE) -> Bed | E98: =VLOOKUP($B98,'Rate card'!$A$4:$G279,4,FALSE) -> Laminate Finish | F98: =VLOOKUP($B98,'Rate card'!$A$4:$G279,5,FALSE) -> MR ply + Inside laminate + finish laminate | G98: =VLOOKUP($B98,'Rate card'!$A$4:$G279,6,FALSE) -> Sqft | H98: 2200 | I98: =6*6.5 -> 39 | J98: =H98*I98 -> 85800 | K98: =6*6.5 -> 39 | M98: =K98*H98 -> 85800 | N98: King size Bed, 2 internal drawers+ 1 side box
A99: 2 | B99: CP 45 | C99: =VLOOKUP($B99,'Rate card'!$A$4:$G279,2,FALSE) -> Carpentry | D99: =VLOOKUP($B99,'Rate card'!$A$4:$G279,3,FALSE) -> Headboard | E99: =VLOOKUP($B99,'Rate card'!$A$4:$G279,4,FALSE) -> Fabric Finish | F99: =VLOOKUP($B99,'Rate card'!$A$4:$G279,5,FALSE) -> MR ply panelling + Foam material and labour. Excludes Fabric cost | G99: =VLOOKUP($B99,'Rate card'!$A$4:$G279,6,FALSE) -> Sqft | H99: 1300 | I99: =6*3.5 -> 21 | J99: =H99*I99 -> 27300 | K99: =6*4.5 -> 27 | M99: =K99*H99 -> 35100 | N99: Headboard
A100: 3 | B100: CP 46 | C100: =VLOOKUP($B100,'Rate card'!$A$4:$G279,2,FALSE) -> Carpentry | D100: Bed side table | E100: =VLOOKUP($B100,'Rate card'!$A$4:$G279,4,FALSE) -> Laminate Finish | F100: =VLOOKUP($B100,'Rate card'!$A$4:$G279,5,FALSE) -> MR ply + Inside laminate + finish laminate (1 Drawer) | G100: =VLOOKUP($B100,'Rate card'!$A$4:$G279,6,FALSE) -> Nos | H100: 20000 | I100: 1 | J100: =H100*I100 -> 20000 | K100: 2 | M100: =K100*H100 -> 40000 | N100: Bed side table
A101: 4 | B101: CP 49 | C101: =VLOOKUP($B101,'Rate card'!$A$4:$G279,2,FALSE) -> Carpentry | D101: =VLOOKUP($B101,'Rate card'!$A$4:$G279,3,FALSE) -> Study Table | E101: =VLOOKUP($B101,'Rate card'!$A$4:$G279,4,FALSE) -> Laminate Finish | F101: =VLOOKUP($B101,'Rate card'!$A$4:$G279,5,FALSE) -> MR ply + Inside laminate + finish laminate (2 pencil drawers) | G101: =VLOOKUP($B101,'Rate card'!$A$4:$G279,6,FALSE) -> Rft | H101: 4500 | I101: 4 | J101: =H101*I101 -> 18000 | K101: 4.5 | M101: =K101*H101 -> 20250 | N101: Study table
A102: 5 | B102: CP 25 | C102: =VLOOKUP($B102,'Rate card'!$A$4:$G279,2,FALSE) -> Carpentry | D102: =VLOOKUP($B102,'Rate card'!$A$4:$G279,3,FALSE) -> Carcass Storage | E102: =VLOOKUP($B102,'Rate card'!$A$4:$G279,4,FALSE) -> Laminate Finish | F102: =VLOOKUP($B102,'Rate card'!$A$4:$G279,5,FALSE) -> MR ply + Inside laminate + finish laminate | G102: =VLOOKUP($B102,'Rate card'!$A$4:$G279,6,FALSE) -> Sqft | H102: =VLOOKUP($B102,'Rate card'!$A$4:$J279,8,FALSE) -> 1800 | I102: 20 | J102: =H102*I102 -> 36000 | K102: =4.5*5.5 -> 24.75 | M102: =K102*H102 -> 44550 | N102: Overhead storage
A103: 6 | B103: CP 25 | C103: =VLOOKUP($B103,'Rate card'!$A$4:$G279,2,FALSE) -> Carpentry | D103: =VLOOKUP($B103,'Rate card'!$A$4:$G279,3,FALSE) -> Carcass Storage | E103: =VLOOKUP($B103,'Rate card'!$A$4:$G279,4,FALSE) -> Laminate Finish | F103: =VLOOKUP($B103,'Rate card'!$A$4:$G279,5,FALSE) -> MR ply + Inside laminate + finish laminate | G103: =VLOOKUP($B103,'Rate card'!$A$4:$G279,6,FALSE) -> Sqft | H103: =VLOOKUP($B103,'Rate card'!$A$4:$J279,8,FALSE) -> 1800 | I103: 18 | J103: =H103*I103 -> 32400 | K103: =5*7 -> 35 | M103: =K103*H103 -> 63000 | N103: Bookshelf
A104: 7 | B104: CP 3 | C104: =VLOOKUP($B104,'Rate card'!$A$4:$G279,2,FALSE) -> Carpentry | D104: =VLOOKUP($B104,'Rate card'!$A$4:$G279,3,FALSE) -> Panelling with framing | E104: =VLOOKUP($B104,'Rate card'!$A$4:$G279,4,FALSE) -> Mirror Finish | F104: =VLOOKUP($B104,'Rate card'!$A$4:$G279,5,FALSE) -> MR ply + ply framing + 5mm clear mirror | G104: =VLOOKUP($B104,'Rate card'!$A$4:$G279,6,FALSE) -> Sqft | H104: =VLOOKUP($B104,'Rate card'!$A$4:$J279,8,FALSE) -> 750 | I104: =2*5 -> 10 | J104: =H104*I104 -> 7500 | K104: =3*3 -> 9 | M104: =K104*H104 -> 6750 | N104: Mirror
A105: 8 | B105: CP 108 | C105: =VLOOKUP($B105,'Rate card'!$A$4:$G279,2,FALSE) -> Carpentry | D105: =VLOOKUP($B105,'Rate card'!$A$4:$G279,3,FALSE) -> Dresser | E105: =VLOOKUP($B105,'Rate card'!$A$4:$G279,4,FALSE) -> Laminate Finish | F105: =VLOOKUP($B105,'Rate card'!$A$4:$G279,5,FALSE) -> MRply + Inside laminate + finish laminate | G105: =VLOOKUP($B105,'Rate card'!$A$4:$G279,6,FALSE) -> Sqft | H105: 1800 | I105: 6 | J105: =H105*I105 -> 10800 | K105: 0 | M105: =K105*H105 -> 0 | N105: Dresser
A106: 9 | B106: CP 1 | C106: Carpentry | D106: Panelling with framing | E106: =VLOOKUP($B106,'Rate card'!$A$4:$G279,4,FALSE) -> Laminate Finish | F106: MR ply + ply framing + finish laminate | G106: =VLOOKUP($B106,'Rate card'!$A$4:$G279,6,FALSE) -> Sqft | H106: =VLOOKUP($B106,'Rate card'!$A$4:$J279,8,FALSE) -> 650 | I106: 40 | J106: =H106*I106 -> 26000 | K106: 0 | M106: =K106*H106 -> 0 | N106: Wall panel
A107: 10 | B107: CP 17 | C107: =VLOOKUP($B107,'Rate card'!$A$4:$G279,2,FALSE) -> Carpentry | D107: =VLOOKUP($B107,'Rate card'!$A$4:$G279,3,FALSE) -> Wardrobe | E107: Back painted | F107: =VLOOKUP($B107,'Rate card'!$A$4:$G279,5,FALSE) -> MR ply + Inside laminate + finish laminate. (Includes 4 pencil drawers, Handles of base rate Rs.1000/pc) | G107: =VLOOKUP($B107,'Rate card'!$A$4:$G279,6,FALSE) -> Sqft | H107: 2500 | I107: =5*10 -> 50 | J107: =H107*I107 -> 125000 | K107: =5*9 -> 45 | M107: =K107*H107 -> 112500 | N107: Wardrobe entrance
...

Sheet 18.06.25
A6: Date : | B6: 45730 | E6: Project Code :
A7: Client Name : | B7: Rahul Dhanawat | E7: Quotation Revision : | F7: 0
A8: Address : | B8: 10BKC | E8: Elemantra Contact Person : | F8: Payal- 93724 07848
S9: Add / modify | W9: Note
A10: Quotation Summary | G10: SR.NO | H10: Description | I10: Amount | S10: 1. Balcony
B11: Area in Sqft | D11: 1673 | G11: 1 | H11: Loose furniture | I11: =J248 -> 460000 | S11: 2. Utility tiles
A12: SR.NO | B12: Description | D12: Amount | G12: 2 | H12: Additional items | I12: =L262 -> 2810400 | S12: 3. Water outlets
A13: 1 | B13: Civil | D13: =L43 -> 845895 | H13: Total B | I13: =SUM(I11:I12) -> 3270400 | S13: 4. Kitchen flooring
A14: 2 | B14: Plumbing | D14: =L49 -> 185000 | G14: Total A+B | I14: =D22+I11+I12 -> 12941066 | S14: 5. Smart lock at the entrace
A15: 3 | B15: Electrical | D15: =L52 -> 585550 | G15: GST 18% extra | S15: 6. Exhaust fans
A16: 4 | B16: POP | D16: =L60 -> 394840 | S16: 7. Rubber bidding
A17: 5 | B17: Carpentry | D17: =L153 -> 5298040 | S17: 8. Shaft closing
A18: 6 | B18: Painting | D18: =L160 -> 1073478.5
A19: 7 | B19: Miscellenious | D19: =J165 -> 190000
B20: NON BOQ | D20: =J210 -> 597862.5
A21: 8 | B21: Design Consultation Fees(10%) | D21: 500000
B22: Total A | D22: =SUM(D13:D21) -> 9670666
B23: Per Sqft Rate | D23: =(D22/D11) -> 5780.434
A25: Sr.No | B25: Id | C25: Item Name | D25: Category | E25: Item Details | F25: Description | G25: UOM | H25: Elemantra Rates | I25: Quantity 14.03.2025 | J25: Amount | K25: Quantity 18.06.2025 | L25: Amount 18.06.2025 | M25: Difference Amount | N25: Location | O25: Remark | Q25: Vendor Rate | R25: Amount
A26: Civil
A27: 1 | B27: D2 | C27: =VLOOKUP($B27,'Rate card'!$A$4:$G280,2,FALSE) -> Demolition | D27: =VLOOKUP($B27,'Rate card'!$A$4:$G280,3,FALSE) -> Brickwall - 6" | E27: =VLOOKUP($B27,'Rate card'!$A$4:$G280,4,FALSE) -> NA | F27: =VLOOKUP($B27,'Rate card'!$A$4:$G280,5,FALSE) -> Demolition | G27: =VLOOKUP($B27,'Rate card'!$A$4:$G280,6,FALSE) -> Sqft | H27: 500 | I27: =3*10+3*10 -> 60 | J27: =I27*H27 -> 30000 | K27: =1.5*10.5+2.25*2.6+3*10.25+2.75*10.25+2.75*8+3*10.25 -> 133.2875 | L27: =K27*H27 -> 66643.75 | M27: =L27-J27 -> 36643.75 | N27: Kitchen & common toilet+Samar toilet+Master bed room | O27: Qty ⬆️ | R27: =VLOOKUP($B27,'Rate card'!$A$4:$J280,7,FALSE) -> 20 | S27: =L27/$D$22 -> 0.0068913299
A28: 2 | C28: Civil | D28: Brickwall - 4" | E28: =E27 -> NA | F28: Providing and laying 4" (100 MM) brick partition wall with good quality bricks well burnt 1st class in cement mortar 1:4 (1 cement : 4 coarse sand) including providing 2 nos of 6mm dia MS round bars at every IV course including scaffolding, curing, raking out joints etc. complete. | G28: =G27 -> Sqft | H28: 150 | I28: =3*10+3*10 -> 60 | J28: =I28*H28 -> 9000 | K28: =1.5*10.25+3*10.25+2.75*8+3*10.25 -> 98.875 | L28: =K28*H28 -> 14831.25 | M28: =L28-J28 -> 5831.25 | N28: Kitchen,samar toilet,master toilet | O28: Qty ⬆️ | S28: =L28/$D$22 -> 0.0015336327
A29: 3 | C29: Civil | D29: Plaster | E29: =E27 -> NA | F29: Providing and laying 12-25 mm thick cement plaster of mis 1 : 4 (1 cement : 4 sand with 50% coarse sand & 50% fine sand) to all type of RCC / brick surface in line, level and plumb including providing wiremesh at all junctions of walls and ceilings etc. complete. | G29: Sqft | H29: 120 | I29: =I28 -> 60 | J29: =I29*H29 -> 7200 | K29: 200 | L29: =K29*H29 -> 24000 | M29: =L29-J29 -> 16800 | N29: Kitchen,samar toilet,master toilet | O29: Qty ⬆️ | S29: =L29/$D$22 -> 0.0024817319
A30: 4 | B30: C23 | C30: =VLOOKUP($B30,'Rate card'!$A$4:$G280,2,FALSE) -> Civil | D30: =VLOOKUP($B30,'Rate card'!$A$4:$G280,3,FALSE) -> Kitchen platform | E30: =VLOOKUP($B30,'Rate card'!$A$4:$G280,4,FALSE) -> Fully Modular Kitchen - Granite/Marble | F30: =VLOOKUP($B30,'Rate card'!$A$4:$G280,5,FALSE) -> Laying marble (18mm thk) of approved colour, shade and size on the platform as per drawing / flooring pattern, matching of grain, laid on a levelled, neat cement base with adhesive of approved make (laticrete) grouted of matching colour pigment to match the shade of stone and protection of floor to be taken into account.(cement concrete base taken into account in the civil works ) | G30: =VLOOKUP($B30,'Rate card'!$A$4:$G280,6,FALSE) -> Sqft | H30: 3000 | I30: =18.5*2 -> 37 | J30: =I30*H30 -> 111000 | K30: 52 | L30: =K30*H30 -> 156000 | M30: =L30-J30 -> 45000 | N30: Kitchen | O30: Qty ⬆️ | R30: =VLOOKUP($B30,'Rate card'!$A$4:$J280,7,FALSE) -> 150 | S30: =L30/$D$22 -> 0.016131257
A31: 5 | C31: Civil | D31: Plaster | E31: =E29 -> NA | F31: Providing and laying 12-25 mm thick cement plaster of mis 1 : 4 (1 cement : 4 sand with 50% coarse sand & 50% fine sand) to all type of RCC / brick surface in line, level and plumb including providing wiremesh at all junctions of walls and ceilings etc. complete. | G31: Sqft | H31: 120 | I31: =I32 -> 192.5 | J31: =I31*H31 -> 23100 | K31: 185 | L31: =K31*H31 -> 22200 | M31: =L31-J31 -> -900 | N31: Kitchen wall | O31: Qty ⬇️ | S31: =L31/$D$22 -> 0.002295602
A32: 6 | C32: Civil | D32: Kitchen wall tiles | E32: Upto( 4' x 2' ) tiles laying | F32: Laying of Wall tiles of approved colour and size as per drawing, over 20 mm thick cement mortar 1 : 4 ( 1 cement : 4 coarse sand ) and jointed with white cement slurry admixed with matching pigment to match the shade of tile & Grouting and spacer to be included. | G32: Sqft | H32: 140 | I32: =11.25*7+1.5*7+12*7+2.75*7 -> 192.5 | J32: =I32*H32 -> 26950 | K32: 186 | L32: =K32*H32 -> 26040 | M32: =L32-J32 -> -910 | N32: Kitchen | O32: Qty ⬇️ | S32: =L32/$D$22 -> 0.0026926791
A33: 7 | B33: C27 | C33: =VLOOKUP($B33,'Rate card'!$A$4:$G280,2,FALSE) -> Civil | D33: =VLOOKUP($B33,'Rate card'!$A$4:$G280,3,FALSE) -> Brickbat | E33: =VLOOKUP($B33,'Rate card'!$A$4:$G280,4,FALSE) | F33: =VLOOKUP($B33,'Rate card'!$A$4:$G280,5,FALSE) -> Providing & laying brickbat coba (6") with PCC | G33: =VLOOKUP($B33,'Rate card'!$A$4:$G280,6,FALSE) -> Sqft | H33: =VLOOKUP($B33,'Rate card'!$A$4:$J280,8,FALSE) -> 200 | I33: =55+40+40+57 -> 192 | J33: =H33*I33 -> 38400 | K33: =55+40+40+57 -> 192 | L33: =K33*H33 -> 38400 | M33: =L33-J33 -> 0 | N33: Toilets | Q33: =VLOOKUP($B33,'Rate card'!$A$4:$J280,7,FALSE) -> 150 | R33: =I33*Q33 -> 28800 | S33: =L33/$D$22 -> 0.003970771
A34: 8 | B34: C30 | C34: =VLOOKUP($B34,'Rate card'!$A$4:$G280,2,FALSE) -> Civil | D34: =VLOOKUP($B34,'Rate card'!$A$4:$G280,3,FALSE) -> Waterproofing | E34: Floor & walls | F34: =VLOOKUP($B34,'Rate card'!$A$4:$G280,5,FALSE) -> Waterproofing with 2 coats | G34: =VLOOKUP($B34,'Rate card'!$A$4:$G280,6,FALSE) -> Sqft | H34: =VLOOKUP($B34,'Rate card'!$A$4:$J280,8,FALSE) -> 80 | I34: 350 | J34: =H34*I34 -> 28000 | K34: 500 | L34: =K34*H34 -> 40000 | M34: =L34-J34 -> 12000 | N34: Toilets | Q34: =VLOOKUP($B34,'Rate card'!$A$4:$J280,7,FALSE) -> 50 | R34: =I34*Q34 -> 17500 | S34: =L34/$D$22 -> 0.0041362198
A35: 9 | C35: Civil | D35: Plaster | E35: =E31 -> NA | F35: Providing and laying 12-25 mm thick cement plaster of mis 1 : 4 (1 cement : 4 sand with 50% coarse sand & 50% fine sand) to all type of RCC / brick surface in line, level and plumb including providing wiremesh at all junctions of walls and ceilings etc. complete. | G35: Sqft | H35: 120 | I35: =272+234+234+275 -> 1015 | J35: =I35*H35 -> 121800 | K35: =272+234+234+275 -> 1015 | L35: =K35*H35 -> 121800 | M35: =L35-J35 -> 0 | N35: Bathroom walls | S35: =L35/$D$22 -> 0.012594789
A36: 10 | C36: Civil | D36: Bathroom floor & wall tiles | E36: Upto( 4' x 2' ) tiles laying | F36: Laying of Wall tiles of approved colour and size as per drawing, over 20 mm thick cement mortar 1 : 4 ( 1 cement : 4 coarse sand ) and jointed with white cement slurry admixed with matching pigment to match the shade of tile & Grouting and spacer to be included. | G36: Sqft | H36: 140 | I36: =55+272+40+234+40+234+57+275 -> 1207 | J36: =I36*H36 -> 168980 | K36: =55+272+40+234+40+234+57+275 -> 1207 | L36: =K36*H36 -> 168980 | M36: =L36-J36 -> 0 | N36: Toilets | S36: =L36/$D$22 -> 0.01747346
A37: 11 | B37: C23 | C37: =VLOOKUP($B37,'Rate card'!$A$4:$G280,2,FALSE) -> Civil | D37: Utility platfrom | E37: =VLOOKUP($B37,'Rate card'!$A$4:$G280,4,FALSE) -> Fully Modular Kitchen - Granite/Marble | F37: =VLOOKUP($B37,'Rate card'!$A$4:$G280,5,FALSE) -> Laying marble (18mm thk) of approved colour, shade and size on the platform as per drawing / flooring pattern, matching of grain, laid on a levelled, neat cement base with adhesive of approved make (laticrete) grouted of matching colour pigment to match the shade of stone and protection of floor to be taken into account.(cement concrete base taken into account in the civil works ) | G37: =VLOOKUP($B37,'Rate card'!$A$4:$G280,6,FALSE) -> Sqft | H37: 3000 | I37: 10 | J37: =I37*H37 -> 30000 | K37: 24 | L37: =K37*H37 -> 72000 | M37: =L37-J37 -> 42000 | N37: utility | O37: Qty ⬆️ | R37: =VLOOKUP($B37,'Rate card'!$A$4:$J280,7,FALSE) -> 150 | S37: =L37/$D$22 -> 0.0074451956
A38: 12 | B38: C15 | C38: =VLOOKUP($B38,'Rate card'!$A$4:$G280,2,FALSE) -> Civil | D38: =VLOOKUP($B38,'Rate card'!$A$4:$G280,3,FALSE) -> Granite frames | E38: =VLOOKUP($B38,'Rate card'!$A$4:$G280,4,FALSE) -> Single patti | F38: =VLOOKUP($B38,'Rate card'!$A$4:$G280,5,FALSE) -> Granite Frame – up to 6 Inches width {Including Bevelling+ Cutting+ Polishing}. Excludes Granite cost | G38: =VLOOKUP($B38,'Rate card'!$A$4:$G280,6,FALSE) -> Rft | H38: =VLOOKUP($B38,'Rate card'!$A$4:$J280,8,FALSE) -> 130 | I38: =20*4 -> 80 | J38: =H38*I38 -> 10400 | K38: 150 | L38: =K38*H38 -> 19500 | M38: =L38-J38 -> 9100 | N38: kitchen & Toilets | O38: Scope removed | Q38: =VLOOKUP($B38,'Rate card'!$A$4:$J280,7,FALSE) -> 80 | R38: =I38*Q38 -> 6400 | S38: =L38/$D$22 -> 0.0020164071
A39: 13 | B39: C45 | C39: =VLOOKUP($B39,'Rate card'!$A$4:$G280,2,FALSE) -> Civil | D39: =VLOOKUP($B39,'Rate card'!$A$4:$G280,3,FALSE) -> Vanity counter | E39: =VLOOKUP($B39,'Rate card'!$A$4:$G280,4,FALSE) -> Granite/Marble | F39: =VLOOKUP($B39,'Rate card'!$A$4:$G280,5,FALSE) -> Laying marble (18mm thk) of approved colour, shade and size on the platform as per drawing / flooring pattern, matching of grain, laid on a levelled, neat cement base with adhesive of approved make (laticrete) grouted of matching colour pigment to match the shade of stone and protection of floor to be taken into account.(cement concrete base taken into account in the civil works ) | G39: =VLOOKUP($B39,'Rate card'!$A$4:$G280,6,FALSE) -> Rft | H39: =VLOOKUP($B39,'Rate card'!$A$4:$J280,8,FALSE) -> 1500 | I39: 22 | J39: =H39*I39 -> 33000 | K39: 22 | L39: =K39*H39 -> 33000 | M39: =L39-J39 -> 0 | N39: Toilets | Q39: =VLOOKUP($B39,'Rate card'!$A$4:$J280,7,FALSE) -> 1000 | R39: =I39*Q39 -> 22000 | S39: =L39/$D$22 -> 0.0034123813
A40: 14 | C40: Tiles behind Wardrobe | G40: sqft | H40: 50 | I40: =I94+I97+I109+I122+I133 -> 327.5 | J40: =(H40*I40) -> 16375 | K40: 400 | L40: =K40*H40 -> 20000 | M40: =L40-J40 -> 3625 | N40: Behind wardrobe | O40: Qty ⬆️ | S40: =L40/$D$22 -> 0.0020681099
A41: 15 | L41: =K41*H41 -> 0 | M41: =L41-J41 -> 0 | S41: =L41/$D$22 -> 0
A42: 13 | B42: C45 | C42: =VLOOKUP($B42,'Rate card'!$A$4:$G280,2,FALSE) -> Civil | D42: Ledge | E42: =VLOOKUP($B42,'Rate card'!$A$4:$G280,4,FALSE) -> Granite/Marble | F42: =VLOOKUP($B42,'Rate card'!$A$4:$G280,5,FALSE) -> Laying marble (18mm thk) of approved colour, shade and size on the platform as per drawing / flooring pattern, matching of grain, laid on a levelled, neat cement base with adhesive of approved make (laticrete) grouted of matching colour pigment to match the shade of stone and protection of floor to be taken into account.(cement concrete base taken into account in the civil works ) | G42: =VLOOKUP($B42,'Rate card'!$A$4:$G280,6,FALSE) -> Rft | H42: =VLOOKUP($B42,'Rate card'!$A$4:$J280,8,FALSE) -> 1500 | I42: 20 | J42: =H42*I42 -> 30000 | K42: 15 | L42: =K42*H42 -> 22500 | M42: =L42-J42 -> -7500 | N42: Toilets | O42: Qty ⬇️ | Q42: =VLOOKUP($B42,'Rate card'!$A$4:$J280,7,FALSE) -> 1000 | R42: =I42*Q42 -> 20000 | S42: =L42/$D$22 -> 0.0023266236
I43: Total | J43: =SUM(J27:J42) -> 684205 | K43: Total | L43: =SUM(L27:L42) -> 845895 | M43: =sum(M27:M42) -> 161690
A44: Plumbing | S44: =L44/$D$22 -> 0
A45: 1 | B45: PL 2 | C45: Plumbing | D45: Bathroom Plumbing | E45: CP fitting work 1 Basin +cp fittings+Ceiling shower | F45: cp fiting and sanitary ware fixing in a bathroom | G45: per bathroom | H45: 35000 | I45: 1 | J45: =H45*I45 -> 35000 | K45: 1 | L45: =K45*H45 -> 35000 | M45: =L45-J45 -> 0 | N45: Samar's toilet | O45: Scope changed | P45: Tap overhead shower wc body jets Diverter | Q45: =VLOOKUP($B45,'Rate card'!$A$4:$J280,7,FALSE) -> 8000 | R45: =I45*Q45 -> 8000 | S45: =L45/$D$22 -> 0.0036191923
A46: 2 | B46: PL 2 | C46: Plumbing | D46: Bathroom Plumbing | E46: Ceiling shower+body jets+c.p fittings | F46: cp fiting and sanitary ware fixing in a bathroom | G46: per bathroom | H46: 45000 | I46: 1 | J46: =H46*I46 -> 45000 | K46: 2 | L46: 90000 | M46: =L46-J46 -> 45000 | N46: Master & Ranbeer | O46: Scope changed | P46: Tap overhead shower wc body jets Diverter | Q46: =VLOOKUP($B46,'Rate card'!$A$4:$J280,7,FALSE) -> 8000 | R46: =I46*Q46 -> 8000 | S46: =L46/$D$22 -> 0.0093064945
A47: 3 | B47: PL 2 | C47: Plumbing | D47: Bathroom Plumbing | E47: CP fitting work 1 Basin +cp fittings+Ceiling shower | F47: cp fiting and sanitary ware fixing in a bathroom | G47: per bathroom | H47: 35000 | I47: 1 | J47: =J45 -> 35000 | K47: 1 | L47: 35000 | M47: =L47-J47 -> 0 | N47: Mother's toilet | P47: Normal shower Diverter | Q47: =VLOOKUP($B47,'Rate card'!$A$4:$J280,7,FALSE) -> 8000 | R47: =I47*Q47 -> 8000 | S47: =L47/$D$22 -> 0.0036191923
A48: 4 | B48: PL 3 | C48: =VLOOKUP($B48,'Rate card'!$A$4:$G280,2,FALSE) -> Plumbing | D48: =VLOOKUP($B48,'Rate card'!$A$4:$G280,3,FALSE) -> Kitchen Plumbing | E48: 3 sink+dishwahser+washing machine | F48: =VLOOKUP($B48,'Rate card'!$A$4:$G280,5,FALSE) -> all plumbing concealed wall and floor CPVC and UPVC pipes and chipping and replastering work | G48: =VLOOKUP($B48,'Rate card'!$A$4:$G280,6,FALSE) -> per kitchen | H48: 25000 | I48: 1 | J48: =H48*I48 -> 25000 | K48: 1 | L48: =K48*H48 -> 25000 | M48: =L48-J48 -> 0 | N48: Kitchen & Utility | P48: Dryer Dishwasher two sink | Q48: =VLOOKUP($B48,'Rate card'!$A$4:$J280,7,FALSE) -> 5500 | R48: =I48*Q48 -> 5500 | S48: =L48/$D$22 -> 0.0025851374
I49: Total | J49: =SUM(J45:J48) -> 140000 | K49: Total | L49: =SUM(L45:L48) -> 185000 | M49: =sum(M45:M48) -> 45000
A50: Electrical | S50: =L50/$D$22 -> 0
A51: 1 | B51: E 1 | C51: Electrical | D51: 5A Switch socket, Light points,AC point, Fan point, Circuit wiring, DB Dressing | E51: new 5A Switch & Socket, light points, 15A, AC point, fan point from DB on wall include the price for wire and conduits, chipping and replastering on wall is included | F51: NOTE - The rates include fixingof switch / socket in position, effecting proper connections testing and commissioning of lighting fixtures and fans including lamps, control gear, power factor improvement capacitor and all fixing accessories that may be required to check. | G51: All areas | H51: 350 | I51: 1673 | J51: =H51*I51 -> 585550 | K51: 1673 | L51: =K51*H51 -> 585550 | M51: =L51-J51 -> 0 | N51: All areas | Q51: =VLOOKUP($B51,'Rate card'!$A$4:$J280,7,FALSE) -> 625 | R51: =I51*Q51 -> 1045625 | S51: =L51/$D$22 -> 0.060549087
I52: Total | J52: =SUM(J51) -> 585550 | K52: Total | L52: =SUM(L51) -> 585550
A53: Pop/Falsceiling | S53: =L53/$D$22 -> 0
A54: 1 | B54: FC 3 | C54: =VLOOKUP($B54,'Rate card'!$A$4:$G280,2,FALSE) -> False Ceiling | D54: =VLOOKUP($B54,'Rate card'!$A$4:$G280,3,FALSE) -> Gypsum Board Ceiling | E54: =VLOOKUP($B54,'Rate card'!$A$4:$G280,4,FALSE) -> Saint Gobain/Gyproc Board + local A Grade channel | F54: =VLOOKUP($B54,'Rate card'!$A$4:$G280,5,FALSE) -> 12.5mm thick gypsum board, with local A Grade Channel including all material, labour, transportation etc | Ceiling Channel and Intermediate Channel at 900mm c/c & Ceiling Section at 450mm c/c | G54: =VLOOKUP($B54,'Rate card'!$A$4:$G280,6,FALSE) -> Sqft | H54: 120 | I54: 1447 | J54: =H54*I54 -> 173640 | K54: 1447 | L54: =K54*H54 -> 173640 | M54: =L54-J54 -> 0 | N54: All areas | S54: =L54/$D$22 -> 0.01795533
A55: 2 | B55: FC 4 | C55: =VLOOKUP($B55,'Rate card'!$A$4:$G280,2,FALSE) -> False Ceiling | D55: =VLOOKUP($B55,'Rate card'!$A$4:$G280,3,FALSE) -> Gypsum Board Cove | E55: =VLOOKUP($B55,'Rate card'!$A$4:$G280,4,FALSE) -> Gypsum cove | F55: =VLOOKUP($B55,'Rate card'!$A$4:$G280,5,FALSE) -> 12.5mm thick gypsum board, with local A Grade Channel including all material, labour, transportation etc | Ceiling Channel and Intermediate Channel at 900mm c/c & Ceiling Section at 450mm c/c | G55: =VLOOKUP($B55,'Rate card'!$A$4:$G280,6,FALSE) -> Rft | H55: 120 | I55: 800 | J55: =H55*I55 -> 96000 | K55: 800 | L55: =K55*H55 -> 96000 | M55: =L55-J55 -> 0 | N55: All areas | S55: =L55/$D$22 -> 0.0099269275
A56: 3 | B56: FC 5 | C56: =VLOOKUP($B56,'Rate card'!$A$4:$G280,2,FALSE) -> False Ceiling | D56: =VLOOKUP($B56,'Rate card'!$A$4:$G280,3,FALSE) -> Hilux Board ceiling | E56: =VLOOKUP($B56,'Rate card'!$A$4:$G280,4,FALSE) -> Hilux Board + local A Grade channel | F56: =VLOOKUP($B56,'Rate card'!$A$4:$G280,5,FALSE) -> 8mm Ramco hilux board, with local A Grade Channel including all material, labour, transportation etc | Ceiling Channel and Intermediate Channel at 900mm c/c & Ceiling Section at 450mm c/c | G56: =VLOOKUP($B56,'Rate card'!$A$4:$G280,6,FALSE) -> Sqft | H56: 200 | I56: 226 | J56: =H56*I56 -> 45200 | K56: 226 | L56: =K56*H56 -> 45200 | M56: =L56-J56 -> 0 | N56: Toilets | Q56: =VLOOKUP($B56,'Rate card'!$A$4:$J280,7,FALSE) -> 120 | R56: =I56*Q56 -> 27120 | S56: =L56/$D$22 -> 0.0046739284
A57: 4 | B57: FC 11 | C57: =VLOOKUP($B57,'Rate card'!$A$4:$G280,2,FALSE) -> POP | D57: =VLOOKUP($B57,'Rate card'!$A$4:$G280,3,FALSE) -> POP Punning | E57: =VLOOKUP($B57,'Rate card'!$A$4:$G280,4,FALSE) -> POP Punning (Plum) 12-25mm thick | F57: =VLOOKUP($B57,'Rate card'!$A$4:$G280,5,FALSE) -> Providing and applying 12-25 mm thick POP punning on wall /ceiling including scrapping and hacking the existing finished surface and applying plaster of paris in proper line and levels etc. complete. | G57: =VLOOKUP($B57,'Rate card'!$A$4:$G280,6,FALSE) -> Sqft | H57: 45 | I57: 1000 | J57: =H57*I57 -> 45000 | K57: 1000 | L57: =K57*H57 -> 45000 | M57: =L57-J57 -> 0 | N57: Patch work wall punning | S57: =L57/$D$22 -> 0.0046532473
A58: 5 | B58: FC 12 | C58: =VLOOKUP($B58,'Rate card'!$A$4:$G280,2,FALSE) -> POP | D58: =VLOOKUP($B58,'Rate card'!$A$4:$G280,3,FALSE) -> POP Punning dhar | E58: =VLOOKUP($B58,'Rate card'!$A$4:$G280,4,FALSE) -> POP Punning (Plum) 12-25mm thick | F58: =VLOOKUP($B58,'Rate card'!$A$4:$G280,5,FALSE) -> Providing and applying 12-25 mm thick POP punning on wall /ceiling including scrapping and hacking the existing finished surface and applying plaster of paris in proper line and levels etc. complete. | G58: =VLOOKUP($B58,'Rate card'!$A$4:$G280,6,FALSE) -> Rft | H58: 25 | I58: 600 | J58: =H58*I58 -> 15000 | K58: 600 | L58: =K58*H58 -> 15000 | M58: =L58-J58 -> 0 | N58: Patch works and wall levelling purpose | S58: =L58/$D$22 -> 0.0015510824
A59: 6 | B59: FC 17 | C59: =VLOOKUP($B59,'Rate card'!$A$4:$G280,2,FALSE) -> False Ceiling | D59: =VLOOKUP($B59,'Rate card'!$A$4:$G280,3,FALSE) -> Light Gala cutting | E59: =VLOOKUP($B59,'Rate card'!$A$4:$G280,4,FALSE) -> NA | F59: =VLOOKUP($B59,'Rate card'!$A$4:$G280,5,FALSE) -> NA | G59: =VLOOKUP($B59,'Rate card'!$A$4:$G280,6,FALSE) -> Nos | H59: 100 | I59: 200 | J59: =H59*I59 -> 20000 | K59: 200 | L59: =K59*H59 -> 20000 | M59: =L58-J58 -> 0 | N59: All areas | S59: =L59/$D$22 -> 0.0020681099
I60: Total | J60: =SUM(J54:J59) -> 394840 | K60: Total | L60: =SUM(L54:L59) -> 394840 | M60: Total
A61: Carpentry | S61: =L61/$D$22 -> 0
A62: Living Room/Dining | S62: =L62/$D$22 -> 0
A63: 1 | B63: CP 111 | C63: =VLOOKUP($B63,'Rate card'!$A$4:$G280,2,FALSE) -> Carpentry | D63: Main Door | E63: Veneer Finish | F63: MR ply +both side Veneer finish | G63: =VLOOKUP($B63,'Rate card'!$A$4:$G280,6,FALSE) -> Nos | H63: 65000 | I63: 1 | J63: =H63*I63 -> 65000 | K63: 1 | L63: =K63*H63 -> 65000 | M63: =L63-J63 -> 0 | N63: New main door | P63: Refurbishment | S63: =L63/$D$22 -> 0.0067213571
A64: 2 | B64: CP 111 | C64: Carpentry | D64: Ply Door Frame | E64: Veneer Finish | F64: MR ply + finish veneer from both sides | G64: Rft | H64: 750 | I64: =4+9+9 -> 22 | J64: =H64*I64 -> 16500 | K64: =4+9+9 -> 22 | L64: =K64*H64 -> 16500 | M64: =L64-J64 -> 0 | N64: Door Frame | P64: Refurbishment | S64: =L64/$D$22 -> 0.0017061907
A65: 3 | B65: CP 1 | C65: Carpentry | D65: Panelling with framing | E65: Veneer Finish | F65: MR ply + ply framing + finish Veneer | G65: =VLOOKUP($B65,'Rate card'!$A$4:$G280,6,FALSE) -> Sqft | H65: 800 | I65: =7*3+9*2 -> 39 | J65: =H65*I65 -> 31200 | K65: 0 | L65: =K65*H65 -> 0 | M65: =L65-J65 -> -31200 | N65: safety door panelling | O65: Scope removed | Q65: =VLOOKUP($B65,'Rate card'!$A$4:$J280,7,FALSE) -> 450 | R65: =I65*Q65 -> 17550 | S65: =L65/$D$22 -> 0
A66: 4 | B66: CP 25 | C66: =VLOOKUP($B66,'Rate card'!$A$4:$G280,2,FALSE) -> Carpentry | D66: =VLOOKUP($B66,'Rate card'!$A$4:$G280,3,FALSE) -> Carcass Storage | E66: =VLOOKUP($B66,'Rate card'!$A$4:$G280,4,FALSE) -> Laminate Finish | F66: =VLOOKUP($B66,'Rate card'!$A$4:$G280,5,FALSE) -> MR ply + Inside laminate + finish laminate | G66: =VLOOKUP($B66,'Rate card'!$A$4:$G280,6,FALSE) -> Sqft | H66: 1800 | I66: =7.5*10 -> 75 | J66: =H66*I66 -> 135000 | K66: =4.75*7.5+2.75*10 -> 63.125 | L66: =K66*H66 -> 113625 | M66: =L66-J66 -> -21375 | N66: shoerack | Q66: =VLOOKUP($B66,'Rate card'!$A$4:$J280,7,FALSE) -> 1350 | R66: =I66*Q66 -> 101250 | S66: =L66/$D$22 -> 0.011749449
A67: 5 | B67: CP 6 | C67: Carpentry | D67: Panelling with framing | E67: Veneer Finish | F67: Mr Ply+ply framing+Finish Veneer + Onyx | G67: =VLOOKUP($B67,'Rate card'!$A$4:$G280,6,FALSE) -> Sqft | H67: 2000 | I67: 1 | J67: =H67*I67 -> 2000 | K67: =(9*9*2) -> 162 | L67: =K67*H67 -> 324000 | M67: =L67-J67 -> 322000 | N67: Panelling in Passage | O67: Scope changed | S67: =L67/$D$22 -> 0.03350338
C68: Carpentry | D68: Console | E68: Onyx | G68: LS | H68: 35000 | K68: 1 | L68: =K68*H68 -> 35000 | M68: =L68-J68 -> 35000 | S68: =L68/$D$22 -> 0.0036191923
A69: 6 | B69: CP 25 | C69: =VLOOKUP($B69,'Rate card'!$A$4:$G280,2,FALSE) -> Carpentry | D69: =VLOOKUP($B69,'Rate card'!$A$4:$G280,3,FALSE) -> Carcass Storage | E69: MDF Finish | F69: MR ply + Inside laminate + finish Veneer | G69: R ft | H69: 6000 | I69: 7.5 | J69: =H69*I69 -> 45000 | K69: 7.5 | L69: =K69*H69 -> 45000 | M69: =L69-J69 -> 0 | N69: TV unit | O69: Qty ⬇️ | Q69: =VLOOKUP($B69,'Rate card'!$A$4:$J280,7,FALSE) -> 1350 | R69: =I69*Q69 -> 10125 | S69: =L69/$D$22 -> 0.0046532473
A70: 7 | B70: CP 25 | C70: =VLOOKUP($B70,'Rate card'!$A$4:$G280,2,FALSE) -> Carpentry | D70: =VLOOKUP($B70,'Rate card'!$A$4:$G280,3,FALSE) -> Carcass Storage | E70: Veneer + Mirror + Tile | F70: MR ply + Inside laminate + finish Veneer | G70: =VLOOKUP($B70,'Rate card'!$A$4:$G280,6,FALSE) -> Sqft | H70: 1000 | I70: =7*8 -> 56 | J70: =H70*I70 -> 56000 | K70: =10.9*9.5 -> 103.55 | L70: =K70*H70 -> 103550 | M70: =L70-J70 -> 47550 | N70: TV panel | O70: Qty ⬆️ | Q70: =VLOOKUP($B70,'Rate card'!$A$4:$J280,7,FALSE) -> 1350 | R70: =I70*Q70 -> 75600 | S70: =L70/$D$22 -> 0.010707639
A71: 8 | B71: CP 25 | C71: =VLOOKUP($B71,'Rate card'!$A$4:$G280,2,FALSE) -> Carpentry | D71: =VLOOKUP($B71,'Rate card'!$A$4:$G280,3,FALSE) -> Carcass Storage | E71: =VLOOKUP($B71,'Rate card'!$A$4:$G280,4,FALSE) -> Laminate Finish | F71: =VLOOKUP($B71,'Rate card'!$A$4:$G280,5,FALSE) -> MR ply + Inside laminate + finish laminate | G71: =VLOOKUP($B71,'Rate card'!$A$4:$G280,6,FALSE) -> Sqft | H71: 3000 | I71: =4*7 -> 28 | J71: =H71*I71 -> 84000 | K71: 21 | L71: =K71*H71 -> 63000 | M71: =L71-J71 -> -21000 | N71: Mandir | Q71: =VLOOKUP($B71,'Rate card'!$A$4:$J280,7,FALSE) -> 1350 | R71: =I71*Q71 -> 37800 | S71: =L71/$D$22 -> 0.0065145462
A72: 9 | B72: CP 25 | C72: =VLOOKUP($B72,'Rate card'!$A$4:$G280,2,FALSE) -> Carpentry | D72: =VLOOKUP($B72,'Rate card'!$A$4:$G280,3,FALSE) -> Carcass Storage | E72: Veneer + Onyx Finish | F72: =F69 -> MR ply + Inside laminate + finish Veneer | G72: =VLOOKUP($B72,'Rate card'!$A$4:$G280,6,FALSE) -> Sqft | H72: 2500 | I72: =5*3.5 -> 17.5 | J72: =H72*I72 -> 43750 | K72: =5*3.5 -> 17.5 | L72: =K72*H72 -> 43750 | M72: =L72-J72 -> 0 | N72: Console | P72: Remove Onyx | Q72: =VLOOKUP($B72,'Rate card'!$A$4:$J280,7,FALSE) -> 1350 | R72: =I72*Q72 -> 23625 | S72: =L72/$D$22 -> 0.0045239904
A73: 10 | B73: CP 6 | C73: =VLOOKUP($B73,'Rate card'!$A$4:$G280,2,FALSE) -> Carpentry | D73: =VLOOKUP($B73,'Rate card'!$A$4:$G280,3,FALSE) -> Panelling with framing | E73: Gypsum | F73: Mr Ply+ply framing+ Gypsum | G73: =VLOOKUP($B73,'Rate card'!$A$4:$G280,6,FALSE) -> Sqft | H73: 600 | I73: =12*2.5 -> 30 | J73: =H73*I73 -> 18000 | K73: =12*2.5 -> 30 | L73: =K73*H73 -> 18000 | M73: =L73-J73 -> 0 | N73: Pelmet | S73: =L73/$D$22 -> 0.0018612989
A74: 11 | B74: CP 6 | C74: Carpentry | D74: Panelling with framing | E74: Texture Paint | F74: Mr Ply+ply framing+ Gypsum | G74: Sqft | H74: 600 | I74: 1 | J74: =H74*I74 -> 600 | K74: 120 | L74: =K74*H74 -> 72000 | M74: =L74-J74 -> 71400 | N74: Wall Panel on dinning wall | S74: =L74/$D$22 -> 0.0074451956
A75: 12 | B75: CP 6 | C75: Carpentry | D75: Panelling with framing | E75: CNC MDF + Veneer | F75: Mr Ply+ply framing+Finish Veneer + Onyx | G75: =VLOOKUP($B75,'Rate card'!$A$4:$G280,6,FALSE) -> Sqft | H75: 1500 | I75: =12*10 -> 120 | J75: =H75*I75 -> 180000 | K75: 108 | L75: =K75*H75 -> 162000 | M75: =L75-J75 -> -18000 | N75: Wall Panel on sofa wall | S75: =L75/$D$22 -> 0.01675169
A76: 13 | B76: CP 6 | C76: Carpentry | D76: Panelling with framing | E76: Veneer + Mirror + Tile | F76: MR ply + Inside laminate + finish Veneer | G76: =VLOOKUP($B76,'Rate card'!$A$4:$G280,6,FALSE) -> Sqft | H76: 1000 | I76: =29*10 -> 290 | J76: =H76*I76 -> 290000 | K76: 220 | L76: =K76*H76 -> 220000 | M76: =L76-J76 -> -70000 | N76: Panelling on mother's & samar's bed room wall | O76: Qty ⬇️ | S76: =L76/$D$22 -> 0.022749209
A77: 13 | B77: CP 6 | C77: Carpentry | D77: Panelling with framing | E77: Gypsum | F77: MR ply + Inside laminate + finish Gypsum | G77: =VLOOKUP($B77,'Rate card'!$A$4:$G280,6,FALSE) -> Sqft | H77: 600 | I77: =5*2.5 -> 12.5 | J77: =H77*I77 -> 7500 | K77: 0 | L77: =K77*H77 -> 0 | M77: =L77-J77 -> -7500 | N77: Ledge behind sofa | P77: Remove item | S77: =L77/$D$22 -> 0
A78: Modular Kitchen | S78: =L78/$D$22 -> 0
A79: 1 | B79: CP 25 | C79: =VLOOKUP($B79,'Rate card'!$A$4:$G280,2,FALSE) -> Carpentry | D79: =VLOOKUP($B79,'Rate card'!$A$4:$G280,3,FALSE) -> Carcass Storage | E79: Acrylic Finish | F79: Marine ply + Inside laminate + Acrylic Finish | G79: =VLOOKUP($B79,'Rate card'!$A$4:$G280,6,FALSE) -> Sqft | H79: 2700 | I79: =18.5*2.5 -> 46.25 | J79: =H79*I79 -> 124875 | K79: 50 | L79: =K79*H79 -> 135000 | M79: =L79-J79 -> 10125 | N79: undercounter | O79: Qty ⬇️ | S79: =L79/$D$22 -> 0.013959742
A80: 2 | B80: CP 25 | C80: =VLOOKUP($B80,'Rate card'!$A$4:$G280,2,FALSE) -> Carpentry | D80: =VLOOKUP($B80,'Rate card'!$A$4:$G280,3,FALSE) -> Carcass Storage | E80: Acrylic Finish | F80: Marine ply + Inside laminate + Acrylic Finish | G80: =VLOOKUP($B80,'Rate card'!$A$4:$G280,6,FALSE) -> Sqft | H80: 2700 | I80: =28+11.25*2.5+4*2.5 -> 66.125 | J80: =H80*I80 -> 178537.5 | K80: =25*4.5 -> 112.5 | L80: =K80*H80 -> 303750 | M80: =L80-J80 -> 125212.5 | N80: overhead+loft | O80: Qty ⬆️ | S80: =L80/$D$22 -> 0.031409419
A81: 3 | B81: CP 25 | C81: =VLOOKUP($B81,'Rate card'!$A$4:$G280,2,FALSE) -> Carpentry | D81: =VLOOKUP($B81,'Rate card'!$A$4:$G280,3,FALSE) -> Carcass Storage | E81: Acrylic Finish | F81: Marine ply + Inside laminate + Acrylic Finish | G81: =VLOOKUP($B81,'Rate card'!$A$4:$G280,6,FALSE) -> Sqft | H81: 2700 | I81: =4*10 -> 40 | J81: =H81*I81 -> 108000 | K81: 0 | L81: =K81*H81 -> 0 | M81: =L81-J81 -> -108000 | N81: Pantry Storage, next to fridge | O81: Qty ⬇️ | S81: =L81/$D$22 -> 0
A82: 4 | B82: CP 61 | C82: =VLOOKUP($B82,'Rate card'!$A$4:$G280,2,FALSE) -> Carpentry | D82: =VLOOKUP($B82,'Rate card'!$A$4:$G280,3,FALSE) -> Kitchen Basket | E82: tandem | F82: =VLOOKUP($B82,'Rate card'!$A$4:$G280,5,FALSE) -> Basket + Channel+Fitting charges | G82: =VLOOKUP($B82,'Rate card'!$A$4:$G280,6,FALSE) -> Nos | H82: 8000 | I82: 5 | J82: =H82*I82 -> 40000 | K82: 13 | L82: =K82*H82 -> 104000 | M82: =L82-J82 -> 64000 | N82: Modular kitchen | O82: Qty ⬆️ | S82: =L82/$D$22 -> 0.010754171
A83: 5 | B83: CP 64 | C83: =VLOOKUP($B83,'Rate card'!$A$4:$G280,2,FALSE) -> Carpentry | D83: =VLOOKUP($B83,'Rate card'!$A$4:$G280,3,FALSE) -> Wicker basket | E83: =VLOOKUP($B83,'Rate card'!$A$4:$G280,4,FALSE) -> Wicker basket | F83: =VLOOKUP($B83,'Rate card'!$A$4:$G280,5,FALSE) -> Basket + Channel+Fitting charges | G83: =VLOOKUP($B83,'Rate card'!$A$4:$G280,6,FALSE) -> Nos | H83: 6000 | I83: 2 | J83: =H83*I83 -> 12000 | K83: 2 | L83: =K83*H83 -> 12000 | M83: =L83-J83 -> 0 | N83: Modular kitchen | S83: =L83/$D$22 -> 0.0012408659
A84: 6 | C84: Carpentry | D84: Kitchen Sliding door | E84: Flutted glass finish | F84: Modular Kitchen | G84: Sqft | H84: 1650 | I84: =3*7 -> 21 | J84: =H84*I84 -> 34650 | K84: =3*7 -> 21 | L84: =K84*H84 -> 34650 | M84: =L84-J84 -> 0 | N84: kitchen | Q84: Scope added | S84: =L84/$D$22 -> 0.0035830004
A85: Utility | S85: =L85/$D$22 -> 0
A86: 1 | B86: CP 25 | C86: =VLOOKUP($B86,'Rate card'!$A$4:$G280,2,FALSE) -> Carpentry | D86: =VLOOKUP($B86,'Rate card'!$A$4:$G280,3,FALSE) -> Carcass Storage | E86: =VLOOKUP($B86,'Rate card'!$A$4:$G280,4,FALSE) -> Laminate Finish | F86: Marine ply + Inside laminate + finish laminate | G86: =VLOOKUP($B86,'Rate card'!$A$4:$G280,6,FALSE) -> Sqft | H86: 1800 | I86: =5.5*2.5 -> 13.75 | J86: =H86*I86 -> 24750 | K86: =8*2.5 -> 20 | L86: =K86*H86 -> 36000 | M86: =L86-J86 -> 11250 | N86: undercounter | O86: Qty ⬆️ | S86: =L86/$D$22 -> 0.0037225978
A87: 2 | B87: CP 25 | C87: =VLOOKUP($B87,'Rate card'!$A$4:$G280,2,FALSE) -> Carpentry | D87: =VLOOKUP($B87,'Rate card'!$A$4:$G280,3,FALSE) -> Carcass Storage | E87: =VLOOKUP($B87,'Rate card'!$A$4:$G280,4,FALSE) -> Laminate Finish | F87: Marine ply + Inside laminate + finish laminate | G87: =VLOOKUP($B87,'Rate card'!$A$4:$G280,6,FALSE) -> Sqft | H87: 1800 | I87: =10*10 -> 100 | J87: =H87*I87 -> 180000 | K87: 175 | L87: =K87*H87 -> 315000 | M87: =L87-J87 -> 135000 | N87: Storage | O87: Qty ⬆️ | S87: =L87/$D$22 -> 0.032572731
A88: 3 | B88: CP 117 | C88: =VLOOKUP($B88,'Rate card'!$A$4:$G280,2,FALSE) -> Carpentry | D88: =VLOOKUP($B88,'Rate card'!$A$4:$G280,3,FALSE) -> Carcass Storage | E88: =VLOOKUP($B88,'Rate card'!$A$4:$G280,4,FALSE) -> Laminate Finish | F88: Marine ply + Inside laminate + finish laminate | G88: =VLOOKUP($B88,'Rate card'!$A$4:$G280,6,FALSE) -> Sqft | H88: 1800 | I88: 22 | J88: =H88*I88 -> 39600 | K88: 0 | L88: =K88*H88 -> 0 | M88: =L88-J88 -> -39600 | N88: Washing machine storage | O88: Qty ⬇️ | Q88: =VLOOKUP($B88,'Rate card'!$A$4:$J280,7,FALSE) -> 2000 | R88: =I88*Q88 -> 44000 | S88: =L88/$D$22 -> 0
A89: Mother's Bedroom | S89: =L89/$D$22 -> 0
A90: 1 | B90: CP 21 | C90: =VLOOKUP($B90,'Rate card'!$A$4:$G280,2,FALSE) -> Carpentry | D90: =VLOOKUP($B90,'Rate card'!$A$4:$G280,3,FALSE) -> Bed | E90: =VLOOKUP($B90,'Rate card'!$A$4:$G280,4,FALSE) -> Laminate Finish | F90: MR ply panelling + Foam material and labour. Excludes Fabric cost | G90: =VLOOKUP($B90,'Rate card'!$A$4:$G280,6,FALSE) -> Sqft | H90: 1800 | I90: =5.5*6.5 -> 35.75 | J90: =H90*I90 -> 64350 | K90: =6.6*6 -> 39.6 | L90: =K90*H90 -> 71280 | M90: =L90-J90 -> 6930 | N90: king size bed | O90: Qty ⬆️ | Q90: =VLOOKUP($B90,'Rate card'!$A$4:$J280,7,FALSE) -> 1400 | R90: =I90*Q90 -> 50050 | S90: =L90/$D$22 -> 0.0073707436
A91: 2 | B91: CP 45 | C91: =VLOOKUP($B91,'Rate card'!$A$4:$G280,2,FALSE) -> Carpentry | D91: =VLOOKUP($B91,'Rate card'!$A$4:$G280,3,FALSE) -> Headboard | E91: =VLOOKUP($B91,'Rate card'!$A$4:$G280,4,FALSE) -> Fabric Finish | F91: =VLOOKUP($B91,'Rate card'!$A$4:$G280,5,FALSE) -> MR ply panelling + Foam material and labour. Excludes Fabric cost | G91: =VLOOKUP($B91,'Rate card'!$A$4:$G280,6,FALSE) -> Sqft | H91: 1300 | I91: =5.5*3 -> 16.5 | J91: =H91*I91 -> 21450 | K91: =9*2.8 -> 25.2 | L91: =K91*H91 -> 32760 | M91: =L91-J91 -> 11310 | N91: Headboard | O91: Qty ⬆️ | Q91: =VLOOKUP($B91,'Rate card'!$A$4:$J280,7,FALSE) -> 950 | R91: =I91*Q91 -> 15675 | S91: =L91/$D$22 -> 0.003387564
A92: 3 | B92: CP 46 | C92: =VLOOKUP($B92,'Rate card'!$A$4:$G280,2,FALSE) -> Carpentry | D92: Bed side table | E92: =VLOOKUP($B92,'Rate card'!$A$4:$G280,4,FALSE) -> Laminate Finish | F92: =VLOOKUP($B92,'Rate card'!$A$4:$G280,5,FALSE) -> MR ply + Inside laminate + finish laminate (1 Drawer) | G92: =VLOOKUP($B92,'Rate card'!$A$4:$G280,6,FALSE) -> Nos | H92: 20000 | I92: 2 | J92: =H92*I92 -> 40000 | K92: 2 | L92: =K92*H92 -> 40000 | M92: =L92-J92 -> 0 | N92: Bed side table | S92: =L92/$D$22 -> 0.0041362198
A93: 4 | B93: CP 25 | C93: =VLOOKUP($B93,'Rate card'!$A$4:$G280,2,FALSE) -> Carpentry | D93: =VLOOKUP($B93,'Rate card'!$A$4:$G280,3,FALSE) -> Carcass Storage | E93: =VLOOKUP($B93,'Rate card'!$A$4:$G280,4,FALSE) -> Laminate Finish | F93: =VLOOKUP($B93,'Rate card'!$A$4:$G280,5,FALSE) -> MR ply + Inside laminate + finish laminate | G93: Sqft | H93: 1800 | I93: 7 | J93: =H93*I93 -> 12600 | K93: 10 | L93: =K93*H93 -> 18000 | M93: =L93-J93 -> 5400 | N93: Dresser | Q93: =VLOOKUP($B93,'Rate card'!$A$4:$J280,7,FALSE) -> 1350 | R93: =I93*Q93 -> 9450 | S93: =L93/$D$22 -> 0.0018612989
A94: 5 | B94: CP 25 | C94: =VLOOKUP($B94,'Rate card'!$A$4:$G280,2,FALSE) -> Carpentry | D94: =VLOOKUP($B94,'Rate card'!$A$4:$G280,3,FALSE) -> Carcass Storage | E94: =VLOOKUP($B94,'Rate card'!$A$4:$G280,4,FALSE) -> Laminate Finish | F94: =VLOOKUP($B94,'Rate card'!$A$4:$G280,5,FALSE) -> MR ply + Inside laminate + finish laminate | G94: =VLOOKUP($B94,'Rate card'!$A$4:$G280,6,FALSE) -> Sqft | H94: =VLOOKUP($B94,'Rate card'!$A$4:$J280,8,FALSE) -> 1800 | I94: =5*10 -> 50 | J94: =H94*I94 -> 90000 | K94: =5*10 -> 50 | L94: =K94*H94 -> 90000 | M94: =L94-J94 -> 0 | N94: Wardrobe near entrance | S94: =L94/$D$22 -> 0.0093064945
A95: 6 | B95: CP 3 | C95: =VLOOKUP($B95,'Rate card'!$A$4:$G280,2,FALSE) -> Carpentry | D95: =VLOOKUP($B95,'Rate card'!$A$4:$G280,3,FALSE) -> Panelling with framing | E95: =VLOOKUP($B95,'Rate card'!$A$4:$G280,4,FALSE) -> Mirror Finish | F95: =VLOOKUP($B95,'Rate card'!$A$4:$G280,5,FALSE) -> MR ply + ply framing + 5mm clear mirror | G95: =VLOOKUP($B95,'Rate card'!$A$4:$G280,6,FALSE) -> Sqft | H95: =VLOOKUP($B95,'Rate card'!$A$4:$J280,8,FALSE) -> 750 | I95: =2.5*7 -> 17.5 | J95: =H95*I95 -> 13125 | K95: =2.5*7 -> 17.5 | L95: =K95*H95 -> 13125 | M95: =L95-J95 -> 0 | N95: Mirror | S95: =L95/$D$22 -> 0.0013571971
A96: 7 | B96: CP 1 | C96: Carpentry | D96: Panelling with framing | E96: =VLOOKUP($B96,'Rate card'!$A$4:$G280,4,FALSE) -> Laminate Finish | F96: MR ply + ply framing + finish laminate | G96: =VLOOKUP($B96,'Rate card'!$A$4:$G280,6,FALSE) -> Sqft | H96: 850 | I96: 80 | J96: =H96*I96 -> 68000 | K96: 80 | L96: =K96*H96 -> 68000 | M96: =L96-J96 -> 0 | N96: Wall panel | O96: Scope changed | P96: Changed to Veneer not sure how to add need to add t patti as well | S96: =L96/$D$22 -> 0.0070315736
A97: 8 | B97: CP 17 | C97: =VLOOKUP($B97,'Rate card'!$A$4:$G280,2,FALSE) -> Carpentry | D97: =VLOOKUP($B97,'Rate card'!$A$4:$G280,3,FALSE) -> Wardrobe | E97: =VLOOKUP($B97,'Rate card'!$A$4:$G280,4,FALSE) -> Laminate Finish | F97: =VLOOKUP($B97,'Rate card'!$A$4:$G280,5,FALSE) -> MR ply + Inside laminate + finish laminate. (Includes 4 pencil drawers, Handles of base rate Rs.1000/pc) | G97: =VLOOKUP($B97,'Rate card'!$A$4:$G280,6,FALSE) -> Sqft | H97: 1800 | I97: =7.5*10 -> 75 | J97: =H97*I97 -> 135000 | K97: 82 | L97: =K97*H97 -> 147600 | M97: =L97-J97 -> 12600 | N97: Wardrobe | O97: Qty ⬇️ | S97: =L97/$D$22 -> 0.015262651
A98: 9 | B98: CP 6 | C98: =VLOOKUP($B98,'Rate card'!$A$4:$G280,2,FALSE) -> Carpentry | D98: =VLOOKUP($B98,'Rate card'!$A$4:$G280,3,FALSE) -> Panelling with framing | E98: =VLOOKUP($B98,'Rate card'!$A$4:$G280,4,FALSE) -> MDF | F98: =VLOOKUP($B98,'Rate card'!$A$4:$G280,5,FALSE) -> MR ply + ply framing + 12mm MDF | G98: =VLOOKUP($B98,'Rate card'!$A$4:$G280,6,FALSE) -> Sqft | H98: 600 | I98: =12*2.5 -> 30 | J98: =H98*I98 -> 18000 | K98: =12*2.5 -> 30 | L98: =K98*H98 -> 18000 | M98: =L98-J98 -> 0 | N98: pelmet | S98: =L98/$D$22 -> 0.0018612989
A99: Samar's Bedroom | S99: =L99/$D$22 -> 0
A100: 1 | B100: CP 21 | C100: =VLOOKUP($B100,'Rate card'!$A$4:$G280,2,FALSE) -> Carpentry | D100: =VLOOKUP($B100,'Rate card'!$A$4:$G280,3,FALSE) -> Bed | E100: =VLOOKUP($B100,'Rate card'!$A$4:$G280,4,FALSE) -> Laminate Finish | F100: =VLOOKUP($B100,'Rate card'!$A$4:$G280,5,FALSE) -> MR ply + Inside laminate + finish laminate | G100: =VLOOKUP($B100,'Rate card'!$A$4:$G280,6,FALSE) -> Sqft | H100: 2200 | I100: =6*6.5 -> 39 | J100: =H100*I100 -> 85800 | K100: =6*6.5 -> 39 | L100: =K100*H100 -> 85800 | M100: =6*6.5 -> 39 | N100: King size Bed, 2 internal drawers+ 1 side box | Q100: =VLOOKUP($B100,'Rate card'!$A$4:$J280,7,FALSE) -> 1400 | R100: =I100*Q100 -> 54600 | S100: =L100/$D$22 -> 0.0088721914
A101: 2 | B101: CP 45 | C101: =VLOOKUP($B101,'Rate card'!$A$4:$G280,2,FALSE) -> Carpentry | D101: =VLOOKUP($B101,'Rate card'!$A$4:$G280,3,FALSE) -> Headboard | E101: =VLOOKUP($B101,'Rate card'!$A$4:$G280,4,FALSE) -> Fabric Finish | F101: =VLOOKUP($B101,'Rate card'!$A$4:$G280,5,FALSE) -> MR ply panelling + Foam material and labour. Excludes Fabric cost | G101: =VLOOKUP($B101,'Rate card'!$A$4:$G280,6,FALSE) -> Sqft | H101: 1300 | I101: =6*3.5 -> 21 | J101: =H101*I101 -> 27300 | K101: =6*3.5 -> 21 | L101: =K101*H101 -> 27300 | M101: =6*3.5 -> 21 | N101: Headboard | Q101: =VLOOKUP($B101,'Rate card'!$A$4:$J280,7,FALSE) -> 950 | R101: =I101*Q101 -> 19950 | S101: =L101/$D$22 -> 0.00282297
A102: 3 | B102: CP 46 | C102: =VLOOKUP($B102,'Rate card'!$A$4:$G280,2,FALSE) -> Carpentry | D102: Bed side table | E102: =VLOOKUP($B102,'Rate card'!$A$4:$G280,4,FALSE) -> Laminate Finish | F102: =VLOOKUP($B102,'Rate card'!$A$4:$G280,5,FALSE) -> MR ply + Inside laminate + finish laminate (1 Drawer) | G102: =VLOOKUP($B102,'Rate card'!$A$4:$G280,6,FALSE) -> Nos | H102: 20000 | I102: 1 | J102: =H102*I102 -> 20000 | K102: 1 | L102: =K102*H102 -> 20000 | M102: 1 | N102: Bed side table | S102: =L102/$D$22 -> 0.0020681099
A103: 4 | B103: CP 49 | C103: =VLOOKUP($B103,'Rate card'!$A$4:$G280,2,FALSE) -> Carpentry | D103: =VLOOKUP($B103,'Rate card'!$A$4:$G280,3,FALSE) -> Study Table | E103: =VLOOKUP($B103,'Rate card'!$A$4:$G280,4,FALSE) -> Laminate Finish | F103: =VLOOKUP($B103,'Rate card'!$A$4:$G280,5,FALSE) -> MR ply + Inside laminate + finish laminate (2 pencil drawers) | G103: =VLOOKUP($B103,'Rate card'!$A$4:$G280,6,FALSE) -> Rft | H103: 4500 | I103: 4 | J103: =H103*I103 -> 18000 | K103: 5 | L103: =K103*H103 -> 22500 | M103: 4 | N103: Study table | S103: =L103/$D$22 -> 0.0023266236
A104: 5 | B104: CP 25 | C104: =VLOOKUP($B104,'Rate card'!$A$4:$G280,2,FALSE) -> Carpentry | D104: =VLOOKUP($B104,'Rate card'!$A$4:$G280,3,FALSE) -> Carcass Storage | E104: =VLOOKUP($B104,'Rate card'!$A$4:$G280,4,FALSE) -> Laminate Finish | F104: =VLOOKUP($B104,'Rate card'!$A$4:$G280,5,FALSE) -> MR ply + Inside laminate + finish laminate | G104: =VLOOKUP($B104,'Rate card'!$A$4:$G280,6,FALSE) -> Sqft | H104: =VLOOKUP($B104,'Rate card'!$A$4:$J280,8,FALSE) -> 1800 | I104: 20 | J104: =H104*I104 -> 36000 | K104: 28 | L104: =K104*H104 -> 50400 | M104: 20 | N104: Overhead storage | S104: =L104/$D$22 -> 0.0052116369
A105: 6 | B105: CP 25 | C105: =VLOOKUP($B105,'Rate card'!$A$4:$G280,2,FALSE) -> Carpentry | D105: =VLOOKUP($B105,'Rate card'!$A$4:$G280,3,FALSE) -> Carcass Storage | E105: =VLOOKUP($B105,'Rate card'!$A$4:$G280,4,FALSE) -> Laminate Finish | F105: =VLOOKUP($B105,'Rate card'!$A$4:$G280,5,FALSE) -> MR ply + Inside laminate + finish laminate | G105: =VLOOKUP($B105,'Rate card'!$A$4:$G280,6,FALSE) -> Sqft | H105: =VLOOKUP($B105,'Rate card'!$A$4:$J280,8,FALSE) -> 1800 | I105: 18 | J105: =H105*I105 -> 32400 | K105: 45 | L105: =K105*H105 -> 81000 | M105: 18 | N105: Bookshelf | S105: =L105/$D$22 -> 0.0083758451
A106: 7 | B106: CP 3 | C106: =VLOOKUP($B106,'Rate card'!$A$4:$G280,2,FALSE) -> Carpentry | D106: =VLOOKUP($B106,'Rate card'!$A$4:$G280,3,FALSE) -> Panelling with framing | E106: =VLOOKUP($B106,'Rate card'!$A$4:$G280,4,FALSE) -> Mirror Finish | F106: =VLOOKUP($B106,'Rate card'!$A$4:$G280,5,FALSE) -> MR ply + ply framing + 5mm clear mirror | G106: =VLOOKUP($B106,'Rate card'!$A$4:$G280,6,FALSE) -> Sqft | H106: =VLOOKUP($B106,'Rate card'!$A$4:$J280,8,FALSE) -> 750 | I106: =2*5 -> 10 | J106: =H106*I106 -> 7500 | K106: =2*5 -> 10 | L106: =K106*H106 -> 7500 | M106: =2*5 -> 10 | N106: Mirror | S106: =L106/$D$22 -> 0.00077554121
...

Sheet RAMDIN - WO
A5: Date : | B5: 45999 | E5: Project Code :
A6: Client Name : | B6: Rahul Dhanawat | E6: WO-1 | F6: RAMDIN
A7: Address : | B7: 10BKC | E7: Elemantra Contact Person : | F7: Payal- 93724 07848
A8: Sr.No | B8: Id | C8: Item Name | D8: Category | E8: Item Details | F8: Description | G8: UOM | H8: Elemantra Rates | I8: RAMDIN RATES | J8: Quantity 14.03.2025 | K8: Amount | L8: Area | M8: RAMDIN AMOUNT | N8: Amount | O8: Location | P8: Remark
A9: Living Room/Dining
A10: 1 | B10: CP 111 | C10: =VLOOKUP($B10,'Rate card'!$A$4:$G1005,2,FALSE) -> Carpentry | D10: Main Door | E10: Veneer Finish | F10: MR ply +both side Veneer finish | G10: =VLOOKUP($B10,'Rate card'!$A$4:$G1005,6,FALSE) -> Nos | H10: 65000 | I10: 550 | J10: 1 | K10: =H10*J10 -> 65000 | L10: 1 | N10: =L10*H10 -> 65000 | O10: New main door
A11: 2 | B11: CP 111 | C11: Carpentry | D11: Ply Door Frame | E11: Veneer Finish | F11: MR ply + finish veneer from both sides | G11: Rft | H11: 750 | I11: 375 | J11: =4+9+9 -> 22 | K11: =H11*J11 -> 16500 | L11: 22 | N11: =L11*H11 -> 16500 | O11: Door Frame
A12: 3 | C12: Carpentry | D12: Panelling with mirror | E12: Mirror Finish | G12: Sqft | H12: 650 | I12: 350 | L12: =6*8.5 -> 51 | N12: =L12*H12 -> 33150 | O12: mirror panel
A13: 4 | B13: CP 6 | C13: Carpentry | D13: Panelling with framing | E13: Veneer Finish | F13: Mr Ply+ply framing+Finish Veneer + Onyx | G13: =VLOOKUP($B13,'Rate card'!$A$4:$G1005,6,FALSE) -> Sqft | H13: 1800 | I13: 400 | J13: 1 | K13: =H13*J13 -> 1800 | L13: =22*8.5 -> 187 | N13: =L13*H13 -> 336600 | O13: Panelling in Passage including shoe room door
A14: 5 | B14: CP 6 | C14: Carpentry | D14: Panelling with framing | E14: CNC MDF + Veneer | F14: Mr Ply+ply framing+Finish Veneer + Onyx | G14: =VLOOKUP($B14,'Rate card'!$A$4:$G1005,6,FALSE) -> Sqft | H14: 1500 | I14: 400 | J14: =12*10 -> 120 | K14: =H14*J14 -> 180000 | L14: =12.5*8.5 -> 106.25 | N14: =L14*H14 -> 159375 | O14: Wall Panel on sofa wall | P14: incluing master bedroom door and 3d panel
A15: 6 | B15: CP 6 | C15: Carpentry | D15: Panelling with framing | E15: Veneer + Mirror + Marble | F15: MR ply + Inside laminate + finish Veneer | G15: =VLOOKUP($B15,'Rate card'!$A$4:$G1005,6,FALSE) -> Sqft | H15: 1800 | I15: 400 | J15: =29*10 -> 290 | K15: =H15*J15 -> 522000 | L15: =34*8.5 -> 289 | N15: =L15*H15 -> 520200 | O15: Panelling on mother's & samar's bed room wall
A16: 7 | B16: CP 6 | C16: Carpentry | D16: Panelling with framing | E16: Mirror Finish | F16: Mr Ply+ply framing+Finish Veneer + Onyx | G16: =VLOOKUP($B16,'Rate card'!$A$4:$G1005,6,FALSE) -> Sqft | H16: 850 | I16: 350 | J16: =12*10 -> 120 | K16: =H16*J16 -> 102000 | L16: =5*8.5 -> 42.5 | N16: =L16*H16 -> 36125 | O16: mirror panel on dining wall | P16: brown mirror
A17: 8 | C17: Carpentry | N17: 45000
A18: Mother's Bedroom
A19: 1 | B19: CP 3 | C19: =VLOOKUP($B19,'Rate card'!$A$4:$G1005,2,FALSE) -> Carpentry | D19: =VLOOKUP($B19,'Rate card'!$A$4:$G1005,3,FALSE) -> Panelling with framing | E19: =VLOOKUP($B19,'Rate card'!$A$4:$G1005,4,FALSE) -> Mirror Finish | F19: =VLOOKUP($B19,'Rate card'!$A$4:$G1005,5,FALSE) -> MR ply + ply framing + 5mm clear mirror | G19: =VLOOKUP($B19,'Rate card'!$A$4:$G1005,6,FALSE) -> Sqft | H19: =VLOOKUP($B19,'Rate card'!$A$4:$J1005,8,FALSE) -> 750 | I19: 350 | J19: =2.5*7 -> 17.5 | K19: =H19*J19 -> 13125 | L19: =7*2 -> 14 | N19: =L19*H19 -> 10500 | O19: Mirror
A20: 2 | B20: CP 1 | C20: Carpentry | D20: Panelling with framing | E20: =VLOOKUP($B20,'Rate card'!$A$4:$G1005,4,FALSE) -> Laminate Finish | F20: MR ply + ply framing + finish laminate | G20: =VLOOKUP($B20,'Rate card'!$A$4:$G1005,6,FALSE) -> Sqft | H20: 950 | I20: 325 | J20: 80 | K20: =H20*J20 -> 76000 | L20: =9*5 -> 45 | N20: =L20*H20 -> 42750 | O20: Wall panel | P20: including rafters nad charcol sheet
A21: 3 | B21: CP 6 | C21: =VLOOKUP($B21,'Rate card'!$A$4:$G1005,2,FALSE) -> Carpentry | D21: =VLOOKUP($B21,'Rate card'!$A$4:$G1005,3,FALSE) -> Panelling with framing | E21: =VLOOKUP($B21,'Rate card'!$A$4:$G1005,4,FALSE) -> MDF | F21: =VLOOKUP($B21,'Rate card'!$A$4:$G1005,5,FALSE) -> MR ply + ply framing + 12mm MDF | G21: =VLOOKUP($B21,'Rate card'!$A$4:$G1005,6,FALSE) -> Sqft | H21: 600 | I21: 325 | J21: =12*2.5 -> 30 | K21: =H21*J21 -> 18000 | L21: =10*2 -> 20 | N21: =L21*H21 -> 12000 | O21: pelmet
A22: Samar's Bedroom
A23: 1 | B23: CP 3 | C23: =VLOOKUP($B23,'Rate card'!$A$4:$G1005,2,FALSE) -> Carpentry | D23: =VLOOKUP($B23,'Rate card'!$A$4:$G1005,3,FALSE) -> Panelling with framing | E23: =VLOOKUP($B23,'Rate card'!$A$4:$G1005,4,FALSE) -> Mirror Finish | F23: =VLOOKUP($B23,'Rate card'!$A$4:$G1005,5,FALSE) -> MR ply + ply framing + 5mm clear mirror | G23: =VLOOKUP($B23,'Rate card'!$A$4:$G1005,6,FALSE) -> Sqft | H23: =VLOOKUP($B23,'Rate card'!$A$4:$J1005,8,FALSE) -> 750 | I23: 350 | J23: =2*5 -> 10 | K23: =H23*J23 -> 7500 | L23: =3*3 -> 9 | N23: =L23*H23 -> 6750 | O23: Mirror
A24: 2 | B24: CP 1 | C24: Carpentry | D24: Panelling with framing | E24: =VLOOKUP($B24,'Rate card'!$A$4:$G1005,4,FALSE) -> Laminate Finish | F24: MR ply + ply framing + finish laminate | G24: =VLOOKUP($B24,'Rate card'!$A$4:$G1005,6,FALSE) -> Sqft | H24: =VLOOKUP($B24,'Rate card'!$A$4:$J1005,8,FALSE) -> 650 | I24: 325 | J24: 40 | K24: =H24*J24 -> 26000 | L24: 0 | N24: =L24*H24 -> 0 | O24: Wall panel
A25: 3 | B25: CP 6 | C25: =VLOOKUP($B25,'Rate card'!$A$4:$G1005,2,FALSE) -> Carpentry | D25: =VLOOKUP($B25,'Rate card'!$A$4:$G1005,3,FALSE) -> Panelling with framing | E25: =VLOOKUP($B25,'Rate card'!$A$4:$G1005,4,FALSE) -> MDF | F25: =VLOOKUP($B25,'Rate card'!$A$4:$G1005,5,FALSE) -> MR ply + ply framing + 12mm MDF | G25: =VLOOKUP($B25,'Rate card'!$A$4:$G1005,6,FALSE) -> Sqft | H25: 600 | I25: 325 | J25: =12*2.5 -> 30 | K25: =H25*J25 -> 18000 | L25: =10*2 -> 20 | N25: =L25*H25 -> 12000 | O25: pelmet
A26: Ranbeer's Bedroom
A27: 1 | B27: CP 6 | C27: =VLOOKUP($B27,'Rate card'!$A$4:$G1005,2,FALSE) -> Carpentry | D27: =VLOOKUP($B27,'Rate card'!$A$4:$G1005,3,FALSE) -> Panelling with framing | E27: Laminate Finish | F27: =VLOOKUP($B27,'Rate card'!$A$4:$G1005,5,FALSE) -> MR ply + ply framing + 12mm MDF | G27: =VLOOKUP($B27,'Rate card'!$A$4:$G1005,6,FALSE) -> Sqft | H27: 850 | I27: 325 | J27: =12*2.5 -> 30 | K27: =H27*J27 -> 25500 | L27: =12*9 -> 108 | N27: =L27*H27 -> 91800 | O27: tv panel
A28: 2 | B28: CP 3 | C28: =VLOOKUP($B28,'Rate card'!$A$4:$G1005,2,FALSE) -> Carpentry | D28: =VLOOKUP($B28,'Rate card'!$A$4:$G1005,3,FALSE) -> Panelling with framing | E28: =VLOOKUP($B28,'Rate card'!$A$4:$G1005,4,FALSE) -> Mirror Finish | F28: =VLOOKUP($B28,'Rate card'!$A$4:$G1005,5,FALSE) -> MR ply + ply framing + 5mm clear mirror | G28: =VLOOKUP($B28,'Rate card'!$A$4:$G1005,6,FALSE) -> Sqft | H28: =VLOOKUP($B28,'Rate card'!$A$4:$J1005,8,FALSE) -> 750 | I28: 350 | J28: =2.5*10 -> 25 | K28: =H28*J28 -> 18750 | L28: =2.5*9 -> 22.5 | N28: =L28*H28 -> 16875 | O28: Mirror
A29: 3 | B29: CP 1 | C29: Carpentry | D29: Panelling with framing | E29: =VLOOKUP($B29,'Rate card'!$A$4:$G1005,4,FALSE) -> Laminate Finish | F29: MR ply + ply framing + finish laminate | G29: =VLOOKUP($B29,'Rate card'!$A$4:$G1005,6,FALSE) -> Sqft | H29: 1500 | I29: 325 | J29: 90 | K29: =H29*J29 -> 135000 | L29: =9*9 -> 81 | N29: =L29*H29 -> 121500 | O29: Wall panel
A30: 4 | B30: CP 6 | C30: =VLOOKUP($B30,'Rate card'!$A$4:$G1005,2,FALSE) -> Carpentry | D30: =VLOOKUP($B30,'Rate card'!$A$4:$G1005,3,FALSE) -> Panelling with framing | E30: =VLOOKUP($B30,'Rate card'!$A$4:$G1005,4,FALSE) -> MDF | F30: =VLOOKUP($B30,'Rate card'!$A$4:$G1005,5,FALSE) -> MR ply + ply framing + 12mm MDF | G30: =VLOOKUP($B30,'Rate card'!$A$4:$G1005,6,FALSE) -> Sqft | H30: 600 | I30: 325 | J30: =11*2.5 -> 27.5 | K30: =H30*J30 -> 16500 | L30: =10*2 -> 20 | N30: =L30*H30 -> 12000 | O30: pelmet
A31: Master bed room
